Workbook

Sheet List Deskripsi RO SAP
B3: RO Code | C3: RO DESCRIPTION | D3: SEGMENT CODE | E3: SEGMENT
B4: 140 | C4: MICRO SALES MANAGEMENT DIVISION | D4: M | E4: MICRO
B5: 130 | C5: ULTRA MICRO BUSINESS DIVISION | D5: M | E5: MICRO
B6: 350 | C6: SMALL BUSINESS GROUP (SMALL) | D6: S | E6: SMALL
B7: 360 | C7: COMMERCIAL BUSINESS GROUP | D7: R | E7: COMMERCIAL
B8: 380 | C8: SMALL BUSINESS GROUP (MEDIUM) | D8: D | E8: MEDIUM
B9: 430 | C9: SMALL & MEDIUM SALES MANAGEMENT 2 DIVISION | D9: D | E9: MEDIUM
B10: 280 | C10: TRANSACTION BANKING DIVISION | D10: W | E10: WHOLESALE
B11: 470 | C11: SYNDICATION & FINANCIAL INSTITUTION NON BANK GROUP | D11: K | E11: CORPORATE
B12: 740 | C12: MANUFACTURING, INFRASTRUCTURE, TRANSPORTATION, OIL & GAS GROUP | D12: K | E12: CORPORATE
B13: 750 | C13: INSTITUTIONAL BUSINESS GROUP | D13: K | E13: CORPORATE
B14: 780 | C14: ENERGY & MINING GROUP | D14: K | E14: CORPORATE
B15: 260 | C15: CONSUMER SALES MANAGEMENT 1 | D15: C | E15: CONSUMER
... B24: 390 | C24: FUNDING & RETAIL PAYMENT SALES MANAGEMENT 2 | D24: N | E24: NETWORK & SERVICES

Sheet List FKSEGMEN 20250630
A1: FKSEGMEN | B1: Cek BRD | C1: KET | D1: BIS_OWNER | E1: KET_PRODUK7 | F1: DESKRIPSI | G1: PRODUK_BARU | H1: PRODUK_NEW
A2: 10000 | B2: =VLOOKUP(A2,[1]BRD!A:A,1,0) -> #N/A | C2: Mikro | D2: 5. MIKRO | E2: Kupedes | F2: KREDIT MIKRO | G2: Kupedes | H2: Kupedes
A3: 11000 | B3: =VLOOKUP(A3,[1]BRD!A:A,1,0) -> #N/A | C3: Mikro | D3: 5. MIKRO | E3: Kupedes | F3: KREDIT MIKRO - KOMERSIAL | G3: Kupedes | H3: Kupedes
A4: 11100 | B4: =VLOOKUP(A4,[1]BRD!A:A,1,0) -> #N/A | C4: Mikro | D4: 5. MIKRO | E4: Kupedes | F4: Kupedes | G4: Kupedes | H4: Kupedes
A5: 11200 | B5: =VLOOKUP(A5,[1]BRD!A:A,1,0) -> #N/A | C5: Mikro | D5: 5. MIKRO | E5: KUR Kupedes | F5: KUR Mikro | G5: KUR Kupedes | H5: KUR Kupedes
A6: 11300 | B6: =VLOOKUP(A6,[1]BRD!A:A,1,0) -> #N/A | C6: Mikro | D6: 5. MIKRO | E6: Kupedes Rakyat | F6: Kupedes Rakyat | G6: Kupedes Rakyat | H6: Kupedes Rakyat
A7: 11400 | B7: =VLOOKUP(A7,[1]BRD!A:A,1,0) -> #N/A | C7: Mikro | D7: 5. MIKRO | E7: KUR Kupedes Baru | F7: KUR Mikro Baru | G7: KUR Kupedes Baru | H7: KUR Mikro Baru
A8: 11900 | B8: =VLOOKUP(A8,[1]BRD!A:A,1,0) -> #N/A | C8: Mikro | D8: 5. MIKRO | E8: KUR Ritel Di BRI Unit | F8: KUR Ritel Di BRI Unit | G8: KUR Ritel Di BRI Unit | H8: KUR Ritel Di BRI Unit
A9: 12000 | B9: =VLOOKUP(A9,[1]BRD!A:A,1,0) -> #N/A | C9: Mikro | D9: 5. MIKRO | E9: Kupedes GBT | F9: KREDIT MIKRO - GBT | G9: Kupedes GBT-Kretap | H9: Kupedes Briguna
A10: 20000 | B10: =VLOOKUP(A10,[1]BRD!A:A,1,0) -> 20000 | C10: Commercial | D10: 8. RITEL | E10: Menengah Kanwil | F10: KREDIT MENENGAH | G10: Menengah Kanwil | H10: Menengah
A11: 21000 | B11: =VLOOKUP(A11,[1]BRD!A:A,1,0) -> #N/A | C11: Menengah | D11: 2. BISNIS UMUM | E11: Bisnis Umum | F11: KREDIT MENENGAH - KP | G11: Menengah Kanpus | H11: Menengah
A12: 21010 | B12: =VLOOKUP(A12,[1]BRD!A:A,1,0) -> #N/A | C12: Menengah | D12: 4. AGRIBISNIS | E12: Agribisnis | F12: (AGB) | G12: Menengah Kanpus | H12: Menengah
A13: 21011 | B13: =VLOOKUP(A13,[1]BRD!A:A,1,0) -> #N/A | C13: Menengah | D13: 4. AGRIBISNIS | E13: Agribisnis | F13: (AGB) 1. S/D Rp 5 M | G13: Menengah Kanpus | H13: Menengah
... A170: 82240 | B170: =VLOOKUP(A170,[1]BRD!A:A,1,0) -> 82240 | C170: Small | D170: 12. KECIL | E170: Program (Non KUR) | F170: 01. KREDIT DATA SUP (CF, CG) | G170: KREDIT DATA SUP (CF, CG) | H170: Program Non KUR

Sheet LNPAR
A1: PTYPE | B1: PSHDSC | C1: PTYDSC | D1: PLNGRP | E1: PGRDSC | F1: PGBOOK | G1: PIBASE | H1: PDEPTC | I1: PCURTY | J1: PBKDYS | K1: PMINRT | L1: PMAXRT | M1: PRFLOR | N1: PRCEIL | O1: PINCLU | P1: PFREQ | Q1: PFCODE | R1: PPMTCD | S1: PLATCD | T1: PPDNOT | U1: PCDNOT | V1: PCPN | W1: PMINCG | X1: PCLASS | Y1: PPRCPM | Z1: P1MMPD | AA1: P2MMPD | AB1: P3MMPD | AC1: P4MMPD | AD1: P5MMPD | AE1: P6MMPD | AF1: P1DDPD | AG1: P2DDPD | AH1: P3DDPD | AI1: P4DDPD | AJ1: P5DDPD | AK1: P6DDPD | AL1: PPDRPT | AM1: PMAXLC | AN1: PMNNEW | AO1: PRHSNW | AP1: PRHSPD | AQ1: PRHSPO | AR1: PDHSDY | AS1: PBLNDY | AT1: POTOL | AU1: PMTBOA | AV1: PTAKLC | AW1: PRDTBK | AX1: PRDTDL | AY1: PRDTCL | AZ1: PRDTAH | BA1: PRDTMS | BB1: PRDTTT | BC1: PRLDBK | BD1: PRLDDL | BE1: PRLDCL | BF1: PRLDAH | BG1: PRLDMS | BH1: PRLDTT | BI1: PRMEBK | BJ1: PRMEDL | BK1: PRMECL | BL1: PRMEAH | BM1: PRMEMS | BN1: PRMETT | BO1: PRMTBK | BP1: PRMTDL | BQ1: PRMTCL | BR1: PRMTAH | BS1: PRMTMS | BT1: PRMTTT | BU1: PMNRBK | BV1: PMNRDL | BW1: PMNRCL | BX1: PMNRAH | BY1: PMNRMS | BZ1: PMNRTT | CA1: PRCABK | CB1: PREXBK | CC1: PREXDL | CD1: PREXCL | CE1: PREXAH | CF1: PREXMS | CG1: PREXTT | CH1: PPRCNO | CI1: PBLLBR | CJ1: PRBEXF | CK1: PPRRTC | CL1: PDCBTR | CM1: PMIAMR | CN1: PLCTYP | CO1: PALTSC | CP1: PALTRT | CQ1: PHMAIL | CR1: PRMIND | CS1: PTITLE | CT1: PCLSZR | CU1: PSTATU | CV1: PREAMO | CW1: PESCRO | CX1: PPARTI | CY1: PHASAR | CZ1: PALMTY | DA1: PALWBD | DB1: PBILAW | DC1: PBILDY | DD1: PESCPO | DE1: PDOCTR | DF1: PPPPCD | DG1: PUSESP | DH1: PLSIC1 | DI1: PLSIC2 | DJ1: PLSIC3 | DK1: PLSIC4 | DL1: P1098C | DM1: PCRREP | DN1: PCRTYP | DO1: PCALRE | DP1: PRTCDY | DQ1: PRTCMX | DR1: PRMSUP | DS1: PCLWBK | DT1: PCMRT# | DU1: PCMRT | DV1: PCAPIN | DW1: PCAPLC | DX1: PCAPCA | DY1: PCTYPE | DZ1: PCAPFL | EA1: PACCAP | EB1: PANACT | EC1: PMDINT | ED1: PYRBSE | EE1: PNEAR$ | EF1: PNEARN | EG1: PADJBK | EH1: PCRATE | EI1: PDREST | EJ1: PMRATE | EK1: PDRWDN | EL1: PLONGP | EM1: PLCMC | EN1: PNCRTC | EO1: PKINTR | EP1: PCFPDT | EQ1: PEPEN | ER1: PSHARE | ES1: PPTERM | ET1: PPTMCD | EU1: PPTMIN | EV1: PUPPCD | EW1: PDFPCD | EX1: PBKFUL | EY1: PLSADV | EZ1: PNEGBL | FA1: PUMATD | FB1: PASMAT | FC1: PLSARR | FD1: PCALBK | FE1: PACMC | FF1: PACOC | FG1: PACLC | FH1: PACINT | FI1: PPBMC | FJ1: PPBOC | FK1: PPBLC | FL1: PPBINT | FM1: PMTHBK | FN1: PSIBAS | FO1: PINPAY | FP1: PINALC | FQ1: PINMAT | FR1: PUPDOB | FS1: PDAFP | FT1: PCPAMR | FU1: PROLM | FV1: PDFES# | FW1: PDFESC | FX1: PDFESI | FY1: PUMDRC | FZ1: PUMDCP | GA1: PIFREQ | GB1: PIFCOD | GC1: PCAPMT | GD1: PCAPNP | GE1: PNPLMT | GF1: P#DNPL | GG1: PCPCOM | GH1: PLCLC | GI1: PLCIN | GJ1: PWVELC | GK1: PNPLF | GL1: PCNIPD | GM1: PUPIOB | GN1: PDANIP | GO1: PADVPM | GP1: PSPLTO | GQ1: PADJDD | GR1: PYBSEL | GS1: PYBSEC | GT1: PMINUL | GU1: PMULPC | GV1: PNOADV | GW1: PABKD | GX1: PFFPDT | GY1: POREAM | GZ1: POCPAM | HA1: POABKD | HB1: PBRATE | HC1: PRTPRD | HD1: PFILON | HE1: PFPREP | HF1: PFPRCD | HG1: PFWMTH | HH1: PFPR1 | HI1: PFPR2 | HJ1: PFPR3 | HK1: PFPR4 | HL1: PFPRCT | HM1: PFCANC | HN1: PFCACD | HO1: PFCA1 | HP1: PFCA2 | HQ1: PFCACT | HR1: PFUDRW | HS1: PFUDPC | HT1: PFUDER | HU1: PFUDAR | HV1: PSUPTR | HW1: PPLOPT | HX1: PCARMD | HY1: PMFORG | HZ1: PMFMAT | IA1: PMFNPD | IB1: PINTMT | IC1: PRSTAM | ID1: PINCTV | IE1: PBIAFG
A2: HA | B2: KUPEKS BLN | C2: KUPEDES MK BULANAN | D2: 212 | E2: POnB,Non Prog,KUPEDE | G2: 8 | H2: 110 | I2: IDR | J2: 7 | K2: 0.12 | L2: 0.36 | M2: 0.12 | N2: 0.36 | O2: N | P2: 1 | Q2: M | R2: 0 | S2: 0 | T2: Y | U2: Y | V2: N | W2: 0 | X2: I | Y2: 1 | Z2: 0 | AA2: 0 | AB2: 0 | AC2: 0 | AD2: 0 | AE2: 0 | AF2: 7 | AG2: 21 | AH2: 35 | AI2: 49 | AJ2: 63 | AK2: 77 | AL2: 0 | AM2: 0 | AN2: 0 | AO2: Y | AP2: R | AQ2: 0 | AR2: 0 | AS2: 1 | AT2: 0 | AU2: Y | BC2: 0 | BD2: 0 | BE2: 0 | BF2: 0 | BG2: 0 | BH2: 0 | BI2: N | BJ2: N | BK2: N | BL2: N | BM2: N | BN2: N | BU2: 0 | BV2: 0 | BW2: 0 | BX2: 0 | BY2: 0 | BZ2: 0 | CA2: P | CB2: N | CC2: N | CD2: N | CE2: N | CF2: N | CG2: N | CH2: N | CI2: 0 | CJ2: N | CL2: 0 | CM2: N | CN2: 0 | CO2: N | CP2: N | CQ2: A | CR2: N | CT2: Y | CU2: 4 | CV2: N | CW2: N | CY2: N | DA2: Y | DC2: 0 | DD2: K | DG2: N | DH2: N | DI2: N | DJ2: N | DK2: N | DP2: 0 | DQ2: 0 | DR2: 90 | DS2: 90 | DT2: 0 | DU2: 0 | DV2: N | DW2: P | DX2: P | DY2: 17 | DZ2: N | EC2: F | ED2: 5 | EE2: R | EF2: 100 | EG2: N | EH2: N | EI2: N | EJ2: Z | EK2: N | EL2: 8 | EM2: N | EO2: 0 | EP2: P | EQ2: Y | ER2: N | ES2: 0 | EV2: Y | EW2: 0 | EX2: N | EY2: N | EZ2: N | FA2: N | FB2: Y | FC2: N | FD2: B | FE2: N | FF2: N | FG2: N | FH2: N | FI2: N | FJ2: N | FK2: N | FL2: N | FM2: 0 | FN2: N | FO2: N | FP2: N | FQ2: N | FR2: 0 | FS2: 0 | FT2: N | FV2: 0 | FY2: N | FZ2: N | GA2: 1 | GB2: M | GC2: N | GD2: N | GE2: N | GF2: 0 | GG2: O | GH2: N | GI2: N | GJ2: N | GK2: Y | GL2: N | GM2: 0 | GN2: 0 | GO2: Y | GP2: Y | GQ2: N | GR2: 2 | GS2: 2 | GT2: 0 | GU2: 0 | GV2: 0 | GW2: N | GX2: Y | HB2: N | HC2: 0 | HD2: N | HE2: N | HG2: 0 | HH2: 0 | HI2: 0 | HJ2: 0 | HK2: 0 | HM2: N | HO2: 0 | HP2: 0 | HR2: 0 | HS2: 0 | HT2: 0 | HU2: 0 | HV2: D | HW2: W | HY2: 3 | HZ2: 3 | IA2: 6 | IB2: N | IC2: N | ID2: Y | IE2: N
A3: HB | B3: KUPEKS 3BL | C3: KUPEDES MK 3 BULANAN | D3: 212 | E3: POnB,Non Prog,KUPEDE | G3: 8 | H3: 110 | I3: IDR | J3: 7 | K3: 0.09 | L3: 0.42 | M3: 0.09 | N3: 0.42 | O3: N | P3: 3 | Q3: M | R3: 0 | S3: 0 | T3: Y | U3: Y | V3: N | W3: 0 | X3: I | Y3: 1 | Z3: 0 | AA3: 0 | AB3: 0 | AC3: 0 | AD3: 0 | AE3: 0 | AF3: 7 | AG3: 21 | AH3: 35 | AI3: 49 | AJ3: 63 | AK3: 77 | AL3: 0 | AM3: 0 | AN3: 0 | AO3: Y | AP3: R | AQ3: 0 | AR3: 0 | AS3: 1 | AT3: 0 | AU3: Y | BC3: 0 | BD3: 0 | BE3: 0 | BF3: 0 | BG3: 0 | BH3: 0 | BI3: N | BJ3: N | BK3: N | BL3: N | BM3: N | BN3: N | BU3: 0 | BV3: 0 | BW3: 0 | BX3: 0 | BY3: 0 | BZ3: 0 | CA3: P | CB3: N | CC3: N | CD3: N | CE3: N | CF3: N | CG3: N | CH3: N | CI3: 0 | CJ3: N | CL3: 0 | CM3: N | CN3: 0 | CO3: N | CP3: N | CQ3: A | CR3: N | CT3: Y | CU3: 4 | CV3: N | CW3: N | CY3: N | DA3: Y | DC3: 0 | DD3: K | DG3: N | DH3: N | DI3: N | DJ3: N | DK3: N | DP3: 0 | DQ3: 0 | DR3: 90 | DS3: 90 | DT3: 0 | DU3: 0 | DV3: N | DW3: P | DX3: P | DY3: 17 | DZ3: N | EC3: F | ED3: 5 | EE3: R | EF3: 100 | EG3: N | EH3: N | EI3: N | EJ3: Z | EK3: N | EL3: 8 | EM3: N | EO3: 0 | EP3: P | EQ3: N | ER3: N | ES3: 0 | EV3: Y | EW3: 0 | EX3: N | EY3: N | EZ3: N | FA3: N | FB3: Y | FC3: N | FD3: B | FE3: N | FF3: N | FG3: N | FH3: N | FI3: N | FJ3: N | FK3: N | FL3: N | FM3: 0 | FN3: N | FO3: N | FP3: N | FQ3: N | FR3: 0 | FS3: 0 | FT3: N | FV3: 0 | FY3: N | FZ3: N | GA3: 3 | GB3: M | GC3: N | GD3: N | GE3: N | GF3: 0 | GG3: O | GH3: N | GI3: N | GJ3: N | GK3: Y | GL3: N | GM3: 0 | GN3: 0 | GO3: Y | GP3: Y | GQ3: N | GR3: 2 | GS3: 2 | GT3: 0 | GU3: 0 | GV3: 0 | GW3: N | GX3: Y | HB3: N | HC3: 0 | HD3: N | HE3: N | HG3: 0 | HH3: 0 | HI3: 0 | HJ3: 0 | HK3: 0 | HM3: N | HO3: 0 | HP3: 0 | HR3: 0 | HS3: 0 | HT3: 0 | HU3: 0 | HV3: D | HW3: W | HY3: 3 | HZ3: 3 | IA3: 6 | IB3: N | IC3: N | ID3: Y | IE3: N
A4: HC | B4: KUPEKS 4BL | C4: KUPEDES MK 4 BULANAN | D4: 212 | E4: POnB,Non Prog,KUPEDE | G4: 8 | H4: 110 | I4: IDR | J4: 7 | K4: 0.09 | L4: 0.42 | M4: 0.09 | N4: 0.42 | O4: N | P4: 4 | Q4: M | R4: 0 | S4: 0 | T4: Y | U4: Y | V4: N | W4: 0 | X4: I | Y4: 1 | Z4: 0 | AA4: 0 | AB4: 0 | AC4: 0 | AD4: 0 | AE4: 0 | AF4: 7 | AG4: 21 | AH4: 35 | AI4: 49 | AJ4: 63 | AK4: 77 | AL4: 0 | AM4: 0 | AN4: 0 | AO4: Y | AP4: R | AQ4: 0 | AR4: 0 | AS4: 1 | AT4: 0 | AU4: Y | BC4: 0 | BD4: 0 | BE4: 0 | BF4: 0 | BG4: 0 | BH4: 0 | BI4: N | BJ4: N | BK4: N | BL4: N | BM4: N | BN4: N | BU4: 0 | BV4: 0 | BW4: 0 | BX4: 0 | BY4: 0 | BZ4: 0 | CA4: P | CB4: N | CC4: N | CD4: N | CE4: N | CF4: N | CG4: N | CH4: N | CI4: 0 | CJ4: N | CL4: 0 | CM4: N | CN4: 0 | CO4: N | CP4: N | CQ4: A | CR4: N | CT4: Y | CU4: 4 | CV4: N | CW4: N | CY4: N | DA4: Y | DC4: 0 | DD4: K | DG4: N | DH4: N | DI4: N | DJ4: N | DK4: N | DP4: 0 | DQ4: 0 | DR4: 90 | DS4: 90 | DT4: 0 | DU4: 0 | DV4: N | DW4: P | DX4: P | DY4: 17 | DZ4: N | EC4: F | ED4: 5 | EE4: R | EF4: 100 | EG4: N | EH4: N | EI4: N | EJ4: Z | EK4: N | EL4: 8 | EM4: N | EO4: 0 | EP4: P | EQ4: N | ER4: N | ES4: 0 | EV4: Y | EW4: 0 | EX4: N | EY4: N | EZ4: N | FA4: N | FB4: Y | FC4: N | FD4: B | FE4: N | FF4: N | FG4: N | FH4: N | FI4: N | FJ4: N | FK4: N | FL4: N | FM4: 0 | FN4: N | FO4: N | FP4: N | FQ4: N | FR4: 0 | FS4: 0 | FT4: N | FV4: 0 | FY4: N | FZ4: N | GA4: 4 | GB4: M | GC4: N | GD4: N | GE4: N | GF4: 0 | GG4: O | GH4: N | GI4: N | GJ4: N | GK4: Y | GL4: N | GM4: 0 | GN4: 0 | GO4: Y | GP4: Y | GQ4: N | GR4: 2 | GS4: 2 | GT4: 0 | GU4: 0 | GV4: 0 | GW4: N | GX4: Y | HB4: N | HC4: 0 | HD4: N | HE4: N | HG4: 0 | HH4: 0 | HI4: 0 | HJ4: 0 | HK4: 0 | HM4: N | HO4: 0 | HP4: 0 | HR4: 0 | HS4: 0 | HT4: 0 | HU4: 0 | HV4: D | HW4: W | HY4: 3 | HZ4: 3 | IA4: 6 | IB4: N | IC4: N | ID4: Y | IE4: N
A5: HD | B5: KUPEKS 6BL | C5: KUPEDES MK 6 BULANAN | D5: 212 | E5: POnB,Non Prog,KUPEDE | G5: 8 | H5: 110 | I5: IDR | J5: 7 | K5: 0.09 | L5: 0.42 | M5: 0.09 | N5: 0.42 | O5: N | P5: 6 | Q5: M | R5: 0 | S5: 0 | T5: Y | U5: Y | V5: N | W5: 0 | X5: I | Y5: 1 | Z5: 0 | AA5: 0 | AB5: 0 | AC5: 0 | AD5: 0 | AE5: 0 | AF5: 7 | AG5: 21 | AH5: 35 | AI5: 49 | AJ5: 63 | AK5: 77 | AL5: 0 | AM5: 0 | AN5: 0 | AO5: Y | AP5: R | AQ5: 0 | AR5: 0 | AS5: 1 | AT5: 0 | AU5: Y | BC5: 0 | BD5: 0 | BE5: 0 | BF5: 0 | BG5: 0 | BH5: 0 | BI5: N | BJ5: N | BK5: N | BL5: N | BM5: N | BN5: N | BU5: 0 | BV5: 0 | BW5: 0 | BX5: 0 | BY5: 0 | BZ5: 0 | CA5: P | CB5: N | CC5: N | CD5: N | CE5: N | CF5: N | CG5: N | CH5: N | CI5: 0 | CJ5: N | CL5: 0 | CM5: N | CN5: 0 | CO5: N | CP5: N | CQ5: A | CR5: N | CT5: Y | CU5: 4 | CV5: N | CW5: N | CY5: N | DA5: Y | DC5: 0 | DD5: K | DG5: N | DH5: N | DI5: N | DJ5: N | DK5: N | DP5: 0 | DQ5: 0 | DR5: 90 | DS5: 90 | DT5: 0 | DU5: 0 | DV5: N | DW5: P | DX5: P | DY5: 17 | DZ5: N | EC5: F | ED5: 5 | EE5: R | EF5: 100 | EG5: N | EH5: N | EI5: N | EJ5: Z | EK5: N | EL5: 8 | EM5: N | EO5: 0 | EP5: P | EQ5: N | ER5: N | ES5: 0 | EV5: Y | EW5: 0 | EX5: N | EY5: N | EZ5: N | FA5: N | FB5: Y | FC5: N | FD5: B | FE5: N | FF5: N | FG5: N | FH5: N | FI5: N | FJ5: N | FK5: N | FL5: N | FM5: 0 | FN5: N | FO5: N | FP5: N | FQ5: N | FR5: 0 | FS5: 0 | FT5: N | FV5: 0 | FY5: N | FZ5: N | GA5: 6 | GB5: M | GC5: N | GD5: N | GE5: N | GF5: 0 | GG5: O | GH5: N | GI5: N | GJ5: N | GK5: Y | GL5: N | GM5: 0 | GN5: 0 | GO5: Y | GP5: Y | GQ5: N | GR5: 2 | GS5: 2 | GT5: 0 | GU5: 0 | GV5: 0 | GW5: N | GX5: Y | HB5: N | HC5: 0 | HD5: N | HE5: N | HG5: 0 | HH5: 0 | HI5: 0 | HJ5: 0 | HK5: 0 | HM5: N | HO5: 0 | HP5: 0 | HR5: 0 | HS5: 0 | HT5: 0 | HU5: 0 | HV5: D | HW5: W | HY5: 3 | HZ5: 3 | IA5: 6 | IB5: N | IC5: N | ID5: Y | IE5: N
A6: HE | B6: KUPEKS 1XL | C6: KUPEDES MK 1X LUNAS | D6: 212 | E6: POnB,Non Prog,KUPEDE | G6: 8 | H6: 110 | I6: IDR | J6: 7 | K6: 0.09 | L6: 0.42 | M6: 0.09 | N6: 0.42 | O6: N | P6: 36 | Q6: M | R6: 5 | S6: 0 | T6: Y | U6: Y | V6: N | W6: 0 | X6: I | Y6: 1 | Z6: 0 | AA6: 0 | AB6: 0 | AC6: 0 | AD6: 0 | AE6: 0 | AF6: 7 | AG6: 21 | AH6: 35 | AI6: 49 | AJ6: 63 | AK6: 77 | AL6: 0 | AM6: 0 | AN6: 0 | AO6: Y | AP6: R | AQ6: 0 | AR6: 0 | AS6: 1 | AT6: 0 | AU6: Y | BC6: 0 | BD6: 0 | BE6: 0 | BF6: 0 | BG6: 0 | BH6: 0 | BI6: N | BJ6: N | BK6: N | BL6: N | BM6: N | BN6: N | BU6: 0 | BV6: 0 | BW6: 0 | BX6: 0 | BY6: 0 | BZ6: 0 | CA6: P | CB6: N | CC6: N | CD6: N | CE6: N | CF6: N | CG6: N | CH6: N | CI6: 0 | CJ6: N | CL6: 0 | CM6: N | CN6: 0 | CO6: N | CP6: N | CQ6: A | CR6: N | CT6: Y | CU6: 4 | CV6: N | CW6: N | CY6: N | DA6: Y | DC6: 0 | DD6: K | DG6: N | DH6: N | DI6: N | DJ6: N | DK6: N | DP6: 0 | DQ6: 0 | DR6: 90 | DS6: 90 | DT6: 0 | DU6: 0 | DV6: N | DW6: P | DX6: P | DY6: 17 | DZ6: N | EC6: F | ED6: 5 | EE6: R | EF6: 100 | EG6: N | EH6: N | EI6: N | EJ6: Z | EK6: N | EL6: 8 | EM6: N | EO6: 0 | EP6: X | EQ6: N | ER6: N | ES6: 0 | EV6: Y | EW6: 5 | EX6: N | EY6: N | EZ6: N | FA6: N | FB6: Y | FC6: N | FD6: B | FE6: N | FF6: N | FG6: N | FH6: N | FI6: N | FJ6: N | FK6: N | FL6: N | FM6: 0 | FN6: N | FO6: N | FP6: N | FQ6: N | FR6: 0 | FS6: 0 | FT6: N | FV6: 0 | FY6: N | FZ6: N | GA6: 36 | GB6: M | GC6: N | GD6: N | GE6: N | GF6: 0 | GG6: O | GH6: N | GI6: N | GJ6: N | GK6: Y | GL6: N | GM6: 0 | GN6: 0 | GO6: Y | GP6: Y | GQ6: N | GR6: 2 | GS6: 2 | GT6: 0 | GU6: 0 | GV6: 0 | GW6: N | GX6: Y | HB6: N | HC6: 0 | HD6: N | HE6: N | HG6: 0 | HH6: 0 | HI6: 0 | HJ6: 0 | HK6: 0 | HM6: N | HO6: 0 | HP6: 0 | HR6: 0 | HS6: 0 | HT6: 0 | HU6: 0 | HV6: D | HW6: W | HY6: 3 | HZ6: 3 | IA6: 6 | IB6: N | IC6: N | ID6: Y | IE6: N
A7: HM | B7: KUPIN 1XL | C7: KUPEDES INV 1X LUNAS | D7: 212 | E7: POnB,Non Prog,KUPEDE | G7: 8 | H7: 110 | I7: IDR | J7: 7 | K7: 0.09 | L7: 0.42 | M7: 0.09 | N7: 0.42 | O7: N | P7: 36 | Q7: M | R7: 5 | S7: 0 | T7: Y | U7: Y | V7: N | W7: 0 | X7: I | Y7: 1 | Z7: 0 | AA7: 0 | AB7: 0 | AC7: 0 | AD7: 0 | AE7: 0 | AF7: 7 | AG7: 21 | AH7: 35 | AI7: 49 | AJ7: 63 | AK7: 77 | AL7: 0 | AM7: 0 | AN7: 0 | AO7: Y | AP7: R | AQ7: 0 | AR7: 0 | AS7: 1 | AT7: 0 | AU7: Y | BC7: 0 | BD7: 0 | BE7: 0 | BF7: 0 | BG7: 0 | BH7: 0 | BI7: N | BJ7: N | BK7: N | BL7: N | BM7: N | BN7: N | BU7: 0 | BV7: 0 | BW7: 0 | BX7: 0 | BY7: 0 | BZ7: 0 | CA7: P | CB7: N | CC7: N | CD7: N | CE7: N | CF7: N | CG7: N | CH7: N | CI7: 0 | CJ7: N | CL7: 0 | CM7: N | CN7: 0 | CO7: N | CP7: N | CQ7: A | CR7: N | CT7: Y | CU7: 4 | CV7: N | CW7: N | CY7: N | DA7: Y | DC7: 0 | DD7: K | DG7: N | DH7: N | DI7: N | DJ7: N | DK7: N | DP7: 0 | DQ7: 0 | DR7: 90 | DS7: 90 | DT7: 0 | DU7: 0 | DV7: N | DW7: P | DX7: P | DY7: 17 | DZ7: N | EC7: F | ED7: 5 | EE7: R | EF7: 100 | EG7: N | EH7: N | EI7: N | EJ7: Z | EK7: N | EL7: 8 | EM7: N | EO7: 0 | EP7: X | EQ7: N | ER7: N | ES7: 0 | EV7: Y | EW7: 5 | EX7: N | EY7: N | EZ7: N | FA7: N | FB7: Y | FC7: N | FD7: B | FE7: N | FF7: N | FG7: N | FH7: N | FI7: N | FJ7: N | FK7: N | FL7: N | FM7: 0 | FN7: N | FO7: N | FP7: N | FQ7: N | FR7: 0 | FS7: 0 | FT7: N | FV7: 0 | FY7: N | FZ7: N | GA7: 36 | GB7: M | GC7: N | GD7: N | GE7: N | GF7: 0 | GG7: O | GH7: N | GI7: N | GJ7: N | GK7: Y | GL7: N | GM7: 0 | GN7: 0 | GO7: Y | GP7: Y | GQ7: N | GR7: 2 | GS7: 2 | GT7: 0 | GU7: 0 | GV7: 0 | GW7: N | GX7: Y | HB7: N | HC7: 0 | HD7: N | HE7: N | HG7: 0 | HH7: 0 | HI7: 0 | HJ7: 0 | HK7: 0 | HM7: N | HO7: 0 | HP7: 0 | HR7: 0 | HS7: 0 | HT7: 0 | HU7: 0 | HV7: D | HW7: W | HY7: 3 | HZ7: 3 | IA7: 6 | IB7: N | IC7: N | ID7: Y | IE7: N
A8: HI | B8: KUPIN BLN | C8: KUPEDES INV BULANAN | D8: 212 | E8: KUPEDES, Divisi Mikr | G8: 8 | H8: 110 | I8: IDR | J8: 7 | K8: 0.12 | L8: 0.36 | M8: 0.12 | N8: 0.36 | O8: N | P8: 1 | Q8: M | R8: 0 | S8: 0 | T8: Y | U8: Y | V8: N | W8: 0 | X8: I | Y8: 1 | Z8: 0 | AA8: 0 | AB8: 0 | AC8: 0 | AD8: 0 | AE8: 0 | AF8: 7 | AG8: 21 | AH8: 35 | AI8: 49 | AJ8: 63 | AK8: 77 | AL8: 0 | AM8: 0 | AN8: 0 | AO8: Y | AP8: R | AQ8: 0 | AR8: 0 | AS8: 1 | AT8: 0 | AU8: Y | BC8: 0 | BD8: 0 | BE8: 0 | BF8: 0 | BG8: 0 | BH8: 0 | BI8: N | BJ8: N | BK8: N | BL8: N | BM8: N | BN8: N | BU8: 0 | BV8: 0 | BW8: 0 | BX8: 0 | BY8: 0 | BZ8: 0 | CA8: P | CB8: N | CC8: N | CD8: N | CE8: N | CF8: N | CG8: N | CH8: N | CI8: 0 | CJ8: N | CL8: 0 | CM8: N | CN8: 0 | CO8: N | CP8: N | CQ8: A | CR8: N | CT8: Y | CU8: 4 | CV8: N | CW8: N | CY8: N | DA8: Y | DC8: 0 | DD8: K | DG8: N | DH8: N | DI8: N | DJ8: N | DK8: N | DP8: 0 | DQ8: 0 | DR8: 90 | DS8: 90 | DT8: 0 | DU8: 0 | DV8: N | DW8: P | DX8: P | DY8: 17 | DZ8: N | EC8: F | ED8: 5 | EE8: R | EF8: 100 | EG8: N | EH8: N | EI8: N | EJ8: Z | EK8: N | EL8: 8 | EM8: N | EO8: 0 | EP8: P | EQ8: Y | ER8: N | ES8: 0 | EV8: Y | EW8: 0 | EX8: N | EY8: N | EZ8: N | FA8: N | FB8: Y | FC8: N | FD8: B | FE8: N | FF8: N | FG8: N | FH8: N | FI8: N | FJ8: N | FK8: N | FL8: N | FM8: 0 | FN8: N | FO8: N | FP8: N | FQ8: N | FR8: 0 | FS8: 0 | FT8: N | FV8: 0 | FY8: N | FZ8: N | GA8: 1 | GB8: M | GC8: N | GD8: N | GE8: N | GF8: 0 | GG8: O | GH8: N | GI8: N | GJ8: N | GK8: Y | GL8: N | GM8: 0 | GN8: 0 | GO8: Y | GP8: Y | GQ8: N | GR8: 2 | GS8: 2 | GT8: 0 | GU8: 0 | GV8: 0 | GW8: N | GX8: Y | HB8: N | HC8: 0 | HD8: N | HE8: N | HG8: 0 | HH8: 0 | HI8: 0 | HJ8: 0 | HK8: 0 | HM8: N | HO8: 0 | HP8: 0 | HR8: 0 | HS8: 0 | HT8: 0 | HU8: 0 | HV8: D | HW8: W | HY8: 3 | HZ8: 3 | IA8: 6 | IB8: N | IC8: N | ID8: Y | IE8: N
A9: HJ | B9: KUPIN 3BLN | C9: KUPEDES INV 3BULANAN | D9: 212 | E9: POnB,Non Prog,KUPEDE | G9: 8 | H9: 110 | I9: IDR | J9: 7 | K9: 0.09 | L9: 0.42 | M9: 0.09 | N9: 0.42 | O9: N | P9: 3 | Q9: M | R9: 0 | S9: 0 | T9: Y | U9: Y | V9: N | W9: 0 | X9: I | Y9: 1 | Z9: 0 | AA9: 0 | AB9: 0 | AC9: 0 | AD9: 0 | AE9: 0 | AF9: 7 | AG9: 21 | AH9: 35 | AI9: 49 | AJ9: 63 | AK9: 77 | AL9: 0 | AM9: 0 | AN9: 0 | AO9: Y | AP9: R | AQ9: 0 | AR9: 0 | AS9: 1 | AT9: 0 | AU9: Y | BC9: 0 | BD9: 0 | BE9: 0 | BF9: 0 | BG9: 0 | BH9: 0 | BI9: N | BJ9: N | BK9: N | BL9: N | BM9: N | BN9: N | BU9: 0 | BV9: 0 | BW9: 0 | BX9: 0 | BY9: 0 | BZ9: 0 | CA9: P | CB9: N | CC9: N | CD9: N | CE9: N | CF9: N | CG9: N | CH9: N | CI9: 0 | CJ9: N | CL9: 0 | CM9: N | CN9: 0 | CO9: N | CP9: N | CQ9: A | CR9: N | CT9: Y | CU9: 4 | CV9: N | CW9: N | CY9: N | DA9: Y | DC9: 0 | DD9: K | DG9: N | DH9: N | DI9: N | DJ9: N | DK9: N | DP9: 0 | DQ9: 0 | DR9: 90 | DS9: 90 | DT9: 0 | DU9: 0 | DV9: N | DW9: P | DX9: P | DY9: 17 | DZ9: N | EC9: F | ED9: 5 | EE9: R | EF9: 100 | EG9: N | EH9: N | EI9: N | EJ9: Z | EK9: N | EL9: 8 | EM9: N | EO9: 0 | EP9: P | EQ9: N | ER9: N | ES9: 0 | EV9: Y | EW9: 0 | EX9: N | EY9: N | EZ9: N | FA9: N | FB9: Y | FC9: N | FD9: B | FE9: N | FF9: N | FG9: N | FH9: N | FI9: N | FJ9: N | FK9: N | FL9: N | FM9: 0 | FN9: N | FO9: N | FP9: N | FQ9: N | FR9: 0 | FS9: 0 | FT9: N | FV9: 0 | FY9: N | FZ9: N | GA9: 3 | GB9: M | GC9: N | GD9: N | GE9: N | GF9: 0 | GG9: O | GH9: N | GI9: N | GJ9: N | GK9: Y | GL9: N | GM9: 0 | GN9: 0 | GO9: Y | GP9: Y | GQ9: N | GR9: 2 | GS9: 2 | GT9: 0 | GU9: 0 | GV9: 0 | GW9: N | GX9: Y | HB9: N | HC9: 0 | HD9: N | HE9: N | HG9: 0 | HH9: 0 | HI9: 0 | HJ9: 0 | HK9: 0 | HM9: N | HO9: 0 | HP9: 0 | HR9: 0 | HS9: 0 | HT9: 0 | HU9: 0 | HV9: D | HW9: W | HY9: 3 | HZ9: 3 | IA9: 6 | IB9: N | IC9: N | ID9: Y | IE9: N
A10: HK | B10: KUPIN 4BLN | C10: KUPEDES INV 4BULANAN | D10: 212 | E10: POnB,Non Prog,KUPEDE | G10: 8 | H10: 110 | I10: IDR | J10: 7 | K10: 0.09 | L10: 0.42 | M10: 0.09 | N10: 0.42 | O10: N | P10: 4 | Q10: M | R10: 0 | S10: 0 | T10: Y | U10: Y | V10: N | W10: 0 | X10: I | Y10: 1 | Z10: 0 | AA10: 0 | AB10: 0 | AC10: 0 | AD10: 0 | AE10: 0 | AF10: 7 | AG10: 21 | AH10: 35 | AI10: 49 | AJ10: 63 | AK10: 77 | AL10: 0 | AM10: 0 | AN10: 0 | AO10: Y | AP10: R | AQ10: 0 | AR10: 0 | AS10: 1 | AT10: 0 | AU10: Y | BC10: 0 | BD10: 0 | BE10: 0 | BF10: 0 | BG10: 0 | BH10: 0 | BI10: N | BJ10: N | BK10: N | BL10: N | BM10: N | BN10: N | BU10: 0 | BV10: 0 | BW10: 0 | BX10: 0 | BY10: 0 | BZ10: 0 | CA10: P | CB10: N | CC10: N | CD10: N | CE10: N | CF10: N | CG10: N | CH10: N | CI10: 0 | CJ10: N | CL10: 0 | CM10: N | CN10: 0 | CO10: N | CP10: N | CQ10: A | CR10: N | CT10: Y | CU10: 4 | CV10: N | CW10: N | CY10: N | DA10: Y | DC10: 0 | DD10: K | DG10: N | DH10: N | DI10: N | DJ10: N | DK10: N | DP10: 0 | DQ10: 0 | DR10: 90 | DS10: 90 | DT10: 0 | DU10: 0 | DV10: N | DW10: P | DX10: P | DY10: 17 | DZ10: N | EC10: F | ED10: 5 | EE10: R | EF10: 100 | EG10: N | EH10: N | EI10: N | EJ10: Z | EK10: N | EL10: 8 | EM10: N | EO10: 0 | EP10: P | EQ10: N | ER10: N | ES10: 0 | EV10: Y | EW10: 0 | EX10: N | EY10: N | EZ10: N | FA10: N | FB10: Y | FC10: N | FD10: B | FE10: N | FF10: N | FG10: N | FH10: N | FI10: N | FJ10: N | FK10: N | FL10: N | FM10: 0 | FN10: N | FO10: N | FP10: N | FQ10: N | FR10: 0 | FS10: 0 | FT10: N | FV10: 0 | FY10: N | FZ10: N | GA10: 4 | GB10: M | GC10: N | GD10: N | GE10: N | GF10: 0 | GG10: O | GH10: N | GI10: N | GJ10: N | GK10: Y | GL10: N | GM10: 0 | GN10: 0 | GO10: Y | GP10: Y | GQ10: N | GR10: 2 | GS10: 2 | GT10: 0 | GU10: 0 | GV10: 0 | GW10: N | GX10: Y | HB10: N | HC10: 0 | HD10: N | HE10: N | HG10: 0 | HH10: 0 | HI10: 0 | HJ10: 0 | HK10: 0 | HM10: N | HO10: 0 | HP10: 0 | HR10: 0 | HS10: 0 | HT10: 0 | HU10: 0 | HV10: D | HW10: W | HY10: 3 | HZ10: 3 | IA10: 6 | IB10: N | IC10: N | ID10: Y | IE10: N
A11: HL | B11: KUPIN 6BLN | C11: KUPEDES INV 6BULANAN | D11: 212 | E11: POnB,Non Prog,KUPEDE | G11: 8 | H11: 110 | I11: IDR | J11: 7 | K11: 0.09 | L11: 0.42 | M11: 0.09 | N11: 0.42 | O11: N | P11: 6 | Q11: M | R11: 0 | S11: 0 | T11: Y | U11: Y | V11: N | W11: 0 | X11: I | Y11: 1 | Z11: 0 | AA11: 0 | AB11: 0 | AC11: 0 | AD11: 0 | AE11: 0 | AF11: 7 | AG11: 21 | AH11: 35 | AI11: 49 | AJ11: 63 | AK11: 77 | AL11: 0 | AM11: 0 | AN11: 0 | AO11: Y | AP11: R | AQ11: 0 | AR11: 0 | AS11: 1 | AT11: 0 | AU11: Y | BC11: 0 | BD11: 0 | BE11: 0 | BF11: 0 | BG11: 0 | BH11: 0 | BI11: N | BJ11: N | BK11: N | BL11: N | BM11: N | BN11: N | BU11: 0 | BV11: 0 | BW11: 0 | BX11: 0 | BY11: 0 | BZ11: 0 | CA11: P | CB11: N | CC11: N | CD11: N | CE11: N | CF11: N | CG11: N | CH11: N | CI11: 0 | CJ11: N | CL11: 0 | CM11: N | CN11: 0 | CO11: N | CP11: N | CQ11: A | CR11: N | CT11: Y | CU11: 4 | CV11: N | CW11: N | CY11: N | DA11: Y | DC11: 0 | DD11: K | DG11: N | DH11: N | DI11: N | DJ11: N | DK11: N | DP11: 0 | DQ11: 0 | DR11: 90 | DS11: 90 | DT11: 0 | DU11: 0 | DV11: N | DW11: P | DX11: P | DY11: 17 | DZ11: N | EC11: F | ED11: 5 | EE11: R | EF11: 100 | EG11: N | EH11: N | EI11: N | EJ11: Z | EK11: N | EL11: 8 | EM11: N | EO11: 0 | EP11: P | EQ11: N | ER11: N | ES11: 0 | EV11: Y | EW11: 0 | EX11: N | EY11: N | EZ11: N | FA11: N | FB11: Y | FC11: N | FD11: B | FE11: N | FF11: N | FG11: N | FH11: N | FI11: N | FJ11: N | FK11: N | FL11: N | FM11: 0 | FN11: N | FO11: N | FP11: N | FQ11: N | FR11: 0 | FS11: 0 | FT11: N | FV11: 0 | FY11: N | FZ11: N | GA11: 6 | GB11: M | GC11: N | GD11: N | GE11: N | GF11: 0 | GG11: O | GH11: N | GI11: N | GJ11: N | GK11: Y | GL11: N | GM11: 0 | GN11: 0 | GO11: Y | GP11: Y | GQ11: N | GR11: 2 | GS11: 2 | GT11: 0 | GU11: 0 | GV11: 0 | GW11: N | GX11: Y | HB11: N | HC11: 0 | HD11: N | HE11: N | HG11: 0 | HH11: 0 | HI11: 0 | HJ11: 0 | HK11: 0 | HM11: N | HO11: 0 | HP11: 0 | HR11: 0 | HS11: 0 | HT11: 0 | HU11: 0 | HV11: D | HW11: W | HY11: 3 | HZ11: 3 | IA11: 6 | IB11: N | IC11: N | ID11: Y | IE11: N
A12: HF | B12: KUPEKS 3GP | C12: KUPEDES MK 3 BLN GP | D12: 212 | E12: POnB,Non Prog,KUPEDE | G12: 8 | H12: 110 | I12: IDR | J12: 7 | K12: 0.12 | L12: 0.42 | M12: 0.12 | N12: 0.42 | O12: N | P12: 1 | Q12: M | R12: 0 | S12: 0 | T12: Y | U12: Y | V12: N | W12: 0 | X12: I | Y12: 1 | Z12: 0 | AA12: 0 | AB12: 0 | AC12: 0 | AD12: 0 | AE12: 0 | AF12: 7 | AG12: 21 | AH12: 35 | AI12: 49 | AJ12: 63 | AK12: 77 | AL12: 0 | AM12: 0 | AN12: 0 | AO12: Y | AP12: R | AQ12: 0 | AR12: 0 | AS12: 1 | AT12: 0 | AU12: Y | BC12: 0 | BD12: 0 | BE12: 0 | BF12: 0 | BG12: 0 | BH12: 0 | BI12: N | BJ12: N | BK12: N | BL12: N | BM12: N | BN12: N | BU12: 0 | BV12: 0 | BW12: 0 | BX12: 0 | BY12: 0 | BZ12: 0 | CA12: P | CB12: N | CC12: N | CD12: N | CE12: N | CF12: N | CG12: N | CH12: N | CI12: 0 | CJ12: N | CL12: 0 | CM12: N | CN12: 0 | CO12: N | CP12: N | CQ12: A | CR12: N | CT12: Y | CU12: 4 | CV12: N | CW12: N | CY12: N | DA12: Y | DC12: 0 | DD12: K | DG12: N | DH12: N | DI12: N | DJ12: N | DK12: N | DP12: 0 | DQ12: 0 | DR12: 90 | DS12: 90 | DT12: 0 | DU12: 0 | DV12: N | DW12: P | DX12: P | DY12: 17 | DZ12: N | EC12: F | ED12: 5 | EE12: R | EF12: 100 | EG12: N | EH12: N | EI12: N | EJ12: Z | EK12: N | EL12: 8 | EM12: N | EO12: 0 | EP12: P | EQ12: N | ER12: N | ES12: 0 | EV12: Y | EW12: 0 | EX12: N | EY12: N | EZ12: N | FA12: N | FB12: Y | FC12: N | FD12: B | FE12: N | FF12: N | FG12: N | FH12: N | FI12: N | FJ12: N | FK12: N | FL12: N | FM12: 3 | FN12: N | FO12: N | FP12: N | FQ12: N | FR12: 0 | FS12: 0 | FT12: N | FV12: 0 | FY12: N | FZ12: N | GA12: 1 | GB12: M | GC12: N | GD12: N | GE12: N | GF12: 0 | GG12: O | GH12: N | GI12: N | GJ12: N | GK12: Y | GL12: N | GM12: 0 | GN12: 0 | GO12: Y | GP12: Y | GQ12: N | GR12: 2 | GS12: 2 | GT12: 0 | GU12: 0 | GV12: 0 | GW12: N | GX12: Y | HB12: N | HC12: 0 | HD12: N | HE12: N | HG12: 0 | HH12: 0 | HI12: 0 | HJ12: 0 | HK12: 0 | HM12: N | HO12: 0 | HP12: 0 | HR12: 0 | HS12: 0 | HT12: 0 | HU12: 0 | HV12: D | HW12: W | HY12: 3 | HZ12: 3 | IA12: 6 | IB12: Y | IC12: Y | ID12: Y | IE12: N
A13: HG | B13: KUPEKS 6GP | C13: KUPEDES MK 6 BLN GP | D13: 212 | E13: POnB,Non Prog,KUPEDE | G13: 8 | H13: 110 | I13: IDR | J13: 7 | K13: 0.12 | L13: 0.42 | M13: 0.12 | N13: 0.42 | O13: N | P13: 1 | Q13: M | R13: 0 | S13: 0 | T13: Y | U13: Y | V13: N | W13: 0 | X13: I | Y13: 1 | Z13: 0 | AA13: 0 | AB13: 0 | AC13: 0 | AD13: 0 | AE13: 0 | AF13: 7 | AG13: 21 | AH13: 35 | AI13: 49 | AJ13: 63 | AK13: 77 | AL13: 0 | AM13: 0 | AN13: 0 | AO13: Y | AP13: R | AQ13: 0 | AR13: 0 | AS13: 1 | AT13: 0 | AU13: Y | BC13: 0 | BD13: 0 | BE13: 0 | BF13: 0 | BG13: 0 | BH13: 0 | BI13: N | BJ13: N | BK13: N | BL13: N | BM13: N | BN13: N | BU13: 0 | BV13: 0 | BW13: 0 | BX13: 0 | BY13: 0 | BZ13: 0 | CA13: P | CB13: N | CC13: N | CD13: N | CE13: N | CF13: N | CG13: N | CH13: N | CI13: 0 | CJ13: N | CL13: 0 | CM13: N | CN13: 0 | CO13: N | CP13: N | CQ13: A | CR13: N | CT13: Y | CU13: 4 | CV13: N | CW13: N | CY13: N | DA13: Y | DC13: 0 | DD13: K | DG13: N | DH13: N | DI13: N | DJ13: N | DK13: N | DP13: 0 | DQ13: 0 | DR13: 90 | DS13: 90 | DT13: 0 | DU13: 0 | DV13: N | DW13: P | DX13: P | DY13: 17 | DZ13: N | EC13: F | ED13: 5 | EE13: R | EF13: 100 | EG13: N | EH13: N | EI13: N | EJ13: Z | EK13: N | EL13: 8 | EM13: N | EO13: 0 | EP13: P | EQ13: N | ER13: N | ES13: 0 | EV13: Y | EW13: 0 | EX13: N | EY13: N | EZ13: N | FA13: N | FB13: Y | FC13: N | FD13: B | FE13: N | FF13: N | FG13: N | FH13: N | FI13: N | FJ13: N | FK13: N | FL13: N | FM13: 6 | FN13: N | FO13: N | FP13: N | FQ13: N | FR13: 0 | FS13: 0 | FT13: N | FV13: 0 | FY13: N | FZ13: N | GA13: 1 | GB13: M | GC13: N | GD13: N | GE13: N | GF13: 0 | GG13: O | GH13: N | GI13: N | GJ13: N | GK13: Y | GL13: N | GM13: 0 | GN13: 0 | GO13: Y | GP13: Y | GQ13: N | GR13: 2 | GS13: 2 | GT13: 0 | GU13: 0 | GV13: 0 | GW13: N | GX13: Y | HB13: N | HC13: 0 | HD13: N | HE13: N | HG13: 0 | HH13: 0 | HI13: 0 | HJ13: 0 | HK13: 0 | HM13: N | HO13: 0 | HP13: 0 | HR13: 0 | HS13: 0 | HT13: 0 | HU13: 0 | HV13: D | HW13: W | HY13: 3 | HZ13: 3 | IA13: 6 | IB13: Y | IC13: Y | ID13: Y | IE13: N
... A18: HQ | B18: KUPTAP | C18: KUPEDES GOLBERTAP | D18: 212 | E18: KUPEDES, Divisi Mikr | G18: 8 | H18: 110 | I18: IDR | J18: 7 | K18: 0.12 | L18: 0.36 | M18: 0.12 | N18: 0.36 | O18: N | P18: 1 | Q18: M | R18: 0 | S18: 0 | T18: Y | U18: Y | V18: N | W18: 0 | X18: I | Y18: 1 | Z18: 0 | AA18: 0 | AB18: 0 | AC18: 0 | AD18: 0 | AE18: 0 | AF18: 7 | AG18: 21 | AH18: 35 | AI18: 49 | AJ18: 63 | AK18: 77 | AL18: 0 | AM18: 0 | AN18: 0 | AO18: Y | AP18: R | AQ18: 0 | AR18: 0 | AS18: 26 | AT18: 0 | AU18: Y | BC18: 0 | BD18: 0 | BE18: 0 | BF18: 0 | BG18: 0 | BH18: 0 | BI18: N | BJ18: N | BK18: N | BL18: N | BM18: N | BN18: N | BU18: 0 | BV18: 0 | BW18: 0 | BX18: 0 | BY18: 0 | BZ18: 0 | CA18: P | CB18: N | CC18: N | CD18: N | CE18: N | CF18: N | CG18: N | CH18: N | CI18: 0 | CJ18: N | CL18: 0 | CM18: N | CN18: 0 | CO18: N | CP18: N | CQ18: A | CR18: N | CT18: Y | CU18: 4 | CV18: N | CW18: N | CY18: N | DA18: Y | DC18: 0 | DD18: K | DG18: N | DH18: N | DI18: N | DJ18: N | DK18: N | DP18: 0 | DQ18: 0 | DR18: 90 | DS18: 90 | DT18: 0 | DU18: 0 | DV18: N | DW18: P | DX18: P | DY18: 17 | DZ18: N | EC18: F | ED18: 5 | EE18: R | EF18: 100 | EG18: N | EH18: N | EI18: N | EJ18: Z | EK18: N | EL18: 8 | EM18: N | EO18: 0 | EP18: P | EQ18: Y | ER18: N | ES18: 0 | EV18: Y | EW18: 0 | EX18: N | EY18: N | EZ18: N | FA18: N | FB18: Y | FC18: N | FD18: B | FE18: N | FF18: N | FG18: N | FH18: N | FI18: N | FJ18: N | FK18: N | FL18: N | FM18: 0 | FN18: N | FO18: N | FP18: N | FQ18: N | FR18: 0 | FS18: 0 | FT18: N | FV18: 0 | FY18: N | FZ18: N | GA18: 1 | GB18: M | GC18: N | GD18: N | GE18: N | GF18: 0 | GG18: O | GH18: N | GI18: N | GJ18: N | GK18: Y | GL18: N | GM18: 0 | GN18: 0 | GO18: Y | GP18: Y | GQ18: N | GR18: 2 | GS18: 2 | GT18: 0 | GU18: 0 | GV18: 0 | GW18: N | GX18: Y | HB18: N | HC18: 0 | HD18: Y | HE18: N | HG18: 0 | HH18: 0 | HI18: 0 | HJ18: 0 | HK18: 0 | HM18: N | HO18: 0 | HP18: 0 | HR18: 0 | HS18: 0 | HT18: 0 | HU18: 0 | HV18: D | HW18: W | HY18: 0 | HZ18: 0 | IA18: 0 | IB18: N | IC18: N | ID18: Y | IE18: N
A19: FH | B19: BRIGuna | C19: BRIGuna (KRETAP) | D19: 210 | E19: POnB,Non Prog,Konsum | G19: 8 | H19: 230 | I19: IDR | J19: 31 | K19: 0.007 | L19: 0.24 | M19: 0.007 | N19: 0.24 | O19: N | P19: 1 | Q19: M | R19: 0 | S19: 11 | T19: Y | U19: Y | V19: N | W19: 0 | X19: I | Y19: 1 | Z19: 0 | AA19: 0 | AB19: 0 | AC19: 0 | AD19: 0 | AE19: 0 | AF19: 7 | AG19: 21 | AH19: 36 | AI19: 49 | AJ19: 63 | AK19: 77 | AL19: 0 | AM19: 0 | AN19: 0 | AO19: Y | AP19: R | AQ19: 0 | AR19: 0 | AS19: 26 | AT19: 0 | AU19: Y | BC19: 0 | BD19: 0 | BE19: 0 | BF19: 0 | BG19: 0 | BH19: 0 | BI19: N | BJ19: N | BK19: N | BL19: N | BM19: N | BN19: N | BU19: 0 | BV19: 0 | BW19: 0 | BX19: 0 | BY19: 0 | BZ19: 0 | CA19: P | CB19: N | CC19: N | CD19: N | CE19: N | CF19: N | CG19: N | CH19: N | CI19: 0 | CJ19: N | CL19: 0 | CM19: N | CN19: 0 | CO19: N | CP19: N | CQ19: B | CR19: N | CT19: N | CU19: 4 | CV19: N | CW19: N | CY19: N | DA19: Y | DC19: 0 | DD19: T | DG19: N | DH19: N | DI19: N | DJ19: N | DK19: N | DP19: 0 | DQ19: 0 | DR19: 90 | DS19: 90 | DT19: 0 | DU19: 0 | DV19: N | DW19: P | DY19: 17 | DZ19: N | EC19: F | ED19: 5 | EE19: U | EF19: 100 | EG19: N | EH19: N | EI19: N | EJ19: N | EK19: N | EL19: 6 | EM19: N | EO19: 99 | EP19: P | EQ19: Y | ER19: N | ES19: 0 | EV19: Y | EW19: 0 | EX19: N | EY19: N | EZ19: N | FA19: N | FB19: Y | FC19: N | FD19: B | FE19: N | FF19: N | FG19: N | FH19: N | FI19: N | FJ19: N | FK19: N | FL19: N | FM19: 0 | FN19: N | FO19: N | FP19: N | FQ19: N | FR19: 0 | FS19: 0 | FT19: N | FV19: 0 | FY19: N | FZ19: N | GA19: 1 | GB19: M | GC19: N | GD19: N | GE19: N | GF19: 0 | GG19: O | GH19: N | GI19: N | GJ19: N | GK19: Y | GL19: N | GM19: 0 | GN19: 0 | GO19: Y | GP19: Y | GQ19: N | GR19: 0 | GS19: 0 | GT19: 0 | GU19: 0 | GV19: 0 | GW19: N | GX19: Y | HB19: N | HC19: 0 | HD19: N | HE19: Y | HF19: O | HG19: 0 | HH19: 0 | HI19: 0 | HJ19: 0 | HK19: 0 | HL19: 18 | HM19: N | HO19: 0 | HP19: 0 | HR19: 0 | HS19: 0 | HT19: 0 | HU19: 0 | HV19: D | HW19: W | HY19: 0 | HZ19: 0 | IA19: 0 | IB19: N | IC19: N | ID19: N | IE19: N
A20: FI | B20: BRIGunaSUN | C20: BRIGunaSUN TASPEN | D20: 210 | E20: POnB,Non Prog,Konsum | G20: 8 | H20: 230 | I20: IDR | J20: 31 | K20: 0.007 | L20: 0.24 | M20: 0.007 | N20: 0.24 | O20: N | P20: 1 | Q20: M | R20: 0 | S20: 11 | T20: Y | U20: Y | V20: N | W20: 0 | X20: I | Y20: 1 | Z20: 0 | AA20: 0 | AB20: 0 | AC20: 0 | AD20: 0 | AE20: 0 | AF20: 7 | AG20: 21 | AH20: 35 | AI20: 49 | AJ20: 63 | AK20: 77 | AL20: 0 | AM20: 0 | AN20: 0 | AO20: Y | AP20: R | AQ20: 0 | AR20: 0 | AS20: 26 | AT20: 0 | AU20: Y | BC20: 0 | BD20: 0 | BE20: 0 | BF20: 0 | BG20: 0 | BH20: 0 | BI20: N | BJ20: N | BK20: N | BL20: N | BM20: N | BN20: N | BU20: 0 | BV20: 0 | BW20: 0 | BX20: 0 | BY20: 0 | BZ20: 0 | CA20: P | CB20: N | CC20: N | CD20: N | CE20: N | CF20: N | CG20: N | CH20: N | CI20: 0 | CJ20: N | CL20: 0 | CM20: N | CN20: 0 | CO20: N | CP20: N | CQ20: B | CR20: N | CT20: N | CU20: 4 | CV20: N | CW20: N | CY20: N | DA20: Y | DC20: 0 | DD20: S | DG20: N | DH20: N | DI20: N | DJ20: N | DK20: N | DP20: 0 | DQ20: 0 | DR20: 90 | DS20: 90 | DT20: 0 | DU20: 0 | DV20: N | DW20: P | DX20: P | DY20: 17 | DZ20: N | EC20: F | ED20: 5 | EE20: U | EF20: 100 | EG20: N | EH20: N | EI20: N | EJ20: N | EK20: N | EL20: 6 | EM20: N | EO20: 99 | EP20: P | EQ20: Y | ER20: N | ES20: 0 | EV20: Y | EW20: 0 | EX20: N | EY20: N | EZ20: N | FA20: N | FB20: Y | FC20: N | FD20: B | FE20: N | FF20: N | FG20: N | FH20: N | FI20: N | FJ20: N | FK20: N | FL20: N | FM20: 0 | FN20: N | FO20: N | FP20: N | FQ20: N | FR20: 0 | FS20: 0 | FT20: N | FV20: 0 | FY20: N | FZ20: N | GA20: 1 | GB20: M | GC20: N | GD20: N | GE20: N | GF20: 0 | GG20: O | GH20: N | GI20: N | GJ20: N | GK20: Y | GL20: N | GM20: 0 | GN20: 0 | GO20: Y | GP20: Y | GQ20: N | GR20: 0 | GS20: 0 | GT20: 0 | GU20: 0 | GV20: 0 | GW20: N | GX20: Y | HB20: N | HC20: 0 | HD20: N | HE20: Y | HF20: O | HG20: 0 | HH20: 0 | HI20: 0 | HJ20: 0 | HK20: 0 | HL20: 18 | HM20: N | HO20: 0 | HP20: 0 | HR20: 0 | HS20: 0 | HT20: 0 | HU20: 0 | HV20: D | HW20: W | HY20: 0 | HZ20: 0 | IA20: 0 | IB20: N | IC20: N | ID20: N | IE20: N
A21: BQ | B21: KI EBJ | C21: KI EBJ 4,3,2,1 | D21: 106 | E21: On B/S,Program,KI-ID | G21: 8 | H21: 310 | I21: IDR | J21: 31 | K21: 0.08 | L21: 0.15 | M21: 0.08 | N21: 0.15 | O21: N | P21: 1 | Q21: M | R21: 6 | S21: 0 | T21: Y | U21: Y | V21: N | W21: 0 | Y21: 1 | Z21: 0 | AA21: 0 | AB21: 0 | AC21: 0 | AD21: 0 | AE21: 0 | AF21: 7 | AG21: 21 | AH21: 1 | AI21: 0 | AJ21: 0 | AK21: 0 | AL21: 0 | AM21: 0 | AN21: 0 | AO21: Y | AP21: R | AQ21: 0 | AR21: 0 | AS21: 1 | AT21: 0 | AU21: Y | BC21: 0 | BD21: 0 | BE21: 0 | BF21: 0 | BG21: 0 | BH21: 0 | BI21: N | BJ21: N | BK21: N | BL21: N | BM21: N | BN21: N | BU21: 0 | BV21: 0 | BW21: 0 | BX21: 0 | BY21: 0 | BZ21: 0 | CA21: P | CB21: N | CC21: N | CD21: N | CE21: N | CF21: N | CG21: N | CH21: N | CI21: 0 | CJ21: N | CL21: 0 | CM21: N | CN21: 0 | CO21: N | CP21: N | CR21: N | CT21: Y | CU21: 4 | CV21: N | CW21: N | CY21: N | DA21: Y | DC21: 0 | DD21: O | DG21: N | DH21: N | DI21: N | DJ21: N | DK21: N | DP21: 0 | DQ21: 0 | DR21: 90 | DS21: 90 | DT21: 0 | DU21: 0 | DV21: N | DW21: P | DX21: P | DY21: 17 | DZ21: N | EC21: D | ED21: 2 | EE21: R | EF21: 100 | EG21: N | EH21: N | EI21: N | EJ21: N | EK21: N | EL21: 2 | EM21: N | EO21: 99 | EP21: P | EQ21: Y | ER21: N | ES21: 0 | EV21: Y | EW21: 6 | EX21: N | EY21: N | EZ21: N | FA21: N | FB21: Y | FC21: N | FD21: B | FE21: N | FF21: N | FG21: N | FH21: N | FI21: N | FJ21: N | FK21: N | FL21: N | FM21: 0 | FN21: N | FO21: N | FP21: N | FQ21: N | FR21: 0 | FS21: 0 | FT21: N | FV21: 0 | FY21: N | FZ21: N | GA21: 1 | GB21: M | GC21: N | GD21: N | GE21: N | GF21: 0 | GG21: O | GH21: N | GI21: Y | GJ21: N | GK21: Y | GL21: P | GM21: 0 | GN21: 0 | GO21: Y | GP21: Y | GQ21: N | GR21: 2 | GS21: 0 | GT21: 0 | GU21: 0 | GV21: 0 | GW21: N | GX21: Y | HB21: N | HC21: 0 | HD21: N | HE21: N | HG21: 0 | HH21: 0 | HI21: 0 | HJ21: 0 | HK21: 0 | HM21: N | HO21: 0 | HP21: 0 | HR21: 0 | HS21: 0 | HT21: 0 | HU21: 0 | HV21: D | HW21: W | HY21: 0 | HZ21: 0 | IA21: 0 | IB21: N | IC21: N | ID21: N | IE21: N
A22: EP | B22: INV KANPUS | C22: KI PRAKARSA KP PROGR | D22: 205 | E22: POnB,Non Prog,KI-IDR | G22: 8 | H22: 240 | I22: IDR | J22: 31 | K22: 0.06 | L22: 0.3 | M22: 0.06 | N22: 0.3 | O22: N | P22: 1 | Q22: M | R22: 6 | S22: 10 | T22: Y | U22: Y | V22: N | W22: 0 | X22: N | Y22: 1 | Z22: 0 | AA22: 0 | AB22: 0 | AC22: 0 | AD22: 0 | AE22: 0 | AF22: 7 | AG22: 21 | AH22: 35 | AI22: 49 | AJ22: 63 | AK22: 77 | AL22: 0 | AM22: 0 | AN22: 0 | AO22: Y | AP22: R | AQ22: 0 | AR22: 0 | AS22: 1 | AT22: 0 | AU22: Y | BA22: O | BC22: 0 | BD22: 0 | BE22: 0 | BF22: 0 | BG22: 0 | BH22: 0 | BI22: N | BJ22: N | BK22: N | BL22: N | BM22: N | BN22: N | BS22: V | BU22: 0 | BV22: 0 | BW22: 0 | BX22: 0 | BY22: 0 | BZ22: 0 | CA22: P | CB22: N | CC22: N | CD22: N | CE22: N | CF22: N | CG22: N | CH22: Y | CI22: 0 | CJ22: N | CL22: 0 | CM22: N | CN22: 0 | CO22: Y | CP22: N | CQ22: B | CR22: N | CT22: Y | CU22: 4 | CV22: Y | CW22: N | CY22: N | DA22: Y | DC22: 0 | DD22: O | DG22: N | DH22: N | DI22: N | DJ22: N | DK22: N | DP22: 0 | DQ22: 0 | DR22: 90 | DS22: 90 | DT22: 0 | DU22: 0 | DV22: N | DW22: P | DX22: P | DY22: 17 | DZ22: N | EC22: D | ED22: 0 | EE22: R | EF22: 100 | EG22: N | EH22: N | EI22: N | EJ22: N | EK22: N | EL22: 5 | EM22: N | EO22: 99 | EP22: P | EQ22: Y | ER22: N | ES22: 0 | EV22: Y | EW22: 6 | EX22: N | EY22: N | EZ22: N | FA22: N | FB22: N | FC22: N | FD22: B | FE22: N | FF22: N | FG22: N | FH22: N | FI22: N | FJ22: N | FK22: N | FL22: N | FM22: 0 | FN22: N | FO22: N | FP22: N | FQ22: N | FR22: 0 | FS22: 0 | FT22: Y | FV22: 0 | FY22: N | FZ22: N | GA22: 1 | GB22: M | GC22: N | GD22: N | GE22: N | GF22: 0 | GG22: O | GH22: N | GI22: Y | GJ22: N | GK22: Y | GL22: P | GM22: 0 | GN22: 0 | GO22: Y | GP22: Y | GQ22: N | GR22: 0 | GS22: 0 | GT22: 0 | GU22: 0 | GV22: 0 | GW22: N | GX22: N | GY22: C | GZ22: C | HB22: N | HC22: 0 | HD22: N | HE22: N | HG22: 0 | HH22: 0 | HI22: 0 | HJ22: 0 | HK22: 0 | HM22: N | HO22: 0 | HP22: 0 | HR22: 0 | HS22: 0 | HT22: 0 | HU22: 0 | HV22: D | HW22: W | HY22: 0 | HZ22: 0 | IA22: 0 | IB22: N | IC22: N | ID22: N | IE22: N
A23: ER | B23: INV KANPUS | C23: KI PRAKARSA KP DKM2 | D23: 208 | E23: POnB,Non Prog,KI-IDR | G23: 8 | H23: 320 | I23: IDR | J23: 31 | K23: 0.01 | L23: 0.3 | M23: 0.01 | N23: 0.3 | O23: N | P23: 1 | Q23: M | R23: 6 | S23: 10 | T23: Y | U23: Y | V23: N | W23: 0 | X23: N | Y23: 1 | Z23: 0 | AA23: 0 | AB23: 0 | AC23: 0 | AD23: 0 | AE23: 0 | AF23: 7 | AG23: 21 | AH23: 35 | AI23: 49 | AJ23: 63 | AK23: 77 | AL23: 0 | AM23: 0 | AN23: 0 | AO23: Y | AP23: R | AQ23: 0 | AR23: 0 | AS23: 1 | AT23: 0 | AU23: Y | BA23: O | BC23: 0 | BD23: 0 | BE23: 0 | BF23: 0 | BG23: 0 | BH23: 0 | BI23: N | BJ23: N | BK23: N | BL23: N | BM23: N | BN23: N | BS23: V | BU23: 0 | BV23: 0 | BW23: 0 | BX23: 0 | BY23: 0 | BZ23: 0 | CA23: P | CB23: N | CC23: N | CD23: N | CE23: N | CF23: N | CG23: N | CH23: Y | CI23: 0 | CJ23: N | CL23: 0 | CM23: N | CN23: 0 | CO23: Y | CP23: N | CQ23: B | CR23: N | CT23: Y | CU23: 4 | CV23: Y | CW23: N | CY23: N | DA23: Y | DC23: 0 | DD23: O | DG23: N | DH23: N | DI23: N | DJ23: N | DK23: N | DP23: 0 | DQ23: 0 | DR23: 90 | DS23: 90 | DT23: 0 | DU23: 0 | DV23: N | DW23: P | DX23: N | DZ23: N | EC23: D | ED23: 0 | EE23: R | EF23: 100 | EG23: N | EH23: N | EI23: N | EJ23: N | EK23: N | EL23: 5 | EM23: N | EO23: 99 | EP23: P | EQ23: Y | ER23: N | ES23: 0 | EV23: Y | EW23: 6 | EX23: N | EY23: N | EZ23: N | FA23: N | FB23: N | FC23: N | FD23: B | FE23: N | FF23: N | FG23: N | FH23: N | FI23: N | FJ23: N | FK23: N | FL23: N | FM23: 0 | FN23: N | FO23: N | FP23: N | FQ23: N | FR23: 0 | FS23: 0 | FT23: Y | FV23: 0 | FY23: N | FZ23: N | GA23: 1 | GB23: M | GC23: N | GD23: N | GE23: N | GF23: 0 | GH23: N | GI23: Y | GJ23: N | GK23: Y | GL23: P | GM23: 0 | GN23: 0 | GO23: Y | GP23: Y | GQ23: N | GR23: 0 | GS23: 0 | GT23: 0 | GU23: 0 | GV23: 0 | GW23: N | GX23: N | GY23: C | GZ23: C | HB23: N | HC23: 0 | HD23: N | HE23: Y | HF23: O | HG23: 0 | HH23: 0 | HI23: 0.02 | HJ23: 0 | HK23: 0 | HL23: 18 | HM23: N | HO23: 0 | HP23: 0 | HR23: 0 | HS23: 0 | HT23: 0 | HU23: 0 | HV23: D | HW23: W | HY23: 0 | HZ23: 0 | IA23: 0 | IB23: N | IC23: N | ID23: N | IE23: N
A24: EQ | B24: INV KANPUS | C24: KI PRAKARSA KP DKM1 | D24: 207 | E24: POnB,Non Prog,KI-IDR | G24: 8 | H24: 310 | I24: IDR | J24: 31 | K24: 0.001 | L24: 0.3 | M24: 0.001 | N24: 0.3 | O24: N | P24: 3 | Q24: M | R24: 6 | S24: 10 | T24: Y | U24: Y | V24: N | W24: 0 | X24: N | Y24: 1 | Z24: 0 | AA24: 0 | AB24: 0 | AC24: 0 | AD24: 0 | AE24: 0 | AF24: 7 | AG24: 21 | AH24: 35 | AI24: 49 | AJ24: 63 | AK24: 77 | AL24: 0 | AM24: 0 | AN24: 0 | AO24: Y | AP24: R | AQ24: 0 | AR24: 0 | AS24: 1 | AT24: 0 | AU24: Y | BA24: O | BC24: 0 | BD24: 0 | BE24: 0 | BF24: 0 | BG24: 0 | BH24: 0 | BI24: N | BJ24: N | BK24: N | BL24: N | BM24: N | BN24: N | BS24: V | BU24: 0 | BV24: 0 | BW24: 0 | BX24: 0 | BY24: 0 | BZ24: 0 | CA24: P | CB24: N | CC24: N | CD24: N | CE24: N | CF24: N | CG24: N | CH24: Y | CI24: 0 | CJ24: N | CL24: 0 | CM24: N | CN24: 0 | CO24: Y | CP24: N | CQ24: B | CR24: N | CT24: Y | CU24: 4 | CV24: Y | CW24: N | CY24: N | DA24: Y | DC24: 0 | DD24: O | DG24: N | DH24: N | DI24: N | DJ24: N | DK24: N | DP24: 0 | DQ24: 0 | DR24: 90 | DS24: 90 | DT24: 0 | DU24: 0 | DV24: N | DW24: P | DX24: P | DY24: 17 | DZ24: N | EC24: D | ED24: 0 | EE24: R | EF24: 100 | EG24: N | EH24: N | EI24: N | EJ24: N | EK24: N | EL24: 5 | EM24: N | EO24: 99 | EP24: P | EQ24: Y | ER24: N | ES24: 0 | EV24: Y | EW24: 6 | EX24: N | EY24: N | EZ24: N | FA24: N | FB24: N | FC24: N | FD24: B | FE24: N | FF24: N | FG24: N | FH24: N | FI24: N | FJ24: N | FK24: N | FL24: N | FM24: 0 | FN24: N | FO24: N | FP24: N | FQ24: N | FR24: 0 | FS24: 0 | FT24: Y | FV24: 0 | FY24: N | FZ24: N | GA24: 1 | GB24: M | GC24: N | GD24: N | GE24: N | GF24: 0 | GG24: O | GH24: N | GI24: Y | GJ24: N | GK24: Y | GL24: P | GM24: 0 | GN24: 0 | GO24: Y | GP24: Y | GQ24: N | GR24: 0 | GS24: 0 | GT24: 0 | GU24: 0 | GV24: 0 | GW24: N | GX24: N | GY24: C | GZ24: C | HB24: N | HC24: 0 | HD24: N | HE24: Y | HF24: O | HG24: 0 | HH24: 0 | HI24: 0.02 | HJ24: 0 | HK24: 0 | HL24: 18 | HM24: N | HO24: 0 | HP24: 0 | HR24: 0 | HS24: 0 | HT24: 0 | HU24: 0 | HV24: D | HW24: W | HY24: 0 | HZ24: 0 | IA24: 0 | IB24: N | IC24: N | ID24: N | IE24: N
A25: EM | B25: KI SMIEP | C25: KI DLM RANGKA SMIEP | D25: 207 | E25: POnB,Non Prog,KI-IDR | G25: 8 | H25: 310 | I25: IDR | J25: 31 | K25: 0.06 | L25: 0.3 | M25: 0.06 | N25: 0.3 | O25: N | P25: 1 | Q25: M | R25: 6 | S25: 10 | T25: Y | U25: Y | V25: N | W25: 0 | X25: I | Y25: 1 | Z25: 0 | AA25: 0 | AB25: 0 | AC25: 0 | AD25: 0 | AE25: 0 | AF25: 7 | AG25: 21 | AH25: 35 | AI25: 49 | AJ25: 63 | AK25: 77 | AL25: 0 | AM25: 0 | AN25: 0 | AO25: Y | AP25: R | AQ25: 0 | AR25: 0 | AS25: 1 | AT25: 0 | AU25: Y | BC25: 0 | BD25: 0 | BE25: 0 | BF25: 0 | BG25: 0 | BH25: 0 | BI25: N | BJ25: N | BK25: N | BL25: N | BM25: N | BN25: N | BU25: 0 | BV25: 0 | BW25: 0 | BX25: 0 | BY25: 0 | BZ25: 0 | CA25: P | CB25: N | CC25: N | CD25: N | CE25: N | CF25: N | CG25: N | CH25: Y | CI25: 0 | CJ25: N | CL25: 0 | CM25: N | CN25: 0 | CO25: Y | CP25: N | CR25: N | CT25: Y | CU25: 4 | CV25: Y | CW25: N | CY25: N | DA25: Y | DC25: 0 | DD25: O | DG25: N | DH25: N | DI25: N | DJ25: N | DK25: N | DP25: 0 | DQ25: 0 | DR25: 90 | DS25: 90 | DT25: 0 | DU25: 0 | DV25: N | DW25: P | DX25: P | DY25: 17 | DZ25: N | EC25: D | ED25: 0 | EE25: R | EF25: 100 | EG25: N | EH25: N | EI25: N | EJ25: N | EK25: N | EL25: 5 | EM25: N | EO25: 99 | EP25: P | EQ25: Y | ER25: N | ES25: 0 | EV25: Y | EW25: 6 | EX25: N | EY25: N | EZ25: N | FA25: N | FB25: N | FC25: N | FD25: B | FE25: N | FF25: N | FG25: N | FH25: N | FI25: N | FJ25: N | FK25: N | FL25: N | FM25: 0 | FN25: N | FO25: N | FP25: N | FQ25: N | FR25: 0 | FS25: 0 | FT25: Y | FV25: 0 | FY25: N | FZ25: N | GA25: 1 | GB25: M | GC25: N | GD25: N | GE25: N | GF25: 0 | GG25: O | GH25: N | GI25: Y | GJ25: N | GK25: Y | GL25: P | GM25: 0 | GN25: 0 | GO25: Y | GP25: Y | GQ25: N | GR25: 0 | GS25: 0 | GT25: 0 | GU25: 0 | GV25: 0 | GW25: N | GX25: N | GY25: C | GZ25: C | HB25: N | HC25: 0 | HD25: N | HE25: N | HG25: 0 | HH25: 0 | HI25: 0 | HJ25: 0 | HK25: 0 | HM25: N | HO25: 0 | HP25: 0 | HR25: 0 | HS25: 0 | HT25: 0 | HU25: 0 | HV25: D | HW25: W | HY25: 0 | HZ25: 0 | IA25: 0 | IB25: N | IC25: N | ID25: N | IE25: N
A26: EL | B26: KI 75 JUTA | C26: KI S/D 75 JUTA | D26: 206 | E26: POnB,Non Prog,KI-IDR | G26: 8 | H26: 230 | I26: IDR | J26: 31 | K26: 0.06 | L26: 0.3 | M26: 0.06 | N26: 0.3 | O26: N | P26: 1 | Q26: M | R26: 6 | S26: 10 | T26: Y | U26: Y | V26: N | W26: 0 | X26: I | Y26: 1 | Z26: 0 | AA26: 0 | AB26: 0 | AC26: 0 | AD26: 0 | AE26: 0 | AF26: 7 | AG26: 21 | AH26: 35 | AI26: 49 | AJ26: 63 | AK26: 77 | AL26: 0 | AM26: 0 | AN26: 0 | AO26: Y | AP26: R | AQ26: 0 | AR26: 0 | AS26: 1 | AT26: 0 | AU26: Y | BC26: 0 | BD26: 0 | BE26: 0 | BF26: 0 | BG26: 0 | BH26: 0 | BI26: N | BJ26: N | BK26: N | BL26: N | BM26: N | BN26: N | BU26: 0 | BV26: 0 | BW26: 0 | BX26: 0 | BY26: 0 | BZ26: 0 | CA26: P | CB26: N | CC26: N | CD26: N | CE26: N | CF26: N | CG26: N | CH26: Y | CI26: 0 | CJ26: N | CL26: 0 | CM26: N | CN26: 0 | CO26: Y | CP26: N | CQ26: A | CR26: N | CT26: Y | CU26: 4 | CV26: Y | CW26: N | CY26: N | DA26: Y | DC26: 0 | DD26: O | DG26: N | DH26: N | DI26: N | DJ26: N | DK26: N | DP26: 0 | DQ26: 0 | DR26: 90 | DS26: 90 | DT26: 0 | DU26: 0 | DV26: N | DW26: P | DX26: P | DY26: 17 | DZ26: N | EC26: D | ED26: 0 | EE26: R | EF26: 100 | EG26: N | EH26: N | EI26: N | EJ26: N | EK26: N | EL26: 5 | EM26: N | EO26: 99 | EP26: P | EQ26: Y | ER26: N | ES26: 0 | EV26: Y | EW26: 6 | EX26: N | EY26: N | EZ26: N | FA26: N | FB26: N | FC26: N | FD26: B | FE26: N | FF26: N | FG26: N | FH26: N | FI26: N | FJ26: N | FK26: N | FL26: N | FM26: 0 | FN26: N | FO26: N | FP26: N | FQ26: N | FR26: 0 | FS26: 0 | FT26: Y | FV26: 0 | FY26: N | FZ26: N | GA26: 1 | GB26: M | GC26: N | GD26: N | GE26: N | GF26: 0 | GG26: O | GH26: N | GI26: Y | GJ26: N | GK26: Y | GL26: P | GM26: 0 | GN26: 0 | GO26: Y | GP26: Y | GQ26: N | GR26: 0 | GS26: 0 | GT26: 0 | GU26: 0 | GV26: 0 | GW26: N | GX26: N | GY26: C | GZ26: C | HB26: N | HC26: 0 | HD26: N | HE26: N | HG26: 0 | HH26: 0 | HI26: 0 | HJ26: 0 | HK26: 0 | HM26: N | HO26: 0 | HP26: 0 | HR26: 0 | HS26: 0 | HT26: 0 | HU26: 0 | HV26: D | HW26: W | HY26: 0 | HZ26: 0 | IA26: 0 | IB26: N | IC26: N | ID26: N | IE26: N
A27: FE | B27: KRETUNG | C27: PERS-NO-AN JK.PENDEK | D27: 210 | E27: POnB,Non Prog,Konsum | G27: 8 | H27: 230 | I27: IDR | J27: 0 | K27: 0.055 | L27: 0.0551 | M27: 0.055 | N27: 0.0551 | O27: N | P27: 1 | Q27: M | R27: 0 | S27: 0 | T27: Y | U27: Y | V27: N | W27: 0 | X27: I | Y27: 1 | Z27: 0 | AA27: 0 | AB27: 0 | AC27: 0 | AD27: 0 | AE27: 0 | AF27: 7 | AG27: 21 | AH27: 35 | AI27: 49 | AJ27: 63 | AK27: 77 | AL27: 0 | AM27: 0 | AN27: 0 | AO27: Y | AP27: R | AQ27: 0 | AR27: 0 | AS27: 26 | AT27: 0 | AU27: Y | BC27: 0 | BD27: 0 | BE27: 0 | BF27: 0 | BG27: 0 | BH27: 0 | BI27: N | BJ27: N | BK27: N | BL27: N | BM27: N | BN27: N | BO27: V | BU27: 0 | BV27: 0 | BW27: 0 | BX27: 0 | BY27: 0 | BZ27: 0 | CA27: P | CB27: N | CC27: N | CD27: N | CE27: N | CF27: N | CG27: N | CH27: N | CI27: 0 | CJ27: N | CL27: 0 | CM27: N | CN27: 0 | CO27: N | CP27: N | CQ27: B | CR27: N | CT27: Y | CU27: 4 | CV27: N | CW27: N | CY27: N | DA27: N | DC27: 0 | DD27: T | DG27: N | DH27: N | DI27: N | DJ27: N | DK27: N | DP27: 0 | DQ27: 0 | DR27: 90 | DS27: 90 | DT27: 0 | DU27: 0 | DV27: N | DW27: P | DX27: P | DY27: 17 | DZ27: N | EC27: M | ED27: 5 | EE27: U | EF27: 500 | EG27: N | EH27: N | EI27: N | EJ27: Z | EK27: N | EL27: 6 | EM27: N | EO27: 0 | EP27: P | EQ27: N | ER27: N | ES27: 0 | EV27: Y | EW27: 0 | EX27: N | EY27: N | EZ27: N | FA27: N | FB27: Y | FC27: N | FD27: B | FE27: N | FF27: N | FG27: N | FH27: N | FI27: N | FJ27: N | FK27: N | FL27: N | FM27: 0 | FN27: N | FO27: N | FP27: N | FQ27: N | FR27: 0 | FS27: 0 | FT27: N | FV27: 0 | FY27: N | FZ27: N | GA27: 1 | GB27: M | GC27: N | GD27: N | GE27: N | GF27: 0 | GG27: O | GH27: N | GI27: N | GJ27: N | GK27: Y | GL27: N | GM27: 0 | GN27: 0 | GO27: Y | GP27: Y | GQ27: N | GR27: 0 | GS27: 0 | GT27: 0 | GU27: 0 | GV27: 0 | GW27: N | GX27: Y | HB27: N | HC27: 0 | HD27: N | HE27: N | HG27: 0 | HH27: 0 | HI27: 0 | HJ27: 0 | HK27: 0 | HM27: N | HO27: 0 | HP27: 0 | HR27: 0 | HS27: 0 | HT27: 0 | HU27: 0 | HV27: D | HW27: W | HY27: 0 | HZ27: 0 | IA27: 0 | IB27: N | IC27: N | ID27: N | IE27: N
A28: EK | B28: RC INVES | C28: RC INVESTASI | D28: 206 | E28: POnB,Non Prog,KI-IDR | G28: 8 | H28: 230 | I28: IDR | J28: 31 | K28: 0.04 | L28: 0.3 | M28: 0.04 | N28: 0.3 | O28: N | P28: 1 | Q28: M | R28: 6 | S28: 10 | T28: Y | U28: Y | V28: N | W28: 0 | X28: N | Y28: 1 | Z28: 0 | AA28: 0 | AB28: 0 | AC28: 0 | AD28: 0 | AE28: 0 | AF28: 7 | AG28: 21 | AH28: 35 | AI28: 49 | AJ28: 63 | AK28: 77 | AL28: 0 | AM28: 0 | AN28: 0 | AO28: Y | AP28: R | AQ28: 0 | AR28: 0 | AS28: 1 | AT28: 0 | AU28: Y | BC28: 0 | BD28: 0 | BE28: 0 | BF28: 0 | BG28: 0 | BH28: 0 | BI28: N | BJ28: N | BK28: N | BL28: N | BM28: N | BN28: N | BU28: 0 | BV28: 0 | BW28: 0 | BX28: 0 | BY28: 0 | BZ28: 0 | CA28: P | CB28: N | CC28: N | CD28: N | CE28: N | CF28: N | CG28: N | CH28: Y | CI28: 0 | CJ28: N | CL28: 0 | CM28: N | CN28: 0 | CO28: Y | CP28: N | CQ28: B | CR28: N | CT28: Y | CU28: 4 | CV28: Y | CW28: N | CY28: N | DA28: Y | DC28: 0 | DD28: O | DG28: N | DH28: N | DI28: N | DJ28: N | DK28: N | DP28: 0 | DQ28: 0 | DR28: 90 | DS28: 90 | DT28: 0 | DU28: 0 | DV28: N | DW28: P | DX28: P | DY28: 17 | DZ28: N | EC28: D | ED28: 0 | EE28: R | EF28: 100 | EG28: N | EH28: N | EI28: N | EJ28: N | EK28: N | EL28: 5 | EM28: N | EO28: 99 | EP28: P | EQ28: Y | ER28: N | ES28: 0 | EV28: Y | EW28: 6 | EX28: N | EY28: N | EZ28: N | FA28: N | FB28: N | FC28: N | FD28: B | FE28: N | FF28: N | FG28: N | FH28: N | FI28: N | FJ28: N | FK28: N | FL28: N | FM28: 0 | FN28: N | FO28: N | FP28: N | FQ28: N | FR28: 0 | FS28: 0 | FT28: Y | FV28: 0 | FY28: N | FZ28: N | GA28: 1 | GB28: M | GC28: N | GD28: N | GE28: N | GF28: 0 | GG28: O | GH28: N | GI28: Y | GJ28: N | GK28: Y | GL28: P | GM28: 0 | GN28: 0 | GO28: Y | GP28: Y | GQ28: N | GR28: 0 | GS28: 0 | GT28: 0 | GU28: 0 | GV28: 0 | GW28: N | GX28: N | GY28: C | GZ28: C | HB28: N | HC28: 0 | HD28: N | HE28: N | HG28: 0 | HH28: 0 | HI28: 0 | HJ28: 0 | HK28: 0 | HM28: N | HO28: 0 | HP28: 0 | HR28: 0 | HS28: 0 | HT28: 0 | HU28: 0 | HV28: D | HW28: W | HY28: 0 | HZ28: 0 | IA28: 0 | IB28: N | IC28: N | ID28: N | IE28: N
A29: EJ | B29: KIK UMUM | C29: KIK UMUM | D29: 206 | E29: POnB,Non Prog,KI-IDR | G29: 8 | H29: 230 | I29: IDR | J29: 31 | K29: 0.06 | L29: 0.3 | M29: 0.06 | N29: 0.3 | O29: N | P29: 1 | Q29: M | R29: 6 | S29: 10 | T29: Y | U29: Y | V29: N | W29: 0 | X29: N | Y29: 1 | Z29: 0 | AA29: 0 | AB29: 0 | AC29: 0 | AD29: 0 | AE29: 0 | AF29: 7 | AG29: 21 | AH29: 35 | AI29: 49 | AJ29: 63 | AK29: 77 | AL29: 0 | AM29: 0 | AN29: 0 | AO29: Y | AP29: R | AQ29: 0 | AR29: 0 | AS29: 1 | AT29: 0 | AU29: Y | BC29: 0 | BD29: 0 | BE29: 0 | BF29: 0 | BG29: 0 | BH29: 0 | BI29: N | BJ29: N | BK29: N | BL29: N | BM29: N | BN29: N | BU29: 0 | BV29: 0 | BW29: 0 | BX29: 0 | BY29: 0 | BZ29: 0 | CA29: P | CB29: N | CC29: N | CD29: N | CE29: N | CF29: N | CG29: N | CH29: Y | CI29: 0 | CJ29: N | CL29: 0 | CM29: N | CN29: 0 | CO29: Y | CP29: N | CQ29: B | CR29: N | CT29: Y | CU29: 4 | CV29: Y | CW29: N | CY29: N | DA29: Y | DC29: 0 | DD29: O | DG29: N | DH29: N | DI29: N | DJ29: N | DK29: N | DP29: 0 | DQ29: 0 | DR29: 90 | DS29: 90 | DT29: 0 | DU29: 0 | DV29: N | DW29: P | DX29: P | DY29: 17 | DZ29: N | EC29: D | ED29: 0 | EE29: R | EF29: 100 | EG29: N | EH29: N | EI29: N | EJ29: N | EK29: N | EL29: 5 | EM29: N | EO29: 99 | EP29: P | EQ29: Y | ER29: N | ES29: 0 | EV29: Y | EW29: 6 | EX29: N | EY29: N | EZ29: N | FA29: N | FB29: N | FC29: N | FD29: B | FE29: N | FF29: N | FG29: N | FH29: N | FI29: N | FJ29: N | FK29: N | FL29: N | FM29: 0 | FN29: N | FO29: N | FP29: N | FQ29: N | FR29: 0 | FS29: 0 | FT29: Y | FV29: 0 | FY29: N | FZ29: N | GA29: 1 | GB29: M | GC29: N | GD29: N | GE29: N | GF29: 0 | GG29: O | GH29: N | GI29: Y | GJ29: N | GK29: Y | GL29: P | GM29: 0 | GN29: 0 | GO29: Y | GP29: Y | GQ29: N | GR29: 0 | GS29: 0 | GT29: 0 | GU29: 0 | GV29: 0 | GW29: N | GX29: N | GY29: C | GZ29: C | HB29: N | HC29: 0 | HD29: N | HE29: N | HG29: 0 | HH29: 0 | HI29: 0 | HJ29: 0 | HK29: 0 | HM29: N | HO29: 0 | HP29: 0 | HR29: 0 | HS29: 0 | HT29: 0 | HU29: 0 | HV29: D | HW29: W | HY29: 0 | HZ29: 0 | IA29: 0 | IB29: N | IC29: N | ID29: N | IE29: N
A30: EI | B30: KKI | C30: KRD KECIL INV DKM1 | D30: 207 | E30: POnB,Non Prog,KI-IDR | G30: 8 | H30: 310 | I30: IDR | J30: 31 | K30: 0.06 | L30: 0.3 | M30: 0.06 | N30: 0.3 | O30: N | P30: 1 | Q30: M | R30: 6 | S30: 10 | T30: Y | U30: Y | V30: N | W30: 0 | X30: N | Y30: 1 | Z30: 0 | AA30: 0 | AB30: 0 | AC30: 0 | AD30: 0 | AE30: 0 | AF30: 7 | AG30: 21 | AH30: 35 | AI30: 49 | AJ30: 63 | AK30: 77 | AL30: 0 | AM30: 0 | AN30: 0 | AO30: Y | AP30: R | AQ30: 0 | AR30: 0 | AS30: 1 | AT30: 0 | AU30: Y | BC30: 0 | BD30: 0 | BE30: 0 | BF30: 0 | BG30: 0 | BH30: 0 | BI30: N | BJ30: N | BK30: N | BL30: N | BM30: N | BN30: N | BU30: 0 | BV30: 0 | BW30: 0 | BX30: 0 | BY30: 0 | BZ30: 0 | CA30: P | CB30: N | CC30: N | CD30: N | CE30: N | CF30: N | CG30: N | CH30: Y | CI30: 0 | CJ30: N | CL30: 0 | CM30: N | CN30: 0 | CO30: Y | CP30: N | CQ30: B | CR30: N | CT30: Y | CU30: 4 | CV30: Y | CW30: N | CY30: N | DA30: Y | DC30: 0 | DD30: O | DG30: N | DH30: N | DI30: N | DJ30: N | DK30: N | DP30: 0 | DQ30: 0 | DR30: 90 | DS30: 90 | DT30: 0 | DU30: 0 | DV30: N | DW30: P | DX30: P | DY30: 17 | DZ30: N | EC30: D | ED30: 0 | EE30: R | EF30: 100 | EG30: N | EH30: N | EI30: N | EJ30: N | EK30: N | EL30: 5 | EM30: N | EO30: 99 | EP30: P | EQ30: Y | ER30: N | ES30: 0 | EV30: Y | EW30: 6 | EX30: N | EY30: N | EZ30: N | FA30: N | FB30: N | FC30: N | FD30: B | FE30: N | FF30: N | FG30: N | FH30: N | FI30: N | FJ30: N | FK30: N | FL30: N | FM30: 0 | FN30: N | FO30: N | FP30: N | FQ30: N | FR30: 0 | FS30: 0 | FT30: Y | FV30: 0 | FY30: N | FZ30: N | GA30: 1 | GB30: M | GC30: N | GD30: N | GE30: N | GF30: 0 | GG30: O | GH30: N | GI30: Y | GJ30: N | GK30: Y | GL30: P | GM30: 0 | GN30: 0 | GO30: Y | GP30: Y | GQ30: N | GR30: 0 | GS30: 0 | GT30: 0 | GU30: 0 | GV30: 0 | GW30: N | GX30: N | GY30: C | GZ30: C | HB30: N | HC30: 0 | HD30: N | HE30: N | HG30: 0 | HH30: 0 | HI30: 0 | HJ30: 0 | HK30: 0 | HM30: N | HO30: 0 | HP30: 0 | HR30: 0 | HS30: 0 | HT30: 0 | HU30: 0 | HV30: D | HW30: W | HY30: 0 | HZ30: 0 | IA30: 0 | IB30: N | IC30: N | ID30: N | IE30: N
A31: EH | B31: KKI | C31: KRD KECIL INV RITEL | D31: 206 | E31: POnB,Non Prog,KI-IDR | G31: 8 | H31: 230 | I31: IDR | J31: 31 | K31: 0.045 | L31: 0.3 | M31: 0.045 | N31: 0.3 | O31: N | P31: 1 | Q31: M | R31: 6 | S31: 10 | T31: Y | U31: Y | V31: N | W31: 0 | X31: N | Y31: 1 | Z31: 0 | AA31: 0 | AB31: 0 | AC31: 0 | AD31: 0 | AE31: 0 | AF31: 7 | AG31: 21 | AH31: 35 | AI31: 49 | AJ31: 63 | AK31: 77 | AL31: 0 | AM31: 0 | AN31: 0 | AO31: Y | AP31: R | AQ31: 0 | AR31: 0 | AS31: 1 | AT31: 0 | AU31: Y | BC31: 0 | BD31: 0 | BE31: 0 | BF31: 0 | BG31: 0 | BH31: 0 | BI31: N | BJ31: N | BK31: N | BL31: N | BM31: N | BN31: N | BU31: 0 | BV31: 0 | BW31: 0 | BX31: 0 | BY31: 0 | BZ31: 0 | CA31: P | CB31: N | CC31: N | CD31: N | CE31: N | CF31: N | CG31: N | CH31: Y | CI31: 0 | CJ31: N | CL31: 0 | CM31: N | CN31: 0 | CO31: Y | CP31: N | CQ31: B | CR31: N | CT31: Y | CU31: 4 | CV31: Y | CW31: N | CY31: N | DA31: Y | DC31: 0 | DD31: O | DG31: N | DH31: N | DI31: N | DJ31: N | DK31: N | DP31: 0 | DQ31: 0 | DR31: 90 | DS31: 90 | DT31: 0 | DU31: 0 | DV31: N | DW31: P | DX31: P | DY31: 17 | DZ31: N | EC31: D | ED31: 0 | EE31: R | EF31: 100 | EG31: N | EH31: N | EI31: N | EJ31: N | EK31: N | EL31: 5 | EM31: N | EO31: 99 | EP31: P | EQ31: Y | ER31: N | ES31: 0 | EV31: Y | EW31: 6 | EX31: N | EY31: N | EZ31: N | FA31: N | FB31: N | FC31: N | FD31: B | FE31: N | FF31: N | FG31: N | FH31: N | FI31: N | FJ31: N | FK31: N | FL31: N | FM31: 0 | FN31: N | FO31: N | FP31: N | FQ31: N | FR31: 0 | FS31: 0 | FT31: Y | FV31: 0 | FY31: N | FZ31: N | GA31: 1 | GB31: M | GC31: N | GD31: N | GE31: N | GF31: 0 | GG31: O | GH31: N | GI31: Y | GJ31: N | GK31: Y | GL31: P | GM31: 0 | GN31: 0 | GO31: Y | GP31: Y | GQ31: N | GR31: 0 | GS31: 0 | GT31: 0 | GU31: 0 | GV31: 0 | GW31: N | GX31: N | GY31: C | GZ31: C | HB31: N | HC31: 0 | HD31: N | HE31: N | HG31: 0 | HH31: 0 | HI31: 0 | HJ31: 0 | HK31: 0 | HM31: N | HO31: 0 | HP31: 0 | HR31: 0 | HS31: 0 | HT31: 0 | HU31: 0 | HV31: D | HW31: W | HY31: 0 | HZ31: 0 | IA31: 0 | IB31: N | IC31: N | ID31: N | IE31: N
A32: EA | B32: KKU 50 JT | C32: KKU INV S/D 50 JUTA | D32: 206 | E32: POnB,Non Prog,KI-IDR | G32: 8 | H32: 230 | I32: IDR | J32: 31 | K32: 0.06 | L32: 0.3 | M32: 0.06 | N32: 0.3 | O32: N | P32: 1 | Q32: M | R32: 6 | S32: 10 | T32: Y | U32: Y | V32: N | W32: 0 | X32: N | Y32: 1 | Z32: 0 | AA32: 0 | AB32: 0 | AC32: 0 | AD32: 0 | AE32: 0 | AF32: 7 | AG32: 21 | AH32: 35 | AI32: 49 | AJ32: 63 | AK32: 77 | AL32: 0 | AM32: 0 | AN32: 0 | AO32: Y | AP32: R | AQ32: 0 | AR32: 0 | AS32: 1 | AT32: 0 | AU32: Y | BC32: 0 | BD32: 0 | BE32: 0 | BF32: 0 | BG32: 0 | BH32: 0 | BI32: N | BJ32: N | BK32: N | BL32: N | BM32: N | BN32: N | BU32: 0 | BV32: 0 | BW32: 0 | BX32: 0 | BY32: 0 | BZ32: 0 | CA32: P | CB32: N | CC32: N | CD32: N | CE32: N | CF32: N | CG32: N | CH32: Y | CI32: 0 | CJ32: N | CL32: 0 | CM32: N | CN32: 0 | CO32: Y | CP32: N | CQ32: B | CR32: N | CT32: Y | CU32: 4 | CV32: Y | CW32: N | CY32: N | DA32: Y | DC32: 0 | DD32: O | DG32: N | DH32: N | DI32: N | DJ32: N | DK32: N | DP32: 0 | DQ32: 0 | DR32: 90 | DS32: 90 | DT32: 0 | DU32: 0 | DV32: N | DW32: P | DX32: P | DY32: 17 | DZ32: N | EC32: D | ED32: 0 | EE32: R | EF32: 100 | EG32: N | EH32: N | EI32: N | EJ32: N | EK32: N | EL32: 5 | EM32: N | EO32: 99 | EP32: P | EQ32: Y | ER32: N | ES32: 0 | EV32: Y | EW32: 6 | EX32: N | EY32: N | EZ32: N | FA32: N | FB32: N | FC32: N | FD32: B | FE32: N | FF32: N | FG32: N | FH32: N | FI32: N | FJ32: N | FK32: N | FL32: N | FM32: 0 | FN32: N | FO32: N | FP32: N | FQ32: N | FR32: 0 | FS32: 0 | FT32: Y | FV32: 0 | FY32: N | FZ32: N | GA32: 1 | GB32: M | GC32: N | GD32: N | GE32: N | GF32: 0 | GG32: O | GH32: N | GI32: Y | GJ32: N | GK32: Y | GL32: P | GM32: 0 | GN32: 0 | GO32: Y | GP32: Y | GQ32: N | GR32: 0 | GS32: 0 | GT32: 0 | GU32: 0 | GV32: 0 | GW32: N | GX32: N | GY32: C | GZ32: C | HB32: N | HC32: 0 | HD32: N | HE32: N | HG32: 0 | HH32: 0 | HI32: 0 | HJ32: 0 | HK32: 0 | HM32: N | HO32: 0 | HP32: 0 | HR32: 0 | HS32: 0 | HT32: 0 | HU32: 0 | HV32: D | HW32: W | HY32: 0 | HZ32: 0 | IA32: 0 | IB32: N | IC32: N | ID32: N | IE32: N
A33: EB | B33: RC INV SEK | C33: KI ALL SEKTOR RITEL | D33: 206 | E33: POnB,Non Prog,KI-IDR | G33: 8 | H33: 230 | I33: IDR | J33: 31 | K33: 0.01 | L33: 0.3 | M33: 0.01 | N33: 0.3 | O33: N | P33: 1 | Q33: M | R33: 6 | S33: 10 | T33: Y | U33: Y | V33: N | W33: 0 | X33: N | Y33: 1 | Z33: 0 | AA33: 0 | AB33: 0 | AC33: 0 | AD33: 0 | AE33: 0 | AF33: 7 | AG33: 21 | AH33: 35 | AI33: 49 | AJ33: 63 | AK33: 77 | AL33: 0 | AM33: 0 | AN33: 0 | AO33: Y | AP33: R | AQ33: 0 | AR33: 0 | AS33: 1 | AT33: 0 | AU33: Y | BC33: 0 | BD33: 0 | BE33: 0 | BF33: 0 | BG33: 0 | BH33: 0 | BI33: N | BJ33: N | BK33: N | BL33: N | BM33: N | BN33: N | BU33: 0 | BV33: 0 | BW33: 0 | BX33: 0 | BY33: 0 | BZ33: 0 | CA33: P | CB33: N | CC33: N | CD33: N | CE33: N | CF33: N | CG33: N | CH33: Y | CI33: 0 | CJ33: N | CL33: 0 | CM33: N | CN33: 0 | CO33: Y | CP33: N | CQ33: B | CR33: N | CT33: Y | CU33: 4 | CV33: Y | CW33: N | CY33: N | DA33: Y | DC33: 0 | DD33: O | DG33: N | DH33: N | DI33: N | DJ33: N | DK33: N | DP33: 0 | DQ33: 0 | DR33: 90 | DS33: 90 | DT33: 0 | DU33: 0 | DV33: N | DW33: P | DX33: N | DZ33: N | EC33: D | ED33: 0 | EE33: R | EF33: 100 | EG33: N | EH33: N | EI33: N | EJ33: N | EK33: N | EL33: 5 | EM33: N | EO33: 99 | EP33: P | EQ33: Y | ER33: N | ES33: 0 | EV33: Y | EW33: 6 | EX33: N | EY33: N | EZ33: N | FA33: N | FB33: N | FC33: N | FD33: B | FE33: N | FF33: N | FG33: N | FH33: N | FI33: N | FJ33: N | FK33: N | FL33: N | FM33: 0 | FN33: N | FO33: N | FP33: N | FQ33: N | FR33: 0 | FS33: 0 | FT33: Y | FV33: 0 | FY33: N | FZ33: N | GA33: 1 | GB33: M | GC33: N | GD33: N | GE33: N | GF33: 0 | GH33: N | GI33: Y | GJ33: N | GK33: Y | GL33: P | GM33: 0 | GN33: 0 | GO33: Y | GP33: Y | GQ33: N | GR33: 0 | GS33: 0 | GT33: 0 | GU33: 0 | GV33: 0 | GW33: N | GX33: N | GY33: C | GZ33: C | HB33: N | HC33: 0 | HD33: N | HE33: N | HG33: 0 | HH33: 0 | HI33: 0 | HJ33: 0 | HK33: 0 | HM33: N | HO33: 0 | HP33: 0 | HR33: 0 | HS33: 0 | HT33: 0 | HU33: 0 | HV33: D | HW33: W | HY33: 0 | HZ33: 0 | IA33: 0 | IB33: N | IC33: N | ID33: N | IE33: N
A34: EC | B34: RC INV SEK | C34: KI ALL SEKTOR DKM1 | D34: 207 | E34: POnB,Non Prog,KI-IDR | G34: 8 | H34: 310 | I34: IDR | J34: 31 | K34: 0.06 | L34: 0.3 | M34: 0.06 | N34: 0.3 | O34: N | P34: 1 | Q34: M | R34: 6 | S34: 10 | T34: Y | U34: Y | V34: N | W34: 0 | X34: N | Y34: 1 | Z34: 0 | AA34: 0 | AB34: 0 | AC34: 0 | AD34: 0 | AE34: 0 | AF34: 7 | AG34: 21 | AH34: 35 | AI34: 49 | AJ34: 63 | AK34: 77 | AL34: 0 | AM34: 0 | AN34: 0 | AO34: Y | AP34: R | AQ34: 0 | AR34: 0 | AS34: 1 | AT34: 0 | AU34: Y | BC34: 0 | BD34: 0 | BE34: 0 | BF34: 0 | BG34: 0 | BH34: 0 | BI34: N | BJ34: N | BK34: N | BL34: N | BM34: N | BN34: N | BU34: 0 | BV34: 0 | BW34: 0 | BX34: 0 | BY34: 0 | BZ34: 0 | CA34: P | CB34: N | CC34: N | CD34: N | CE34: N | CF34: N | CG34: N | CH34: Y | CI34: 0 | CJ34: N | CL34: 0 | CM34: N | CN34: 0 | CO34: Y | CP34: N | CR34: N | CT34: Y | CU34: 4 | CV34: Y | CW34: N | CY34: N | DA34: Y | DC34: 0 | DD34: O | DG34: N | DH34: N | DI34: N | DJ34: N | DK34: N | DP34: 0 | DQ34: 0 | DR34: 90 | DS34: 90 | DT34: 0 | DU34: 0 | DV34: N | DW34: P | DX34: P | DY34: 17 | DZ34: N | EC34: D | ED34: 0 | EE34: R | EF34: 100 | EG34: N | EH34: N | EI34: N | EJ34: N | EK34: N | EL34: 5 | EM34: N | EO34: 99 | EP34: P | EQ34: Y | ER34: N | ES34: 0 | EV34: Y | EW34: 6 | EX34: N | EY34: N | EZ34: N | FA34: N | FB34: N | FC34: N | FD34: B | FE34: N | FF34: N | FG34: N | FH34: N | FI34: N | FJ34: N | FK34: N | FL34: N | FM34: 0 | FN34: N | FO34: N | FP34: N | FQ34: N | FR34: 0 | FS34: 0 | FT34: Y | FV34: 0 | FY34: N | FZ34: N | GA34: 1 | GB34: M | GC34: N | GD34: N | GE34: N | GF34: 0 | GG34: O | GH34: N | GI34: Y | GJ34: N | GK34: Y | GL34: P | GM34: 0 | GN34: 0 | GO34: Y | GP34: Y | GQ34: N | GR34: 0 | GS34: 0 | GT34: 0 | GU34: 0 | GV34: 0 | GW34: N | GX34: N | GY34: C | GZ34: C | HB34: N | HC34: 0 | HD34: N | HE34: N | HG34: 0 | HH34: 0 | HI34: 0 | HJ34: 0 | HK34: 0 | HM34: N | HO34: 0 | HP34: 0 | HR34: 0 | HS34: 0 | HT34: 0 | HU34: 0 | HV34: D | HW34: W | HY34: 0 | HZ34: 0 | IA34: 0 | IB34: N | IC34: N | ID34: N | IE34: N
A35: AQ | B35: KMK PUPUK | C35: KMK PENGADAAN PUPUK | D35: 101 | E35: On B/S, Program, KMK | G35: 8 | H35: 240 | I35: IDR | J35: 31 | K35: 0.08 | L35: 0.15 | M35: 0.08 | N35: 0.15 | O35: N | P35: 1 | Q35: M | R35: 6 | S35: 0 | T35: Y | U35: Y | V35: N | W35: 0 | X35: I | Y35: 1 | Z35: 0 | AA35: 0 | AB35: 0 | AC35: 0 | AD35: 0 | AE35: 0 | AF35: 7 | AG35: 21 | AH35: 35 | AI35: 0 | AJ35: 0 | AK35: 0 | AL35: 0 | AM35: 0 | AN35: 0 | AO35: Y | AP35: R | AQ35: 0 | AR35: 0 | AS35: 1 | AT35: 0 | AU35: Y | BC35: 0 | BD35: 0 | BE35: 0 | BF35: 0 | BG35: 0 | BH35: 0 | BI35: N | BJ35: N | BK35: N | BL35: N | BM35: N | BN35: N | BU35: 0 | BV35: 0 | BW35: 0 | BX35: 0 | BY35: 0 | BZ35: 0 | CA35: P | CB35: N | CC35: N | CD35: N | CE35: N | CF35: N | CG35: N | CH35: N | CI35: 0 | CJ35: N | CL35: 0 | CM35: N | CN35: 0 | CO35: N | CP35: N | CQ35: A | CR35: N | CT35: N | CU35: 4 | CV35: N | CW35: N | CY35: N | DA35: Y | DC35: 0 | DD35: P | DG35: N | DH35: N | DI35: N | DJ35: N | DK35: N | DP35: 0 | DQ35: 0 | DR35: 90 | DS35: 90 | DT35: 0 | DU35: 0 | DV35: N | DW35: P | DX35: P | DY35: 17 | DZ35: N | EC35: D | ED35: 2 | EE35: R | EF35: 100 | EG35: N | EH35: N | EI35: N | EJ35: N | EK35: N | EL35: 1 | EM35: N | EO35: 99 | EP35: X | EQ35: Y | ER35: N | ES35: 0 | EV35: Y | EW35: 6 | EX35: N | EY35: N | EZ35: Y | FA35: N | FB35: Y | FC35: N | FD35: B | FE35: N | FF35: N | FG35: N | FH35: N | FI35: N | FJ35: N | FK35: N | FL35: N | FM35: 0 | FN35: N | FO35: N | FP35: N | FQ35: N | FR35: 0 | FS35: 0 | FT35: N | FV35: 0 | FY35: N | FZ35: N | GA35: 1 | GB35: M | GC35: N | GD35: N | GE35: N | GF35: 0 | GG35: O | GH35: N | GI35: Y | GJ35: N | GK35: Y | GL35: P | GM35: 0 | GN35: 0 | GO35: N | GP35: Y | GQ35: N | GR35: 2 | GS35: 0 | GT35: 0 | GU35: 0 | GV35: 0 | GW35: N | GX35: Y | HB35: N | HC35: 0 | HD35: N | HE35: N | HG35: 0 | HH35: 0 | HI35: 0 | HJ35: 0 | HK35: 0 | HM35: N | HO35: 0 | HP35: 0 | HR35: 0 | HS35: 0 | HT35: 0 | HU35: 0 | HV35: D | HW35: W | HY35: 0 | HZ35: 0 | IA35: 0 | IB35: N | IC35: N | ID35: N | IE35: N
A36: FF | B36: KRETUNG | C36: PERS-NO-AN JK.PANJAN | D36: 210 | E36: POnB,Non Prog,Konsum | G36: 8 | H36: 230 | I36: IDR | J36: 0 | K36: 0.055 | L36: 0.0551 | M36: 0.055 | N36: 0.0551 | O36: N | P36: 1 | Q36: M | R36: 0 | S36: 0 | T36: Y | U36: Y | V36: N | W36: 0 | X36: I | Y36: 1 | Z36: 0 | AA36: 0 | AB36: 0 | AC36: 0 | AD36: 0 | AE36: 0 | AF36: 7 | AG36: 21 | AH36: 35 | AI36: 49 | AJ36: 63 | AK36: 77 | AL36: 0 | AM36: 0 | AN36: 0 | AO36: Y | AP36: R | AQ36: 0 | AR36: 0 | AS36: 26 | AT36: 0 | AU36: Y | BC36: 0 | BD36: 0 | BE36: 0 | BF36: 0 | BG36: 0 | BH36: 0 | BI36: N | BJ36: N | BK36: N | BL36: N | BM36: N | BN36: N | BU36: 0 | BV36: 0 | BW36: 0 | BX36: 0 | BY36: 0 | BZ36: 0 | CA36: P | CB36: N | CC36: N | CD36: N | CE36: N | CF36: N | CG36: N | CH36: N | CI36: 0 | CJ36: N | CL36: 0 | CM36: N | CN36: 0 | CO36: N | CP36: N | CQ36: B | CR36: N | CT36: Y | CU36: 4 | CV36: N | CW36: N | CY36: N | DA36: N | DC36: 0 | DD36: T | DG36: N | DH36: N | DI36: N | DJ36: N | DK36: N | DP36: 0 | DQ36: 0 | DR36: 90 | DS36: 90 | DT36: 0 | DU36: 0 | DV36: N | DW36: P | DX36: P | DY36: 17 | DZ36: N | EC36: M | ED36: 5 | EE36: U | EF36: 500 | EG36: N | EH36: N | EI36: N | EJ36: Z | EK36: N | EL36: 6 | EM36: N | EO36: 0 | EP36: P | EQ36: N | ER36: N | ES36: 0 | EV36: Y | EW36: 0 | EX36: N | EY36: N | EZ36: N | FA36: N | FB36: Y | FC36: N | FD36: B | FE36: N | FF36: N | FG36: N | FH36: N | FI36: N | FJ36: N | FK36: N | FL36: N | FM36: 0 | FN36: N | FO36: N | FP36: N | FQ36: N | FR36: 0 | FS36: 0 | FT36: N | FV36: 0 | FY36: N | FZ36: N | GA36: 1 | GB36: M | GC36: N | GD36: N | GE36: N | GF36: 0 | GG36: O | GH36: N | GI36: N | GJ36: N | GK36: Y | GL36: N | GM36: 0 | GN36: 0 | GO36: Y | GP36: Y | GQ36: N | GR36: 0 | GS36: 0 | GT36: 0 | GU36: 0 | GV36: 0 | GW36: N | GX36: Y | HB36: N | HC36: 0 | HD36: N | HE36: N | HG36: 0 | HH36: 0 | HI36: 0 | HJ36: 0 | HK36: 0 | HM36: N | HO36: 0 | HP36: 0 | HR36: 0 | HS36: 0 | HT36: 0 | HU36: 0 | HV36: D | HW36: W | HY36: 0 | HZ36: 0 | IA36: 0 | IB36: N | IC36: N | ID36: N | IE36: N
A37: FA | B37: PIN PEG LA | C37: PERS ANNUITET KONS | D37: 210 | E37: POnB, Non Prog.Konsu | G37: 9 | H37: 230 | I37: IDR | J37: 31 | K37: 0.05 | L37: 0.18 | M37: 0.05 | N37: 0.18 | O37: N | P37: 1 | Q37: M | R37: 3 | S37: 0 | T37: N | U37: Y | V37: N | W37: 0 | X37: I | Y37: 1 | Z37: 0 | AA37: 0 | AB37: 0 | AC37: 0 | AD37: 0 | AE37: 0 | AF37: 0 | AG37: 0 | AH37: 0 | AI37: 0 | AJ37: 0 | AK37: 0 | AL37: 7 | AM37: 0 | AN37: 0 | AO37: Y | AP37: R | AQ37: 0 | AR37: 0 | AS37: 1 | AT37: 0 | AU37: Y | AW37: O | BC37: 0 | BD37: 0 | BE37: 0 | BF37: 0 | BG37: 0 | BH37: 0 | BI37: N | BJ37: N | BK37: N | BL37: N | BM37: N | BN37: N | BO37: V | BU37: 0 | BV37: 0 | BW37: 0 | BX37: 0 | BY37: 0 | BZ37: 0 | CA37: P | CB37: N | CC37: N | CD37: N | CE37: N | CF37: N | CG37: N | CH37: N | CI37: 0 | CJ37: N | CL37: 0 | CM37: N | CN37: 0 | CO37: N | CP37: N | CQ37: B | CR37: N | CT37: Y | CU37: 4 | CV37: N | CW37: N | CY37: N | DA37: Y | DC37: 0 | DD37: T | DG37: N | DH37: N | DI37: N | DJ37: N | DK37: N | DP37: 0 | DQ37: 0 | DR37: 90 | DS37: 90 | DT37: 0 | DU37: 0 | DV37: N | DW37: P | DX37: P | DY37: 17 | DZ37: N | EB37: N | ED37: 5 | EE37: U | EF37: 100 | EG37: N | EH37: N | EI37: N | EJ37: Z | EK37: N | EL37: 6 | EM37: N | EO37: 99 | EP37: P | EQ37: N | ER37: N | ES37: 0 | EV37: Y | EW37: 3 | EX37: N | EY37: N | EZ37: N | FA37: N | FB37: Y | FC37: N | FD37: B | FE37: N | FF37: N | FG37: N | FH37: N | FI37: N | FJ37: N | FK37: N | FL37: N | FM37: 0 | FN37: N | FO37: N | FP37: N | FQ37: N | FR37: 0 | FS37: 0 | FT37: N | FV37: 0 | FY37: N | FZ37: N | GA37: 1 | GB37: M | GC37: N | GD37: N | GE37: N | GF37: 0 | GG37: O | GH37: N | GI37: N | GJ37: N | GK37: Y | GL37: N | GM37: 0 | GN37: 0 | GO37: Y | GP37: Y | GQ37: N | GR37: 0 | GS37: 0 | GT37: 0 | GU37: 0 | GV37: 0 | GW37: N | GX37: Y | HB37: N | HC37: 0 | HD37: N | HE37: N | HG37: 0 | HH37: 0 | HI37: 0 | HJ37: 0 | HK37: 0 | HM37: N | HO37: 0 | HP37: 0 | HR37: 0 | HS37: 0 | HT37: 0 | HU37: 0 | HV37: D | HW37: W | HY37: 0 | HZ37: 0 | IA37: 0 | IB37: N | IC37: N | ID37: N | IE37: N
A38: FJ | B38: KRD ONH | C38: PRS-NON-AN KONSUMTIF | D38: 210 | E38: POnB,Non Prog,Konsum | G38: 8 | H38: 230 | I38: IDR | J38: 31 | K38: 0.12 | L38: 0.24 | M38: 0.12 | N38: 0.24 | O38: N | P38: 1 | Q38: M | R38: 6 | S38: 10 | T38: Y | U38: Y | V38: N | W38: 0 | X38: I | Y38: 1 | Z38: 0 | AA38: 0 | AB38: 0 | AC38: 0 | AD38: 0 | AE38: 0 | AF38: 7 | AG38: 21 | AH38: 35 | AI38: 49 | AJ38: 63 | AK38: 77 | AL38: 0 | AM38: 0 | AN38: 0 | AO38: Y | AP38: R | AQ38: 0 | AR38: 0 | AS38: 1 | AT38: 0 | AU38: Y | BC38: 0 | BD38: 0 | BE38: 0 | BF38: 0 | BG38: 0 | BH38: 0 | BI38: N | BJ38: N | BK38: N | BL38: N | BM38: N | BN38: N | BU38: 0 | BV38: 0 | BW38: 0 | BX38: 0 | BY38: 0 | BZ38: 0 | CA38: P | CB38: N | CC38: N | CD38: N | CE38: N | CF38: N | CG38: N | CH38: N | CI38: 0 | CJ38: N | CL38: 0 | CM38: N | CN38: 0 | CO38: N | CP38: N | CQ38: B | CR38: N | CT38: Y | CU38: 4 | CV38: N | CW38: N | CY38: N | DA38: Y | DC38: 0 | DD38: O | DG38: N | DH38: N | DI38: N | DJ38: N | DK38: N | DP38: 0 | DQ38: 0 | DR38: 90 | DS38: 90 | DT38: 0 | DU38: 0 | DV38: N | DW38: P | DZ38: N | EC38: D | ED38: 0 | EE38: U | EF38: 100 | EG38: N | EH38: N | EI38: N | EJ38: N | EK38: N | EL38: 6 | EM38: N | EO38: 99 | EP38: P | EQ38: N | ER38: N | ES38: 0 | EV38: Y | EW38: 6 | EX38: N | EY38: N | EZ38: N | FA38: N | FB38: Y | FC38: N | FD38: B | FE38: N | FF38: N | FG38: N | FH38: N | FI38: N | FJ38: N | FK38: N | FL38: N | FM38: 0 | FN38: N | FO38: N | FP38: N | FQ38: N | FR38: 0 | FS38: 0 | FT38: N | FV38: 0 | FY38: N | FZ38: N | GA38: 1 | GB38: M | GC38: N | GD38: N | GE38: N | GF38: 0 | GH38: N | GI38: Y | GJ38: N | GK38: Y | GL38: E | GM38: 0 | GN38: 0 | GO38: Y | GP38: Y | GQ38: N | GR38: 0 | GS38: 0 | GT38: 0 | GU38: 0 | GV38: 0 | GW38: N | GX38: Y | HB38: N | HC38: 0 | HD38: N | HE38: N | HG38: 0 | HH38: 0 | HI38: 0 | HJ38: 0 | HK38: 0 | HM38: N | HO38: 0 | HP38: 0 | HR38: 0 | HS38: 0 | HT38: 0 | HU38: 0 | HV38: D | HW38: W | HY38: 0 | HZ38: 0 | IA38: 0 | IB38: Y | IC38: N | ID38: N | IE38: N
A39: FK | B39: KREMUNA | C39: PRS-NON-AN MULTIGUNA | D39: 210 | E39: POnB, Non Prog.Konsu | G39: 8 | H39: 230 | I39: IDR | J39: 31 | K39: 0.147 | L39: 0.27 | M39: 0.147 | N39: 0.27 | O39: N | P39: 1 | Q39: M | R39: 0 | S39: 11 | T39: Y | U39: Y | V39: N | W39: 0 | X39: I | Y39: 1 | Z39: 0 | AA39: 0 | AB39: 0 | AC39: 0 | AD39: 0 | AE39: 0 | AF39: 7 | AG39: 21 | AH39: 35 | AI39: 49 | AJ39: 63 | AK39: 77 | AL39: 0 | AM39: 0 | AN39: 0 | AO39: Y | AP39: R | AQ39: 0 | AR39: 0 | AS39: 1 | AT39: 0 | AU39: Y | BC39: 0 | BD39: 0 | BE39: 0 | BF39: 0 | BG39: 0 | BH39: 0 | BI39: N | BJ39: N | BK39: N | BL39: N | BM39: N | BN39: N | BU39: 0 | BV39: 0 | BW39: 0 | BX39: 0 | BY39: 0 | BZ39: 0 | CA39: P | CB39: N | CC39: N | CD39: N | CE39: N | CF39: N | CG39: N | CH39: N | CI39: 0 | CJ39: N | CL39: 0 | CM39: N | CN39: 0 | CO39: N | CP39: N | CQ39: B | CR39: N | CT39: Y | CU39: 4 | CV39: N | CW39: N | CY39: N | DA39: Y | DC39: 0 | DD39: T | DG39: N | DH39: N | DI39: N | DJ39: N | DK39: N | DP39: 0 | DQ39: 0 | DR39: 90 | DS39: 90 | DT39: 0 | DU39: 0 | DV39: N | DW39: P | DX39: P | DY39: 17 | DZ39: N | EC39: F | ED39: 5 | EE39: U | EF39: 100 | EG39: N | EH39: N | EI39: N | EJ39: N | EK39: N | EL39: 6 | EM39: N | EO39: 0 | EP39: P | EQ39: N | ER39: N | ES39: 0 | EV39: Y | EW39: 0 | EX39: N | EY39: N | EZ39: N | FA39: N | FB39: Y | FC39: N | FD39: B | FE39: N | FF39: N | FG39: N | FH39: N | FI39: N | FJ39: N | FK39: N | FL39: N | FM39: 0 | FN39: N | FO39: N | FP39: N | FQ39: N | FR39: 0 | FS39: 0 | FT39: N | FV39: 0 | FY39: N | FZ39: N | GA39: 1 | GB39: M | GC39: N | GD39: N | GE39: N | GF39: 0 | GG39: O | GH39: N | GI39: Y | GJ39: N | GK39: Y | GL39: N | GM39: 0 | GN39: 0 | GO39: Y | GP39: Y | GQ39: N | GR39: 0 | GS39: 0 | GT39: 0 | GU39: 0 | GV39: 0 | GW39: N | GX39: Y | HB39: N | HC39: 0 | HD39: N | HE39: N | HG39: 0 | HH39: 0 | HI39: 0 | HJ39: 0 | HK39: 0 | HM39: N | HO39: 0 | HP39: 0 | HR39: 0 | HS39: 0 | HT39: 0 | HU39: 0 | HV39: D | HW39: W | HY39: 6 | HZ39: 0 | IA39: 0 | IB39: Y | IC39: Y | ID39: N | IE39: N
A40: IU | B40: KUT P UMUM | C40: KUT PALAWIJA UMUM | D40: 101 | E40: On B/S,Program,KMK-I | G40: 8 | H40: 240 | I40: IDR | J40: 0 | K40: 0.08 | L40: 0.2 | M40: 0.08 | N40: 0.2 | O40: N | P40: 1 | Q40: M | R40: 6 | S40: 0 | T40: N | U40: Y | V40: N | W40: 0 | X40: K | Y40: 1 | Z40: 0 | AA40: 0 | AB40: 0 | AC40: 0 | AD40: 0 | AE40: 0 | AF40: 0 | AG40: 0 | AH40: 0 | AI40: 0 | AJ40: 0 | AK40: 0 | AL40: 0 | AM40: 0 | AN40: 0 | AO40: Y | AP40: R | AQ40: 0 | AR40: 0 | AS40: 1 | AT40: 0 | AU40: Y | BC40: 0 | BD40: 0 | BE40: 0 | BF40: 0 | BG40: 0 | BH40: 0 | BI40: N | BJ40: N | BK40: N | BL40: N | BM40: N | BN40: N | BU40: 0 | BV40: 0 | BW40: 0 | BX40: 0 | BY40: 0 | BZ40: 0 | CA40: P | CB40: N | CC40: N | CD40: N | CE40: N | CF40: N | CG40: N | CH40: N | CI40: 0 | CJ40: N | CL40: 0 | CM40: N | CN40: 0 | CO40: N | CP40: N | CQ40: B | CR40: N | CT40: Y | CU40: 4 | CV40: N | CW40: N | CY40: N | DA40: N | DC40: 0 | DD40: O | DG40: N | DH40: N | DI40: N | DJ40: N | DK40: N | DP40: 0 | DQ40: 0 | DR40: 90 | DS40: 90 | DT40: 0 | DU40: 0 | DV40: N | DW40: P | DX40: P | DY40: 17 | DZ40: N | EC40: D | ED40: 2 | EE40: R | EF40: 100 | EG40: N | EH40: N | EI40: N | EJ40: N | EK40: N | EL40: 1 | EM40: N | EO40: 0 | EP40: P | EQ40: Y | ER40: N | ES40: 0 | EV40: Y | EW40: 6 | EX40: N | EY40: N | EZ40: N | FA40: N | FB40: Y | FC40: N | FD40: B | FE40: N | FF40: N | FG40: N | FH40: N | FI40: N | FJ40: N | FK40: N | FL40: N | FM40: 0 | FN40: N | FO40: N | FP40: N | FQ40: N | FR40: 0 | FS40: 0 | FT40: N | FV40: 0 | FY40: N | FZ40: N | GA40: 1 | GB40: M | GC40: N | GD40: N | GE40: N | GF40: 0 | GG40: O | GH40: N | GI40: N | GJ40: N | GK40: Y | GL40: P | GM40: 0 | GN40: 0 | GO40: Y | GP40: Y | GQ40: N | GR40: 2 | GS40: 0 | GT40: 0 | GU40: 0 | GV40: 0 | GW40: N | GX40: Y | HB40: N | HC40: 0 | HD40: N | HE40: N | HG40: 0 | HH40: 0 | HI40: 0 | HJ40: 0 | HK40: 0 | HM40: N | HO40: 0 | HP40: 0 | HR40: 0 | HS40: 0 | HT40: 0 | HU40: 0 | HV40: D | HW40: W | HY40: 0 | HZ40: 0 | IA40: 0 | IB40: N | IC40: N | ID40: N | IE40: N
A41: JB | B41: PI PERIKAN | C41: P INDUSTRI PERIKANAN | D41: 302 | E41: POffB,Perhit Bunga K | G41: 8 | H41: 240 | I41: IDR | J41: 0 | K41: 0.07 | L41: 0.2 | M41: 0.07 | N41: 0.2 | O41: N | P41: 1 | Q41: M | R41: 6 | S41: 0 | T41: N | U41: Y | V41: N | W41: 0 | X41: K | Y41: 1 | Z41: 0 | AA41: 0 | AB41: 0 | AC41: 0 | AD41: 0 | AE41: 0 | AF41: 0 | AG41: 0 | AH41: 0 | AI41: 0 | AJ41: 0 | AK41: 0 | AL41: 0 | AM41: 0 | AN41: 0 | AO41: Y | AP41: R | AQ41: 0 | AR41: 0 | AS41: 1 | AT41: 0 | AU41: Y | BC41: 0 | BD41: 0 | BE41: 0 | BF41: 0 | BG41: 0 | BH41: 0 | BI41: N | BJ41: N | BK41: N | BL41: N | BM41: N | BN41: N | BU41: 0 | BV41: 0 | BW41: 0 | BX41: 0 | BY41: 0 | BZ41: 0 | CA41: P | CB41: N | CC41: N | CD41: N | CE41: N | CF41: N | CG41: N | CH41: N | CI41: 0 | CJ41: N | CL41: 0 | CM41: N | CN41: 0 | CO41: Y | CP41: N | CQ41: B | CR41: N | CT41: Y | CU41: 4 | CV41: N | CW41: N | CY41: N | DA41: N | DC41: 0 | DD41: O | DG41: N | DH41: N | DI41: N | DJ41: N | DK41: N | DP41: 0 | DQ41: 0 | DR41: 90 | DS41: 90 | DT41: 0 | DU41: 0 | DV41: N | DW41: P | DX41: P | DY41: 17 | DZ41: N | EC41: D | ED41: 2 | EE41: R | EF41: 100 | EG41: N | EH41: N | EI41: N | EJ41: N | EK41: N | EL41: 10 | EM41: N | EO41: 0 | EP41: P | EQ41: N | ER41: N | ES41: 0 | EV41: Y | EW41: 6 | EX41: N | EY41: N | EZ41: N | FA41: N | FB41: Y | FC41: N | FD41: B | FE41: N | FF41: N | FG41: N | FH41: N | FI41: N | FJ41: N | FK41: N | FL41: N | FM41: 0 | FN41: N | FO41: N | FP41: N | FQ41: N | FR41: 0 | FS41: 0 | FT41: N | FV41: 0 | FY41: N | FZ41: N | GA41: 1 | GB41: M | GC41: N | GD41: N | GE41: N | GF41: 0 | GG41: O | GH41: N | GI41: N | GJ41: N | GK41: Y | GL41: P | GM41: 0 | GN41: 0 | GO41: Y | GP41: Y | GQ41: N | GR41: 2 | GS41: 0 | GT41: 0 | GU41: 0 | GV41: 0 | GW41: N | GX41: Y | HB41: N | HC41: 0 | HD41: N | HE41: N | HG41: 0 | HH41: 0 | HI41: 0 | HJ41: 0 | HK41: 0 | HM41: N | HO41: 0 | HP41: 0 | HR41: 0 | HS41: 0 | HT41: 0 | HU41: 0 | HV41: D | HW41: W | HY41: 0 | HZ41: 0 | IA41: 0 | IB41: N | IC41: N | ID41: N | IE41: N
A42: NA | B42: KLP | C42: KREDIT LISTRIK PEDES | D42: 404 | E42: POffB,Fee Konsumtif- | G42: 8 | H42: 240 | I42: IDR | J42: 0 | K42: 0.07 | L42: 0.2 | M42: 0.07 | N42: 0.2 | O42: N | P42: 1 | Q42: M | R42: 6 | S42: 0 | T42: N | U42: Y | V42: N | W42: 0 | X42: I | Y42: 1 | Z42: 0 | AA42: 0 | AB42: 0 | AC42: 0 | AD42: 0 | AE42: 0 | AF42: 0 | AG42: 0 | AH42: 0 | AI42: 0 | AJ42: 0 | AK42: 0 | AL42: 0 | AM42: 0 | AN42: 0 | AO42: Y | AP42: R | AQ42: 0 | AR42: 0 | AS42: 1 | AT42: 0 | AU42: Y | BC42: 0 | BD42: 0 | BE42: 0 | BF42: 0 | BG42: 0 | BH42: 0 | BI42: N | BJ42: N | BK42: N | BL42: N | BM42: N | BN42: N | BU42: 0 | BV42: 0 | BW42: 0 | BX42: 0 | BY42: 0 | BZ42: 0 | CA42: P | CB42: N | CC42: N | CD42: N | CE42: N | CF42: N | CG42: N | CH42: N | CI42: 0 | CJ42: N | CL42: 0 | CM42: N | CN42: 0 | CO42: N | CP42: N | CQ42: A | CR42: N | CT42: Y | CU42: 4 | CV42: N | CW42: N | CY42: N | DA42: N | DC42: 0 | DD42: O | DG42: N | DH42: N | DI42: N | DJ42: N | DK42: N | DP42: 0 | DQ42: 0 | DR42: 90 | DS42: 90 | DT42: 0 | DU42: 0 | DV42: N | DW42: P | DX42: P | DY42: 17 | DZ42: N | EC42: D | ED42: 2 | EE42: R | EF42: 100 | EG42: N | EH42: N | EI42: N | EJ42: N | EK42: N | EL42: 14 | EM42: N | EO42: 0 | EP42: P | EQ42: Y | ER42: N | ES42: 0 | EV42: Y | EW42: 3 | EX42: N | EY42: N | EZ42: N | FA42: N | FB42: Y | FC42: N | FD42: B | FE42: N | FF42: N | FG42: N | FH42: N | FI42: N | FJ42: N | FK42: N | FL42: N | FM42: 0 | FN42: N | FO42: N | FP42: N | FQ42: N | FR42: 0 | FS42: 0 | FT42: N | FV42: 0 | FY42: N | FZ42: N | GA42: 1 | GB42: M | GC42: N | GD42: N | GE42: N | GF42: 0 | GG42: O | GH42: N | GI42: N | GJ42: N | GK42: Y | GL42: P | GM42: 0 | GN42: 0 | GO42: Y | GP42: Y | GQ42: N | GR42: 2 | GS42: 0 | GT42: 0 | GU42: 0 | GV42: 0 | GW42: N | GX42: Y | HB42: N | HC42: 0 | HD42: N | HE42: N | HG42: 0 | HH42: 0 | HI42: 0 | HJ42: 0 | HK42: 0 | HM42: N | HO42: 0 | HP42: 0 | HR42: 0 | HS42: 0 | HT42: 0 | HU42: 0 | HV42: D | HW42: W | HY42: 0 | HZ42: 0 | IA42: 0 | IB42: N | IC42: N | ID42: N | IE42: N
A43: QC | B43: KI VALAS | C43: KI VLS PRAKS KP DKM1 | D43: 227 | E43: POnB,Non Prog,KI-USD | G43: 8 | H43: 310 | I43: USD | J43: 31 | K43: 0.01 | L43: 0.2 | M43: 0.01 | N43: 0.2 | O43: N | P43: 1 | Q43: M | R43: 6 | S43: 10 | T43: Y | U43: Y | V43: N | W43: 0 | X43: N | Y43: 1 | Z43: 0 | AA43: 0 | AB43: 0 | AC43: 0 | AD43: 0 | AE43: 0 | AF43: 7 | AG43: 21 | AH43: 35 | AI43: 49 | AJ43: 63 | AK43: 77 | AL43: 0 | AM43: 0 | AN43: 0 | AO43: Y | AP43: R | AQ43: 0 | AR43: 0 | AS43: 1 | AT43: 0 | AU43: Y | BC43: 0 | BD43: 0 | BE43: 0 | BF43: 0 | BG43: 0 | BH43: 0 | BI43: N | BJ43: N | BK43: N | BL43: N | BM43: N | BN43: N | BU43: 0 | BV43: 0 | BW43: 0 | BX43: 0 | BY43: 0 | BZ43: 0 | CA43: P | CB43: N | CC43: N | CD43: N | CE43: N | CF43: N | CG43: N | CH43: N | CI43: 0 | CJ43: N | CL43: 0 | CM43: N | CN43: 0 | CO43: Y | CP43: N | CQ43: B | CR43: N | CT43: Y | CU43: 4 | CV43: Y | CW43: N | CY43: N | DA43: Y | DC43: 0 | DD43: O | DG43: N | DH43: N | DI43: N | DJ43: N | DK43: N | DP43: 0 | DQ43: 0 | DR43: 90 | DS43: 90 | DT43: 0 | DU43: 0 | DV43: N | DW43: P | DX43: P | DY43: 17 | DZ43: N | EC43: D | ED43: 2 | EE43: U | EF43: 1 | EG43: N | EH43: N | EI43: N | EJ43: N | EK43: N | EL43: 5 | EM43: N | EO43: 0 | EP43: P | EQ43: Y | ER43: N | ES43: 0 | EV43: Y | EW43: 6 | EX43: N | EY43: N | EZ43: N | FA43: N | FB43: Y | FC43: N | FD43: B | FE43: N | FF43: N | FG43: N | FH43: Y | FI43: N | FJ43: N | FK43: N | FL43: Y | FM43: 0 | FN43: N | FO43: N | FP43: N | FQ43: N | FR43: 0 | FS43: 0 | FT43: Y | FV43: 0 | FY43: N | FZ43: N | GA43: 1 | GB43: M | GC43: N | GD43: N | GE43: N | GF43: 0 | GG43: O | GH43: N | GI43: Y | GJ43: N | GK43: Y | GL43: P | GM43: 0 | GN43: 0 | GO43: Y | GP43: N | GQ43: N | GR43: 0 | GS43: 0 | GT43: 0 | GU43: 0 | GV43: 0 | GW43: N | GX43: Y | GY43: C | GZ43: C | HB43: N | HC43: 0 | HD43: N | HE43: Y | HF43: O | HG43: 0 | HH43: 0 | HI43: 0.02 | HJ43: 0 | HK43: 0 | HL43: 18 | HM43: N | HO43: 0 | HP43: 0 | HR43: 0 | HS43: 0 | HT43: 0 | HU43: 0 | HV43: D | HW43: W | HY43: 0 | HZ43: 0 | IA43: 0 | IB43: N | IC43: N | ID43: N | IE43: N
A44: QD | B44: KI VALAS | C44: KI VLS PRAKS KP DKM2 | D44: 228 | E44: POnB,Non Prog,KI-USD | G44: 8 | H44: 320 | I44: USD | J44: 31 | K44: 0.01 | L44: 0.2 | M44: 0.01 | N44: 0.2 | O44: N | P44: 1 | Q44: M | R44: 6 | S44: 10 | T44: Y | U44: Y | V44: N | W44: 0 | X44: N | Y44: 1 | Z44: 0 | AA44: 0 | AB44: 0 | AC44: 0 | AD44: 0 | AE44: 0 | AF44: 7 | AG44: 21 | AH44: 35 | AI44: 49 | AJ44: 63 | AK44: 77 | AL44: 0 | AM44: 0 | AN44: 0 | AO44: Y | AP44: R | AQ44: 0 | AR44: 0 | AS44: 1 | AT44: 0 | AU44: Y | BC44: 0 | BD44: 0 | BE44: 0 | BF44: 0 | BG44: 0 | BH44: 0 | BI44: N | BJ44: N | BK44: N | BL44: N | BM44: N | BN44: N | BU44: 0 | BV44: 0 | BW44: 0 | BX44: 0 | BY44: 0 | BZ44: 0 | CA44: P | CB44: N | CC44: N | CD44: N | CE44: N | CF44: N | CG44: N | CH44: N | CI44: 0 | CJ44: N | CL44: 0 | CM44: N | CN44: 0 | CO44: Y | CP44: N | CQ44: B | CR44: N | CT44: Y | CU44: 4 | CV44: Y | CW44: N | CY44: N | DA44: Y | DC44: 0 | DD44: O | DG44: N | DH44: N | DI44: N | DJ44: N | DK44: N | DP44: 0 | DQ44: 0 | DR44: 90 | DS44: 90 | DT44: 0 | DU44: 0 | DV44: N | DW44: P | DX44: P | DY44: 17 | DZ44: N | EC44: D | ED44: 2 | EE44: U | EF44: 1 | EG44: N | EH44: N | EI44: N | EJ44: N | EK44: N | EL44: 5 | EM44: N | EO44: 0 | EP44: P | EQ44: Y | ER44: N | ES44: 0 | EV44: Y | EW44: 6 | EX44: N | EY44: N | EZ44: N | FA44: N | FB44: Y | FC44: N | FD44: B | FE44: N | FF44: N | FG44: N | FH44: Y | FI44: N | FJ44: N | FK44: N | FL44: Y | FM44: 0 | FN44: N | FO44: N | FP44: N | FQ44: N | FR44: 0 | FS44: 0 | FT44: Y | FV44: 0 | FY44: N | FZ44: N | GA44: 1 | GB44: M | GC44: N | GD44: N | GE44: N | GF44: 0 | GG44: O | GH44: N | GI44: Y | GJ44: N | GK44: Y | GL44: P | GM44: 0 | GN44: 0 | GO44: Y | GP44: Y | GQ44: N | GR44: 0 | GS44: 0 | GT44: 0 | GU44: 0 | GV44: 0 | GW44: N | GX44: Y | GY44: C | GZ44: C | HB44: N | HC44: 0 | HD44: N | HE44: Y | HF44: O | HG44: 0 | HH44: 0 | HI44: 0.02 | HJ44: 0 | HK44: 0 | HL44: 18 | HM44: N | HO44: 0 | HP44: 0 | HR44: 0 | HS44: 0 | HT44: 0 | HU44: 0 | HV44: D | HW44: W | HY44: 0 | HZ44: 0 | IA44: 0 | IB44: N | IC44: N | ID44: N | IE44: N
A45: TE | B45: UBLC | C45: Usance Bill LC | D45: 940 | E45: Inward Bill under LC | G45: 8 | H45: 210 | I45: IDR | J45: 0 | K45: 0.1 | L45: 0.18 | M45: 0.1 | N45: 0.18 | O45: N | P45: 1 | Q45: M | R45: 5 | S45: 10 | T45: N | U45: N | V45: N | W45: 0 | X45: I | Y45: 1 | Z45: 0 | AA45: 0 | AB45: 0 | AC45: 0 | AD45: 0 | AE45: 0 | AF45: 0 | AG45: 0 | AH45: 0 | AI45: 0 | AJ45: 0 | AK45: 0 | AL45: 0 | AM45: 0 | AN45: 0 | AO45: Y | AP45: R | AQ45: 0 | AR45: 0 | AS45: 1 | AT45: 0 | AU45: N | BC45: 0 | BD45: 0 | BE45: 0 | BF45: 0 | BG45: 0 | BH45: 0 | BI45: N | BJ45: N | BK45: N | BL45: N | BM45: N | BN45: N | BU45: 0 | BV45: 0 | BW45: 0 | BX45: 0 | BY45: 0 | BZ45: 0 | CA45: P | CB45: N | CC45: N | CD45: N | CE45: N | CF45: N | CG45: N | CH45: N | CI45: 0 | CJ45: N | CL45: 0 | CM45: N | CN45: 0 | CO45: N | CP45: Y | CR45: N | CT45: Y | CU45: 4 | CV45: N | CW45: N | CY45: N | DA45: N | DC45: 0 | DD45: O | DG45: N | DH45: N | DI45: N | DJ45: N | DK45: N | DP45: 0 | DQ45: 0 | DR45: 90 | DS45: 90 | DT45: 0 | DU45: 0 | DV45: N | DW45: M | DX45: N | DZ45: N | EC45: D | ED45: 0 | EE45: R | EF45: 1 | EG45: N | EH45: N | EI45: N | EJ45: N | EK45: N | EL45: 15 | EM45: N | EO45: 0 | EP45: P | EQ45: N | ER45: N | ES45: 0 | EV45: N | EW45: 5 | EX45: N | EY45: N | EZ45: N | FA45: N | FB45: N | FC45: Y | FD45: B | FE45: N | FF45: N | FG45: N | FH45: N | FI45: N | FJ45: N | FK45: N | FL45: N | FM45: 0 | FN45: N | FO45: N | FP45: N | FQ45: N | FR45: 0 | FS45: 0 | FT45: N | FV45: 0 | FY45: N | FZ45: N | GA45: 1 | GB45: M | GC45: N | GD45: N | GE45: Y | GF45: 90 | GH45: N | GI45: N | GJ45: N | GK45: Y | GL45: P | GM45: 0 | GN45: 0 | GO45: Y | GP45: N | GQ45: N | GR45: 0 | GS45: 0 | GT45: 0 | GU45: 0 | GV45: 0 | GW45: N | GX45: N | HB45: N | HC45: 0 | HD45: N | HE45: N | HG45: 0 | HH45: 0 | HI45: 0 | HJ45: 0 | HK45: 0 | HM45: N | HO45: 0 | HP45: 0 | HR45: 0 | HS45: 0 | HT45: 0 | HU45: 0 | HV45: D | HY45: 0 | HZ45: 0 | IA45: 0 | IB45: N | IC45: N | ID45: N | IE45: N
A46: TE | B46: UBLC | C46: Usance Bill LC | D46: 941 | E46: Inward Bill under LC | G46: 8 | H46: 210 | I46: USD | J46: 0 | K46: 0.1 | L46: 0.18 | M46: 0.1 | N46: 0.18 | O46: N | P46: 1 | Q46: M | R46: 5 | S46: 10 | T46: N | U46: N | V46: N | W46: 0 | X46: I | Y46: 1 | Z46: 0 | AA46: 0 | AB46: 0 | AC46: 0 | AD46: 0 | AE46: 0 | AF46: 0 | AG46: 0 | AH46: 0 | AI46: 0 | AJ46: 0 | AK46: 0 | AL46: 0 | AM46: 0 | AN46: 0 | AO46: Y | AP46: R | AQ46: 2 | AR46: 0 | AS46: 1 | AT46: 0 | AU46: N | BC46: 0 | BD46: 0 | BE46: 0 | BF46: 0 | BG46: 0 | BH46: 0 | BI46: N | BJ46: N | BK46: N | BL46: N | BM46: N | BN46: N | BU46: 0 | BV46: 0 | BW46: 0 | BX46: 0 | BY46: 0 | BZ46: 0 | CA46: A | CB46: N | CC46: N | CD46: N | CE46: N | CF46: N | CG46: N | CH46: N | CI46: 0 | CJ46: N | CL46: 0 | CM46: N | CN46: 0 | CO46: N | CP46: Y | CR46: N | CT46: Y | CU46: 4 | CV46: N | CW46: N | CY46: N | DA46: N | DC46: 0 | DD46: O | DG46: N | DH46: N | DI46: N | DJ46: N | DK46: N | DP46: 0 | DQ46: 0 | DR46: 90 | DS46: 90 | DT46: 0 | DU46: 0 | DV46: N | DW46: M | DX46: N | DZ46: N | EC46: D | ED46: 2 | EE46: U | EF46: 1 | EG46: N | EH46: N | EI46: N | EJ46: N | EK46: N | EL46: 15 | EM46: N | EO46: 99 | EP46: P | EQ46: N | ER46: N | ES46: 0 | EV46: N | EW46: 5 | EX46: N | EY46: N | EZ46: N | FA46: N | FB46: N | FC46: N | FD46: B | FE46: N | FF46: N | FG46: N | FH46: N | FI46: N | FJ46: N | FK46: N | FL46: N | FM46: 0 | FN46: N | FO46: N | FP46: N | FQ46: N | FR46: 0 | FS46: 0 | FT46: N | FV46: 0 | FY46: N | FZ46: N | GA46: 1 | GB46: M | GC46: N | GD46: N | GE46: Y | GF46: 90 | GH46: N | GI46: N | GJ46: N | GK46: Y | GL46: P | GM46: 0 | GN46: 0 | GO46: Y | GP46: N | GQ46: N | GR46: 2 | GS46: 2 | GT46: 0 | GU46: 0 | GV46: 0 | GW46: N | GX46: N | HB46: N | HC46: 0 | HD46: N | HE46: N | HG46: 0 | HH46: 0 | HI46: 0 | HJ46: 0 | HK46: 0 | HM46: N | HO46: 0 | HP46: 0 | HR46: 0 | HS46: 0 | HT46: 0 | HU46: 0 | HV46: D | HY46: 0 | HZ46: 0 | IA46: 0 | IB46: N | IC46: N | ID46: N | IE46: N
A47: TF | B47: FBEP-S LC | C47: FBEP-AP LC Sight | D47: 960 | E47: Bill Purchased under | G47: 8 | H47: 210 | I47: IDR | J47: 0 | K47: 0.1 | L47: 0.18 | M47: 0.1 | N47: 0.18 | O47: N | P47: 1 | Q47: M | R47: 5 | S47: 10 | T47: N | U47: N | V47: N | W47: 0 | X47: I | Y47: 1 | Z47: 0 | AA47: 0 | AB47: 0 | AC47: 0 | AD47: 0 | AE47: 0 | AF47: 0 | AG47: 0 | AH47: 0 | AI47: 0 | AJ47: 0 | AK47: 0 | AL47: 0 | AM47: 0 | AN47: 0 | AO47: Y | AP47: R | AQ47: 0 | AR47: 0 | AS47: 1 | AT47: 0 | AU47: N | BC47: 0 | BD47: 0 | BE47: 0 | BF47: 0 | BG47: 0 | BH47: 0 | BI47: N | BJ47: N | BK47: N | BL47: N | BM47: N | BN47: N | BU47: 0 | BV47: 0 | BW47: 0 | BX47: 0 | BY47: 0 | BZ47: 0 | CA47: P | CB47: N | CC47: N | CD47: N | CE47: N | CF47: N | CG47: N | CH47: N | CI47: 0 | CJ47: N | CL47: 0 | CM47: N | CN47: 0 | CO47: N | CP47: Y | CR47: N | CT47: Y | CU47: 4 | CV47: Y | CW47: N | CY47: N | DA47: N | DC47: 0 | DD47: O | DG47: N | DH47: N | DI47: N | DJ47: N | DK47: N | DP47: 0 | DQ47: 0 | DR47: 90 | DS47: 90 | DT47: 0 | DU47: 0 | DV47: N | DW47: M | DX47: N | DZ47: N | EC47: D | ED47: 0 | EE47: U | EF47: 1 | EG47: N | EH47: N | EI47: N | EJ47: N | EK47: N | EL47: 15 | EM47: N | EO47: 0 | EP47: P | EQ47: N | ER47: N | ES47: 0 | EV47: N | EW47: 5 | EX47: N | EY47: N | EZ47: N | FA47: N | FB47: N | FC47: N | FD47: B | FE47: N | FF47: N | FG47: Y | FH47: Y | FI47: N | FJ47: N | FK47: Y | FL47: Y | FM47: 0 | FN47: N | FO47: N | FP47: N | FQ47: N | FR47: 0 | FS47: 0 | FT47: N | FV47: 0 | FY47: N | FZ47: N | GA47: 1 | GB47: M | GC47: N | GD47: N | GE47: Y | GF47: 90 | GH47: N | GI47: N | GJ47: N | GK47: Y | GL47: P | GM47: 0 | GN47: 0 | GO47: Y | GP47: N | GQ47: N | GR47: 0 | GS47: 0 | GT47: 0 | GU47: 0 | GV47: 0 | GW47: N | GX47: N | GY47: C | HB47: N | HC47: 0 | HD47: Y | HE47: N | HG47: 0 | HH47: 0 | HI47: 0 | HJ47: 0 | HK47: 0 | HM47: N | HO47: 0 | HP47: 0 | HR47: 0 | HS47: 0 | HT47: 0 | HU47: 0 | HV47: D | HY47: 0 | HZ47: 0 | IA47: 0 | IB47: N | IC47: N | ID47: N | IE47: N
A48: HR | B48: KUP CASH C | C48: KPDS CASHCOL BG BLN | D48: 212 | E48: POnB,Non Prog,KUPEDE | G48: 8 | H48: 110 | I48: IDR | J48: 7 | K48: 0.04 | L48: 0.36 | M48: 0.04 | N48: 0.36 | O48: N | P48: 36 | Q48: M | R48: 6 | S48: 0 | T48: Y | U48: Y | V48: N | W48: 0 | X48: I | Y48: 1 | Z48: 0 | AA48: 0 | AB48: 0 | AC48: 0 | AD48: 0 | AE48: 0 | AF48: 7 | AG48: 21 | AH48: 35 | AI48: 49 | AJ48: 63 | AK48: 77 | AL48: 0 | AM48: 0 | AN48: 0 | AO48: Y | AP48: R | AQ48: 0 | AR48: 0 | AS48: 1 | AT48: 0 | AU48: Y | BC48: 0 | BD48: 0 | BE48: 0 | BF48: 0 | BG48: 0 | BH48: 0 | BI48: N | BJ48: N | BK48: N | BL48: N | BM48: N | BN48: N | BU48: 0 | BV48: 0 | BW48: 0 | BX48: 0 | BY48: 0 | BZ48: 0 | CA48: P | CB48: N | CC48: N | CD48: N | CE48: N | CF48: N | CG48: N | CH48: N | CI48: 0 | CL48: 0 | CM48: N | CN48: 0 | CO48: Y | CP48: N | CQ48: A | CR48: N | CT48: Y | CU48: 4 | CV48: N | CW48: N | CY48: N | DA48: Y | DC48: 0 | DD48: K | DG48: N | DH48: N | DI48: N | DJ48: N | DK48: N | DP48: 0 | DQ48: 0 | DR48: 90 | DS48: 90 | DT48: 0 | DU48: 0 | DV48: N | DW48: P | DX48: N | DZ48: N | EC48: F | ED48: 0 | EE48: R | EF48: 100 | EG48: N | EH48: N | EI48: N | EJ48: Z | EK48: N | EL48: 8 | EM48: N | EO48: 0 | EP48: X | EQ48: N | ES48: 0 | EV48: Y | EW48: 6 | EX48: N | EY48: N | EZ48: N | FA48: N | FB48: Y | FC48: N | FE48: N | FF48: N | FG48: N | FH48: N | FI48: N | FJ48: N | FK48: N | FL48: N | FM48: 0 | FN48: N | FO48: N | FP48: N | FQ48: N | FR48: 0 | FS48: 0 | FT48: N | FV48: 0 | FY48: N | FZ48: N | GA48: 1 | GB48: M | GC48: N | GD48: N | GE48: N | GF48: 0 | GH48: N | GI48: N | GJ48: N | GK48: Y | GL48: P | GM48: 0 | GN48: 0 | GO48: Y | GP48: Y | GQ48: N | GR48: 0 | GS48: 0 | GT48: 0 | GU48: 0 | GV48: 0 | GW48: N | GX48: Y | HC48: 0 | HD48: Y | HE48: N | HG48: 0 | HH48: 0 | HI48: 0 | HJ48: 0 | HK48: 0 | HM48: N | HO48: 0 | HP48: 0 | HR48: 0 | HS48: 0 | HT48: 0 | HU48: 0 | HV48: D | HW48: W | HY48: 3 | HZ48: 3 | IA48: 0 | IB48: Y | IC48: N | ID48: N | IE48: N
A49: HS | B49: KUPEKS BLN | C49: KUP CASHCOL P+B BLN | D49: 212 | E49: POnB,Non Prog,KUPEDE | G49: 8 | H49: 110 | I49: IDR | J49: 7 | K49: 0.04 | L49: 0.36 | M49: 0.04 | N49: 0.36 | O49: N | P49: 1 | Q49: M | R49: 0 | S49: 0 | T49: Y | U49: Y | V49: N | W49: 0 | X49: I | Y49: 1 | Z49: 0 | AA49: 0 | AB49: 0 | AC49: 0 | AD49: 0 | AE49: 0 | AF49: 7 | AG49: 21 | AH49: 35 | AI49: 49 | AJ49: 63 | AK49: 77 | AL49: 0 | AM49: 0 | AN49: 0 | AO49: Y | AP49: R | AQ49: 0 | AR49: 0 | AS49: 1 | AT49: 0 | AU49: Y | BC49: 0 | BD49: 0 | BE49: 0 | BF49: 0 | BG49: 0 | BH49: 0 | BI49: N | BJ49: N | BK49: N | BL49: N | BM49: N | BN49: N | BU49: 0 | BV49: 0 | BW49: 0 | BX49: 0 | BY49: 0 | BZ49: 0 | CA49: P | CB49: N | CC49: N | CD49: N | CE49: N | CF49: N | CG49: N | CH49: N | CI49: 0 | CJ49: N | CL49: 0 | CM49: N | CN49: 0 | CO49: N | CP49: N | CQ49: A | CR49: N | CT49: Y | CU49: 4 | CV49: N | CW49: N | CY49: N | DA49: Y | DC49: 0 | DD49: K | DG49: N | DH49: N | DI49: N | DJ49: N | DK49: N | DP49: 0 | DQ49: 0 | DR49: 90 | DS49: 90 | DT49: 0 | DU49: 0 | DV49: N | DW49: P | DX49: N | DZ49: N | EC49: F | ED49: 5 | EE49: R | EF49: 100 | EG49: N | EH49: N | EI49: N | EJ49: Z | EK49: N | EL49: 8 | EM49: N | EO49: 0 | EP49: P | EQ49: N | ER49: N | ES49: 0 | EV49: Y | EW49: 0 | EX49: N | EY49: N | EZ49: N | FA49: N | FB49: Y | FC49: N | FD49: B | FE49: N | FF49: N | FG49: N | FH49: N | FI49: N | FJ49: N | FK49: N | FL49: N | FM49: 0 | FN49: N | FO49: N | FP49: N | FQ49: N | FR49: 0 | FS49: 0 | FT49: N | FV49: 0 | FY49: N | FZ49: N | GA49: 1 | GB49: M | GC49: N | GD49: N | GE49: N | GF49: 0 | GH49: N | GI49: N | GJ49: N | GK49: Y | GL49: P | GM49: 0 | GN49: 0 | GO49: Y | GP49: Y | GQ49: N | GR49: 2 | GS49: 2 | GT49: 0 | GU49: 0 | GV49: 0 | GW49: N | GX49: Y | HB49: N | HC49: 0 | HD49: Y | HE49: N | HG49: 0 | HH49: 0 | HI49: 0 | HJ49: 0 | HK49: 0 | HM49: N | HO49: 0 | HP49: 0 | HR49: 0 | HS49: 0 | HT49: 0 | HU49: 0 | HV49: D | HW49: W | HY49: 3 | HZ49: 3 | IA49: 0 | IB49: Y | IC49: Y | ID49: N | IE49: N
A50: TF | B50: FBEP-S LC | C50: FBEP-AP LC Sight | D50: 961 | E50: Bill Purchased under | G50: 8 | H50: 210 | I50: USD | J50: 0 | K50: 0.1 | L50: 0.18 | M50: 0.1 | N50: 0.18 | O50: N | P50: 1 | Q50: M | R50: 5 | S50: 10 | T50: N | U50: N | V50: N | W50: 0 | X50: I | Y50: 1 | Z50: 0 | AA50: 0 | AB50: 0 | AC50: 0 | AD50: 0 | AE50: 0 | AF50: 0 | AG50: 0 | AH50: 0 | AI50: 0 | AJ50: 0 | AK50: 0 | AL50: 0 | AM50: 0 | AN50: 0 | AO50: Y | AP50: R | AQ50: 2 | AR50: 0 | AS50: 1 | AT50: 0 | AU50: N | BC50: 0 | BD50: 0 | BE50: 0 | BF50: 0 | BG50: 0 | BH50: 0 | BI50: N | BJ50: N | BK50: N | BL50: N | BM50: N | BN50: N | BU50: 0 | BV50: 0 | BW50: 0 | BX50: 0 | BY50: 0 | BZ50: 0 | CA50: P | CB50: N | CC50: N | CD50: N | CE50: N | CF50: N | CG50: N | CH50: N | CI50: 0 | CJ50: N | CL50: 0 | CM50: N | CN50: 0 | CO50: N | CP50: Y | CR50: N | CT50: Y | CU50: 4 | CV50: Y | CW50: N | CY50: N | DA50: N | DC50: 0 | DD50: O | DG50: N | DH50: N | DI50: N | DJ50: N | DK50: N | DP50: 0 | DQ50: 0 | DR50: 90 | DS50: 90 | DT50: 0 | DU50: 0 | DV50: N | DW50: M | DX50: N | DZ50: N | EC50: D | ED50: 2 | EE50: U | EF50: 1 | EG50: N | EH50: N | EI50: N | EJ50: N | EK50: N | EL50: 15 | EM50: N | EO50: 99 | EP50: P | EQ50: N | ER50: N | ES50: 0 | EV50: N | EW50: 5 | EX50: N | EY50: N | EZ50: N | FA50: N | FB50: N | FC50: Y | FD50: B | FE50: N | FF50: N | FG50: Y | FH50: Y | FI50: N | FJ50: N | FK50: Y | FL50: Y | FM50: 0 | FN50: N | FO50: N | FP50: N | FQ50: N | FR50: 0 | FS50: 0 | FT50: N | FV50: 0 | FY50: N | FZ50: N | GA50: 1 | GB50: M | GC50: N | GD50: N | GE50: Y | GF50: 90 | GH50: N | GI50: N | GJ50: N | GK50: Y | GL50: P | GM50: 0 | GN50: 0 | GO50: Y | GP50: N | GQ50: N | GR50: 2 | GS50: 2 | GT50: 0 | GU50: 0 | GV50: 0 | GW50: N | GX50: N | GY50: C | HB50: N | HC50: 0 | HD50: N | HE50: N | HG50: 0 | HH50: 0 | HI50: 0 | HJ50: 0 | HK50: 0 | HM50: N | HO50: 0 | HP50: 0 | HR50: 0 | HS50: 0 | HT50: 0 | HU50: 0 | HV50: D | HY50: 0 | HZ50: 0 | IA50: 0 | IB50: N | IC50: N | ID50: N | IE50: N
A51: TE | B51: UBLC JPY | C51: UB under LC JPY | D51: 942 | E51: Inward Bill under LC | G51: 8 | H51: 210 | I51: JPY | J51: 0 | K51: 0.1 | L51: 0.18 | M51: 0.1 | N51: 0.18 | O51: N | P51: 1 | Q51: M | R51: 5 | S51: 10 | T51: N | U51: N | V51: N | W51: 0 | X51: I | Y51: 1 | Z51: 0 | AA51: 0 | AB51: 0 | AC51: 0 | AD51: 0 | AE51: 0 | AF51: 0 | AG51: 0 | AH51: 0 | AI51: 0 | AJ51: 0 | AK51: 0 | AL51: 0 | AM51: 0 | AN51: 0 | AO51: Y | AP51: R | AQ51: 0 | AR51: 0 | AS51: 1 | AT51: 0 | AU51: N | BC51: 0 | BD51: 0 | BE51: 0 | BF51: 0 | BG51: 0 | BH51: 0 | BI51: N | BJ51: N | BK51: N | BL51: N | BM51: N | BN51: N | BU51: 0 | BV51: 0 | BW51: 0 | BX51: 0 | BY51: 0 | BZ51: 0 | CB51: N | CC51: N | CD51: N | CE51: N | CF51: N | CG51: N | CH51: N | CI51: 0 | CL51: 0 | CM51: N | CN51: 0 | CO51: N | CP51: Y | CR51: N | CT51: Y | CU51: 4 | CV51: N | CW51: N | CY51: N | DA51: Y | DC51: 0 | DD51: O | DG51: N | DH51: N | DI51: N | DJ51: N | DK51: N | DP51: 0 | DQ51: 0 | DR51: 90 | DS51: 90 | DT51: 0 | DU51: 0 | DV51: N | DX51: N | DZ51: N | EC51: D | ED51: 2 | EE51: U | EF51: 1 | EG51: N | EH51: N | EI51: N | EJ51: N | EK51: N | EL51: 15 | EM51: N | EO51: 0 | EP51: P | EQ51: N | ER51: N | ES51: 5 | ET51: D | EV51: N | EW51: 5 | EX51: N | EY51: N | EZ51: N | FA51: N | FB51: N | FC51: N | FE51: N | FF51: N | FG51: Y | FH51: N | FI51: N | FJ51: Y | FK51: Y | FL51: N | FM51: 0 | FN51: N | FO51: N | FP51: N | FQ51: N | FR51: 0 | FS51: 0 | FT51: N | FV51: 0 | FY51: N | FZ51: N | GA51: 1 | GB51: M | GC51: N | GD51: N | GE51: Y | GF51: 90 | GH51: N | GI51: N | GJ51: N | GK51: Y | GM51: 0 | GN51: 0 | GO51: Y | GP51: N | GQ51: N | GR51: 2 | GS51: 2 | GT51: 0 | GU51: 0 | GV51: 0 | GW51: N | GX51: N | HB51: N | HC51: 0 | HD51: Y | HE51: N | HG51: 0 | HH51: 0 | HI51: 0 | HJ51: 0 | HK51: 0 | HM51: N | HO51: 0 | HP51: 0 | HR51: 0 | HS51: 0 | HT51: 0 | HU51: 0 | HV51: D | HY51: 0 | HZ51: 0 | IA51: 0 | IB51: N | IC51: N | ID51: N | IE51: Y
A52: TF | B52: FBEP-AP S | C52: FBEP-AP Sight JPY | D52: 962 | E52: Bill Purchased Under | G52: 8 | H52: 210 | I52: JPY | J52: 0 | K52: 0.1 | L52: 0.18 | M52: 0.1 | N52: 0.18 | O52: N | P52: 1 | Q52: M | R52: 5 | S52: 10 | T52: N | U52: N | V52: N | W52: 0 | X52: I | Y52: 1 | Z52: 0 | AA52: 0 | AB52: 0 | AC52: 0 | AD52: 0 | AE52: 0 | AF52: 0 | AG52: 0 | AH52: 0 | AI52: 0 | AJ52: 0 | AK52: 0 | AL52: 0 | AM52: 0 | AN52: 0 | AO52: Y | AP52: R | AQ52: 0 | AR52: 0 | AS52: 1 | AT52: 0 | AU52: N | BC52: 0 | BD52: 0 | BE52: 0 | BF52: 0 | BG52: 0 | BH52: 0 | BI52: N | BJ52: N | BK52: N | BL52: N | BM52: N | BN52: N | BU52: 0 | BV52: 0 | BW52: 0 | BX52: 0 | BY52: 0 | BZ52: 0 | CB52: N | CC52: N | CD52: N | CE52: N | CF52: N | CG52: N | CH52: N | CI52: 0 | CL52: 0 | CM52: N | CN52: 0 | CO52: N | CP52: Y | CR52: N | CT52: Y | CU52: 4 | CV52: N | CW52: N | CY52: N | DA52: Y | DC52: 0 | DD52: O | DG52: N | DH52: N | DI52: N | DJ52: N | DK52: N | DP52: 0 | DQ52: 0 | DR52: 90 | DS52: 90 | DT52: 0 | DU52: 0 | DV52: N | DX52: N | DZ52: N | EC52: D | ED52: 2 | EE52: U | EF52: 1 | EG52: N | EH52: N | EI52: N | EJ52: Y | EK52: N | EL52: 15 | EM52: N | EO52: 0 | EP52: P | EQ52: N | ER52: N | ES52: 5 | ET52: D | EV52: N | EW52: 5 | EX52: N | EY52: N | EZ52: N | FA52: N | FB52: N | FC52: N | FE52: N | FF52: N | FG52: Y | FH52: N | FI52: N | FJ52: Y | FK52: Y | FL52: N | FM52: 0 | FN52: N | FO52: N | FP52: N | FQ52: N | FR52: 0 | FS52: 0 | FT52: N | FV52: 0 | FY52: N | FZ52: N | GA52: 1 | GB52: M | GC52: N | GD52: N | GE52: Y | GF52: 90 | GH52: N | GI52: N | GJ52: N | GK52: Y | GM52: 0 | GN52: 0 | GO52: Y | GP52: N | GQ52: N | GR52: 2 | GS52: 2 | GT52: 0 | GU52: 0 | GV52: 0 | GW52: N | GX52: N | HB52: N | HC52: 0 | HD52: Y | HE52: N | HG52: 0 | HH52: 0 | HI52: 0 | HJ52: 0 | HK52: 0 | HM52: N | HO52: 0 | HP52: 0 | HR52: 0 | HS52: 0 | HT52: 0 | HU52: 0 | HV52: D | HY52: 0 | HZ52: 0 | IA52: 0 | IB52: N | IC52: N | ID52: N | IE52: Y
A53: A1 | B53: KMKP | C53: KMKP MASSAL & KHUSUS | D53: 101 | E53: On B/S, Program, KMK | G53: 8 | H53: 240 | I53: IDR | J53: 0 | K53: 0.08 | L53: 0.36 | M53: 0.08 | N53: 0.36 | O53: N | P53: 1 | Q53: M | R53: 6 | S53: 0 | T53: N | U53: N | V53: N | W53: 0 | X53: I | Y53: 1 | Z53: 0 | AA53: 0 | AB53: 0 | AC53: 0 | AD53: 0 | AE53: 0 | AF53: 0 | AG53: 0 | AH53: 0 | AI53: 0 | AJ53: 0 | AK53: 0 | AL53: 0 | AM53: 0 | AN53: 0 | AO53: Y | AP53: R | AQ53: 0 | AR53: 0 | AS53: 1 | AT53: 0 | AU53: Y | BC53: 0 | BD53: 0 | BE53: 0 | BF53: 0 | BG53: 0 | BH53: 0 | BI53: N | BJ53: N | BK53: N | BL53: N | BM53: N | BN53: N | BU53: 0 | BV53: 0 | BW53: 0 | BX53: 0 | BY53: 0 | BZ53: 0 | CA53: P | CB53: N | CC53: N | CD53: N | CE53: N | CF53: N | CG53: N | CH53: N | CI53: 0 | CL53: 0 | CM53: N | CN53: 0 | CO53: Y | CP53: N | CQ53: A | CR53: N | CT53: Y | CU53: 4 | CV53: N | CW53: N | CY53: N | DA53: N | DC53: 0 | DD53: P | DG53: N | DH53: N | DI53: N | DJ53: N | DK53: N | DP53: 0 | DQ53: 0 | DR53: 90 | DS53: 90 | DT53: 0 | DU53: 0 | DV53: N | DZ53: N | EC53: D | ED53: 2 | EE53: R | EF53: 50 | EG53: N | EH53: N | EI53: N | EJ53: N | EK53: N | EL53: 1 | EM53: N | EO53: 0 | EP53: P | EQ53: N | ES53: 0 | EV53: Y | EW53: 6 | EX53: N | EY53: N | EZ53: Y | FA53: N | FB53: Y | FC53: N | FE53: N | FF53: N | FG53: N | FH53: N | FI53: N | FJ53: N | FK53: N | FL53: N | FM53: 0 | FN53: N | FO53: N | FP53: N | FQ53: N | FR53: 0 | FS53: 0 | FT53: N | FV53: 0 | FY53: N | FZ53: N | GA53: 1 | GB53: M | GC53: N | GD53: N | GE53: N | GF53: 0 | GH53: N | GI53: Y | GJ53: N | GK53: Y | GL53: P | GM53: 0 | GN53: 0 | GO53: N | GP53: Y | GQ53: N | GR53: 2 | GS53: 0 | GT53: 0 | GU53: 0 | GV53: 0 | GW53: N | GX53: Y | HB53: N | HC53: 0 | HD53: N | HE53: N | HG53: 0 | HH53: 0 | HI53: 0 | HJ53: 0 | HK53: 0 | HM53: N | HO53: 0 | HP53: 0 | HR53: 0 | HS53: 0 | HT53: 0 | HU53: 0 | HV53: D | HW53: W | HY53: 0 | HZ53: 0 | IA53: 0 | IB53: N | IC53: N | ID53: N | IE53: N
A54: A2 | B54: KMKP U | C54: KMKP UMUM | D54: 102 | E54: On B/S,Program,KMK-I | G54: 8 | H54: 230 | I54: IDR | J54: 0 | K54: 0.08 | L54: 0.16 | M54: 0.08 | N54: 0.16 | O54: N | P54: 1 | Q54: M | R54: 6 | S54: 0 | T54: N | U54: N | V54: N | W54: 0 | X54: I | Y54: 1 | Z54: 0 | AA54: 0 | AB54: 0 | AC54: 0 | AD54: 0 | AE54: 0 | AF54: 0 | AG54: 0 | AH54: 0 | AI54: 0 | AJ54: 0 | AK54: 0 | AL54: 0 | AM54: 0 | AN54: 0 | AO54: Y | AP54: R | AQ54: 0 | AR54: 0 | AS54: 1 | AT54: 0 | AU54: Y | BC54: 0 | BD54: 0 | BE54: 0 | BF54: 0 | BG54: 0 | BH54: 0 | BI54: N | BJ54: N | BK54: N | BL54: N | BM54: N | BN54: N | BU54: 0 | BV54: 0 | BW54: 0 | BX54: 0 | BY54: 0 | BZ54: 0 | CA54: P | CB54: N | CC54: N | CD54: N | CE54: N | CF54: N | CG54: N | CH54: N | CI54: 0 | CL54: 0 | CM54: N | CN54: 0 | CO54: Y | CP54: N | CQ54: A | CR54: N | CT54: Y | CU54: 4 | CV54: N | CW54: N | CY54: N | DA54: N | DC54: 0 | DD54: P | DG54: N | DH54: N | DI54: N | DJ54: N | DK54: N | DP54: 0 | DQ54: 0 | DR54: 90 | DS54: 90 | DT54: 0 | DU54: 0 | DV54: N | DZ54: N | EC54: D | ED54: 2 | EE54: R | EF54: 100 | EG54: N | EH54: N | EI54: N | EJ54: N | EK54: N | EL54: 1 | EM54: N | EO54: 0 | EP54: P | EQ54: Y | ES54: 0 | EV54: Y | EW54: 6 | EX54: N | EY54: N | EZ54: Y | FA54: N | FB54: Y | FC54: N | FE54: N | FF54: N | FG54: N | FH54: N | FI54: N | FJ54: N | FK54: N | FL54: N | FM54: 0 | FN54: N | FO54: N | FP54: N | FQ54: N | FR54: 0 | FS54: 0 | FT54: N | FV54: 0 | FY54: N | FZ54: N | GA54: 1 | GB54: M | GC54: N | GD54: N | GE54: N | GF54: 0 | GH54: N | GI54: N | GJ54: N | GK54: Y | GL54: P | GM54: 0 | GN54: 0 | GO54: N | GP54: Y | GQ54: N | GR54: 0 | GS54: 0 | GT54: 0 | GU54: 0 | GV54: 0 | GW54: N | GX54: Y | HB54: N | HC54: 0 | HD54: N | HE54: N | HG54: 0 | HH54: 0 | HI54: 0 | HJ54: 0 | HK54: 0 | HM54: N | HO54: 0 | HP54: 0 | HR54: 0 | HS54: 0 | HT54: 0 | HU54: 0 | HV54: D | HW54: W | HY54: 0 | HZ54: 0 | IA54: 0 | IB54: N | IC54: N | ID54: N | IE54: N
A55: AB | B55: P4K III | C55: KREDIT P4K FASE III | D55: 101 | E55: On B/S,Program,KMK-I | G55: 8 | H55: 240 | I55: IDR | J55: 7 | K55: 0.12 | L55: 0.36 | M55: 0.12 | N55: 0.36 | O55: N | P55: 1 | Q55: M | R55: 0 | S55: 0 | T55: Y | U55: Y | V55: N | W55: 0 | X55: I | Y55: 1 | Z55: 0 | AA55: 0 | AB55: 0 | AC55: 0 | AD55: 0 | AE55: 0 | AF55: 7 | AG55: 21 | AH55: 35 | AI55: 49 | AJ55: 63 | AK55: 77 | AL55: 0 | AM55: 0 | AN55: 0 | AO55: Y | AP55: R | AQ55: 0 | AR55: 0 | AS55: 1 | AT55: 0 | AU55: Y | BC55: 0 | BD55: 0 | BE55: 0 | BF55: 0 | BG55: 0 | BH55: 0 | BI55: N | BJ55: N | BK55: N | BL55: N | BM55: N | BN55: N | BU55: 0 | BV55: 0 | BW55: 0 | BX55: 0 | BY55: 0 | BZ55: 0 | CA55: P | CB55: N | CC55: N | CD55: N | CE55: N | CF55: N | CG55: N | CH55: N | CI55: 0 | CJ55: N | CL55: 0 | CM55: N | CN55: 0 | CO55: N | CP55: N | CQ55: A | CR55: N | CT55: Y | CU55: 4 | CV55: N | CW55: N | CY55: N | DA55: Y | DC55: 0 | DD55: O | DG55: N | DH55: N | DI55: N | DJ55: N | DK55: N | DP55: 0 | DQ55: 0 | DR55: 90 | DS55: 90 | DT55: 0 | DU55: 0 | DV55: N | DW55: P | DY55: 17 | DZ55: N | EC55: F | ED55: 5 | EE55: R | EF55: 100 | EG55: N | EH55: N | EI55: N | EJ55: Z | EK55: N | EL55: 1 | EM55: N | EO55: 0 | EP55: P | EQ55: Y | ER55: N | ES55: 0 | EV55: Y | EW55: 0 | EX55: N | EY55: N | EZ55: N | FA55: N | FB55: Y | FC55: N | FD55: B | FE55: N | FF55: N | FG55: N | FH55: N | FI55: N | FJ55: N | FK55: N | FL55: N | FM55: 0 | FN55: N | FO55: N | FP55: N | FQ55: N | FR55: 0 | FS55: 0 | FT55: N | FV55: 0 | FY55: N | FZ55: N | GA55: 1 | GB55: M | GC55: N | GD55: N | GE55: N | GF55: 0 | GG55: O | GH55: N | GI55: N | GJ55: N | GK55: Y | GL55: P | GM55: 0 | GN55: 0 | GO55: Y | GP55: Y | GQ55: Y | GR55: 2 | GS55: 2 | GT55: 0 | GU55: 0 | GV55: 0 | GW55: N | GX55: Y | HB55: N | HC55: 0 | HD55: N | HE55: N | HG55: 0 | HH55: 0 | HI55: 0 | HJ55: 0 | HK55: 0 | HM55: N | HO55: 0 | HP55: 0 | HR55: 0 | HS55: 0 | HT55: 0 | HU55: 0 | HV55: D | HW55: W | HY55: 0 | HZ55: 0 | IA55: 0 | IB55: Y | IC55: N | ID55: Y | IE55: N
A56: AA | B56: P4K II | C56: KREDIT P4K FASE II | D56: 101 | E56: On B/S,Program,KMK-I | G56: 8 | H56: 240 | I56: IDR | J56: 7 | K56: 0.12 | L56: 0.36 | M56: 0.12 | N56: 0.36 | O56: N | P56: 1 | Q56: M | R56: 0 | S56: 0 | T56: Y | U56: Y | V56: N | W56: 0 | X56: I | Y56: 1 | Z56: 0 | AA56: 0 | AB56: 0 | AC56: 0 | AD56: 0 | AE56: 0 | AF56: 7 | AG56: 21 | AH56: 35 | AI56: 49 | AJ56: 63 | AK56: 77 | AL56: 0 | AM56: 0 | AN56: 0 | AO56: Y | AP56: R | AQ56: 0 | AR56: 0 | AS56: 14 | AT56: 0 | AU56: Y | BC56: 0 | BD56: 0 | BE56: 0 | BF56: 0 | BG56: 0 | BH56: 0 | BI56: N | BJ56: N | BK56: N | BL56: N | BM56: N | BN56: N | BU56: 0 | BV56: 0 | BW56: 0 | BX56: 0 | BY56: 0 | BZ56: 0 | CA56: P | CB56: N | CC56: N | CD56: N | CE56: N | CF56: N | CG56: N | CH56: N | CI56: 0 | CJ56: N | CL56: 0 | CM56: N | CN56: 0 | CO56: N | CP56: N | CQ56: A | CR56: N | CT56: Y | CU56: 4 | CV56: N | CW56: N | CY56: N | DA56: Y | DC56: 0 | DD56: O | DG56: N | DH56: N | DI56: N | DJ56: N | DK56: N | DP56: 0 | DQ56: 0 | DR56: 90 | DS56: 90 | DT56: 0 | DU56: 0 | DV56: N | DW56: P | DY56: 17 | DZ56: N | EC56: F | ED56: 5 | EE56: R | EF56: 100 | EG56: N | EH56: N | EI56: N | EJ56: Z | EK56: N | EL56: 1 | EM56: N | EO56: 0 | EP56: P | EQ56: N | ER56: N | ES56: 0 | EV56: Y | EW56: 0 | EX56: N | EY56: N | EZ56: N | FA56: N | FB56: Y | FC56: N | FD56: B | FE56: N | FF56: N | FG56: N | FH56: N | FI56: N | FJ56: N | FK56: N | FL56: N | FM56: 0 | FN56: N | FO56: N | FP56: N | FQ56: N | FR56: 0 | FS56: 0 | FT56: N | FV56: 0 | FY56: N | FZ56: N | GA56: 1 | GB56: M | GC56: N | GD56: N | GE56: N | GF56: 0 | GG56: O | GH56: N | GI56: N | GJ56: N | GK56: Y | GL56: P | GM56: 0 | GN56: 0 | GO56: Y | GP56: Y | GQ56: Y | GR56: 2 | GS56: 2 | GT56: 0 | GU56: 0 | GV56: 0 | GW56: N | GX56: Y | HB56: N | HC56: 0 | HD56: N | HE56: N | HG56: 0 | HH56: 0 | HI56: 0 | HJ56: 0 | HK56: 0 | HM56: N | HO56: 0 | HP56: 0 | HR56: 0 | HS56: 0 | HT56: 0 | HU56: 0 | HV56: D | HW56: W | HY56: 9 | HZ56: 0 | IA56: 12 | IB56: Y | IC56: Y | ID56: Y | IE56: N
A57: AC | B57: PHBK-LPSM | C57: KREDIT PHBK-KSM/LPSM | D57: 101 | E57: On B/S,Program,KMK-I | G57: 8 | H57: 240 | I57: IDR | J57: 31 | K57: 0.06 | L57: 0.36 | M57: 0.06 | N57: 0.36 | O57: N | P57: 1 | Q57: M | R57: 0 | S57: 0 | T57: Y | U57: Y | V57: N | W57: 0 | X57: I | Y57: 1 | Z57: 0 | AA57: 0 | AB57: 0 | AC57: 0 | AD57: 0 | AE57: 0 | AF57: 7 | AG57: 21 | AH57: 35 | AI57: 49 | AJ57: 63 | AK57: 77 | AL57: 0 | AM57: 0 | AN57: 0 | AO57: Y | AP57: R | AQ57: 0 | AR57: 0 | AS57: 1 | AT57: 0 | AU57: Y | BC57: 0 | BD57: 0 | BE57: 0 | BF57: 0 | BG57: 0 | BH57: 0 | BI57: N | BJ57: N | BK57: N | BL57: N | BM57: N | BN57: N | BU57: 0 | BV57: 0 | BW57: 0 | BX57: 0 | BY57: 0 | BZ57: 0 | CA57: P | CB57: N | CC57: N | CD57: N | CE57: N | CF57: N | CG57: N | CH57: N | CI57: 0 | CJ57: N | CL57: 0 | CM57: N | CN57: 0 | CO57: N | CP57: N | CQ57: A | CR57: N | CT57: Y | CU57: 4 | CV57: N | CW57: N | CY57: N | DA57: Y | DC57: 0 | DD57: O | DG57: N | DH57: N | DI57: N | DJ57: N | DK57: N | DP57: 0 | DQ57: 0 | DR57: 90 | DS57: 90 | DT57: 0 | DU57: 0 | DV57: N | DW57: P | DX57: P | DY57: 17 | DZ57: N | EC57: D | ED57: 2 | EE57: R | EF57: 100 | EG57: N | EH57: N | EI57: N | EJ57: N | EK57: N | EL57: 1 | EM57: N | EO57: 99 | EP57: P | EQ57: Y | ER57: N | ES57: 0 | EV57: Y | EW57: 0 | EX57: N | EY57: N | EZ57: N | FA57: N | FB57: Y | FC57: N | FD57: B | FE57: N | FF57: N | FG57: N | FH57: N | FI57: N | FJ57: N | FK57: N | FL57: N | FM57: 0 | FN57: N | FO57: N | FP57: N | FQ57: N | FR57: 0 | FS57: 0 | FT57: N | FV57: 0 | FY57: N | FZ57: N | GA57: 1 | GB57: M | GC57: N | GD57: N | GE57: N | GF57: 0 | GG57: O | GH57: N | GI57: Y | GJ57: N | GK57: Y | GL57: P | GM57: 0 | GN57: 0 | GO57: Y | GP57: Y | GQ57: N | GR57: 2 | GS57: 0 | GT57: 0 | GU57: 0 | GV57: 0 | GW57: N | GX57: Y | HB57: N | HC57: 0 | HD57: N | HE57: N | HG57: 0 | HH57: 0 | HI57: 0 | HJ57: 0 | HK57: 0 | HM57: N | HO57: 0 | HP57: 0 | HR57: 0 | HS57: 0 | HT57: 0 | HU57: 0 | HV57: D | HW57: W | HY57: 0 | HZ57: 0 | IA57: 0 | IB57: N | IC57: N | ID57: N | IE57: N
A58: AD | B58: KR BIDAN | C58: KREDIT BIDAN | D58: 101 | E58: On B/S, Program, KMK | G58: 8 | H58: 240 | I58: IDR | J58: 7 | K58: 0.06 | L58: 0.36 | M58: 0.06 | N58: 0.36 | O58: N | P58: 1 | Q58: M | R58: 0 | S58: 0 | T58: Y | U58: Y | V58: N | W58: 0 | X58: I | Y58: 1 | Z58: 0 | AA58: 0 | AB58: 0 | AC58: 0 | AD58: 0 | AE58: 0 | AF58: 7 | AG58: 21 | AH58: 35 | AI58: 49 | AJ58: 63 | AK58: 77 | AL58: 0 | AM58: 0 | AN58: 0 | AO58: Y | AP58: R | AQ58: 0 | AR58: 0 | AS58: 14 | AT58: 0 | AU58: Y | BC58: 0 | BD58: 0 | BE58: 0 | BF58: 0 | BG58: 0 | BH58: 0 | BI58: N | BJ58: N | BK58: N | BL58: N | BM58: N | BN58: N | BU58: 0 | BV58: 0 | BW58: 0 | BX58: 0 | BY58: 0 | BZ58: 0 | CA58: P | CB58: N | CC58: N | CD58: N | CE58: N | CF58: N | CG58: N | CH58: N | CI58: 0 | CJ58: N | CL58: 0 | CM58: N | CN58: 0 | CO58: N | CP58: N | CQ58: A | CR58: N | CT58: Y | CU58: 4 | CV58: N | CW58: N | CY58: N | DA58: Y | DC58: 0 | DD58: O | DG58: N | DH58: N | DI58: N | DJ58: N | DK58: N | DP58: 0 | DQ58: 0 | DR58: 90 | DS58: 90 | DT58: 0 | DU58: 0 | DV58: N | DW58: P | DX58: P | DY58: 17 | DZ58: N | EC58: F | ED58: 5 | EE58: R | EF58: 100 | EG58: N | EH58: N | EI58: N | EJ58: Z | EK58: N | EL58: 1 | EM58: N | EO58: 0 | EP58: P | EQ58: N | ER58: N | ES58: 0 | EV58: Y | EW58: 0 | EX58: N | EY58: N | EZ58: N | FA58: N | FB58: Y | FC58: N | FD58: B | FE58: N | FF58: N | FG58: N | FH58: N | FI58: N | FJ58: N | FK58: N | FL58: N | FM58: 0 | FN58: N | FO58: N | FP58: N | FQ58: N | FR58: 0 | FS58: 0 | FT58: N | FV58: 0 | FY58: N | FZ58: N | GA58: 1 | GB58: M | GC58: N | GD58: N | GE58: N | GF58: 0 | GG58: O | GH58: N | GI58: N | GJ58: N | GK58: Y | GL58: P | GM58: 0 | GN58: 0 | GO58: Y | GP58: Y | GQ58: Y | GR58: 2 | GS58: 2 | GT58: 0 | GU58: 0 | GV58: 0 | GW58: N | GX58: Y | HB58: N | HC58: 0 | HD58: N | HE58: N | HG58: 0 | HH58: 0 | HI58: 0 | HJ58: 0 | HK58: 0 | HM58: N | HO58: 0 | HP58: 0 | HR58: 0 | HS58: 0 | HT58: 0 | HU58: 0 | HV58: D | HW58: W | HY58: 0 | HZ58: 0 | IA58: 0 | IB58: Y | IC58: N | ID58: Y | IE58: N
A59: AE | B59: KPKU | C59: KREDIT KPKU PROKESRA | D59: 101 | E59: On B/S,Program,KMK-I | G59: 8 | H59: 240 | I59: IDR | J59: 31 | K59: 0.06 | L59: 0.36 | M59: 0.06 | N59: 0.36 | O59: N | P59: 1 | Q59: M | R59: 6 | S59: 10 | T59: Y | U59: Y | V59: N | W59: 0 | X59: I | Y59: 1 | Z59: 0 | AA59: 0 | AB59: 0 | AC59: 0 | AD59: 0 | AE59: 0 | AF59: 7 | AG59: 21 | AH59: 35 | AI59: 49 | AJ59: 63 | AK59: 77 | AL59: 0 | AM59: 0 | AN59: 0 | AO59: Y | AP59: R | AQ59: 0 | AR59: 0 | AS59: 1 | AT59: 0 | AU59: Y | BC59: 0 | BD59: 0 | BE59: 0 | BF59: 0 | BG59: 0 | BH59: 0 | BI59: N | BJ59: N | BK59: N | BL59: N | BM59: N | BN59: N | BU59: 0 | BV59: 0 | BW59: 0 | BX59: 0 | BY59: 0 | BZ59: 0 | CA59: P | CB59: N | CC59: N | CD59: N | CE59: N | CF59: N | CG59: N | CH59: N | CI59: 0 | CJ59: N | CL59: 0 | CM59: N | CN59: 0 | CO59: N | CP59: N | CQ59: A | CR59: N | CT59: Y | CU59: 4 | CV59: N | CW59: N | CY59: N | DA59: Y | DC59: 0 | DD59: O | DG59: N | DH59: N | DI59: N | DJ59: N | DK59: N | DP59: 0 | DQ59: 0 | DR59: 90 | DS59: 90 | DT59: 0 | DU59: 0 | DV59: N | DW59: P | DX59: P | DY59: 15 | DZ59: N | EC59: D | ED59: 2 | EE59: R | EF59: 100 | EG59: N | EH59: N | EI59: N | EJ59: Z | EK59: N | EL59: 1 | EM59: N | EO59: 99 | EP59: P | EQ59: Y | ER59: N | ES59: 0 | EV59: Y | EW59: 0 | EX59: N | EY59: N | EZ59: N | FA59: N | FB59: Y | FC59: N | FD59: B | FE59: N | FF59: N | FG59: N | FH59: N | FI59: N | FJ59: N | FK59: N | FL59: N | FM59: 0 | FN59: N | FO59: N | FP59: N | FQ59: N | FR59: 0 | FS59: 0 | FT59: N | FV59: 0 | FY59: N | FZ59: N | GA59: 1 | GB59: M | GC59: N | GD59: N | GE59: N | GF59: 0 | GG59: O | GH59: N | GI59: Y | GJ59: N | GK59: Y | GL59: P | GM59: 0 | GN59: 0 | GO59: Y | GP59: Y | GQ59: N | GR59: 2 | GS59: 0 | GT59: 0 | GU59: 0 | GV59: 0 | GW59: N | GX59: Y | HB59: N | HC59: 0 | HD59: N | HE59: N | HG59: 0 | HH59: 0 | HI59: 0 | HJ59: 0 | HK59: 0 | HM59: N | HO59: 0 | HP59: 0 | HR59: 0 | HS59: 0 | HT59: 0 | HU59: 0 | HV59: D | HW59: W | HY59: 0 | HZ59: 0 | IA59: 0 | IB59: N | IC59: N | ID59: N | IE59: N
A60: AF | B60: PHBK-KSM | C60: KREDIT PHBK-KSM | D60: 101 | E60: On B/S,Program,KMK-I | G60: 8 | H60: 240 | I60: IDR | J60: 31 | K60: 0.06 | L60: 0.36 | M60: 0.06 | N60: 0.36 | O60: N | P60: 1 | Q60: M | R60: 6 | S60: 0 | T60: Y | U60: Y | V60: N | W60: 0 | X60: I | Y60: 1 | Z60: 0 | AA60: 0 | AB60: 0 | AC60: 0 | AD60: 0 | AE60: 0 | AF60: 7 | AG60: 21 | AH60: 35 | AI60: 49 | AJ60: 63 | AK60: 77 | AL60: 0 | AM60: 0 | AN60: 0 | AO60: Y | AP60: R | AQ60: 0 | AR60: 0 | AS60: 1 | AT60: 0 | AU60: Y | BC60: 0 | BD60: 0 | BE60: 0 | BF60: 0 | BG60: 0 | BH60: 0 | BI60: N | BJ60: N | BK60: N | BL60: N | BM60: N | BN60: N | BU60: 0 | BV60: 0 | BW60: 0 | BX60: 0 | BY60: 0 | BZ60: 0 | CA60: P | CB60: N | CC60: N | CD60: N | CE60: N | CF60: N | CG60: N | CH60: N | CI60: 0 | CJ60: N | CL60: 0 | CM60: N | CN60: 0 | CO60: N | CP60: N | CQ60: A | CR60: N | CT60: Y | CU60: 4 | CV60: N | CW60: N | CY60: N | DA60: Y | DC60: 0 | DD60: O | DG60: N | DH60: N | DI60: N | DJ60: N | DK60: N | DP60: 0 | DQ60: 0 | DR60: 90 | DS60: 90 | DT60: 0 | DU60: 0 | DV60: N | DW60: P | DX60: P | DY60: 17 | DZ60: N | EC60: D | ED60: 2 | EE60: R | EF60: 100 | EG60: N | EH60: N | EI60: N | EJ60: N | EK60: N | EL60: 1 | EM60: N | EO60: 99 | EP60: P | EQ60: Y | ER60: N | ES60: 0 | EV60: Y | EW60: 0 | EX60: N | EY60: N | EZ60: N | FA60: N | FB60: Y | FC60: N | FD60: B | FE60: N | FF60: N | FG60: N | FH60: N | FI60: N | FJ60: N | FK60: N | FL60: N | FM60: 0 | FN60: N | FO60: N | FP60: N | FQ60: N | FR60: 0 | FS60: 0 | FT60: N | FV60: 0 | FY60: N | FZ60: N | GA60: 1 | GB60: M | GC60: N | GD60: N | GE60: N | GF60: 0 | GG60: O | GH60: N | GI60: Y | GJ60: N | GK60: Y | GL60: P | GM60: 0 | GN60: 0 | GO60: Y | GP60: Y | GQ60: N | GR60: 2 | GS60: 0 | GT60: 0 | GU60: 0 | GV60: 0 | GW60: N | GX60: Y | HB60: N | HC60: 0 | HD60: N | HE60: N | HG60: 0 | HH60: 0 | HI60: 0 | HJ60: 0 | HK60: 0 | HM60: N | HO60: 0 | HP60: 0 | HR60: 0 | HS60: 0 | HT60: 0 | HU60: 0 | HV60: D | HW60: W | HY60: 0 | HZ60: 0 | IA60: 0 | IB60: N | IC60: N | ID60: N | IE60: N
A61: AG | B61: R/C PUPUK | C61: R/C PUPUK | D61: 101 | E61: On B/S, Program, KMK | G61: 8 | H61: 240 | I61: IDR | J61: 31 | K61: 0.08 | L61: 0.36 | M61: 0.08 | N61: 0.36 | O61: N | P61: 1 | Q61: M | R61: 6 | S61: 0 | T61: Y | U61: Y | V61: N | W61: 0 | X61: I | Y61: 1 | Z61: 0 | AA61: 0 | AB61: 0 | AC61: 0 | AD61: 0 | AE61: 0 | AF61: 7 | AG61: 21 | AH61: 35 | AI61: 0 | AJ61: 0 | AK61: 0 | AL61: 0 | AM61: 0 | AN61: 0 | AO61: Y | AP61: R | AQ61: 0 | AR61: 0 | AS61: 0 | AT61: 0 | AU61: Y | BC61: 0 | BD61: 0 | BE61: 0 | BF61: 0 | BG61: 0 | BH61: 0 | BI61: N | BJ61: N | BK61: N | BL61: N | BM61: N | BN61: N | BU61: 0 | BV61: 0 | BW61: 0 | BX61: 0 | BY61: 0 | BZ61: 0 | CA61: P | CB61: N | CC61: N | CD61: N | CE61: N | CF61: N | CG61: N | CH61: N | CI61: 0 | CJ61: N | CL61: 0 | CM61: N | CN61: 0 | CO61: N | CP61: N | CQ61: A | CR61: N | CT61: N | CU61: 4 | CV61: N | CW61: N | CY61: N | DA61: Y | DC61: 0 | DD61: P | DG61: N | DH61: N | DI61: N | DJ61: N | DK61: N | DP61: 0 | DQ61: 0 | DR61: 90 | DS61: 90 | DT61: 0 | DU61: 0 | DV61: N | DW61: P | DX61: P | DY61: 15 | DZ61: N | EC61: D | ED61: 2 | EE61: R | EF61: 100 | EG61: N | EH61: N | EI61: N | EJ61: Z | EK61: N | EL61: 1 | EM61: N | EO61: 99 | EP61: X | EQ61: Y | ER61: N | ES61: 0 | EV61: Y | EW61: 6 | EX61: N | EY61: N | EZ61: Y | FA61: N | FB61: Y | FC61: N | FD61: B | FE61: N | FF61: N | FG61: N | FH61: N | FI61: N | FJ61: N | FK61: N | FL61: N | FM61: 0 | FN61: N | FO61: N | FP61: N | FQ61: N | FR61: 0 | FS61: 0 | FT61: N | FV61: 0 | FY61: N | FZ61: N | GA61: 1 | GB61: M | GC61: N | GD61: N | GE61: N | GF61: 0 | GG61: O | GH61: N | GI61: Y | GJ61: N | GK61: Y | GL61: P | GM61: 0 | GN61: 0 | GO61: N | GP61: Y | GQ61: N | GR61: 2 | GS61: 0 | GT61: 0 | GU61: 0 | GV61: 0 | GW61: N | GX61: Y | HB61: N | HC61: 0 | HD61: N | HE61: Y | HF61: O | HG61: 0 | HH61: 0 | HI61: 0.02 | HJ61: 0 | HK61: 0 | HL61: 18 | HM61: N | HO61: 0 | HP61: 0 | HR61: 0 | HS61: 0 | HT61: 0 | HU61: 0 | HV61: D | HW61: W | HY61: 0 | HZ61: 0 | IA61: 0 | IB61: N | IC61: N | ID61: N | IE61: N
A62: A3 | B62: KKP PANGAN | C62: KKP PENGADAAN PANGAN | D62: 101 | E62: On B/S,Program,KMK-I | G62: 8 | H62: 240 | I62: IDR | J62: 31 | K62: 0.01 | L62: 0.2 | M62: 0.01 | N62: 0.2 | O62: N | P62: 1 | Q62: M | R62: 6 | S62: 10 | T62: Y | U62: Y | V62: N | W62: 0 | X62: I | Y62: 1 | Z62: 0 | AA62: 0 | AB62: 0 | AC62: 0 | AD62: 0 | AE62: 0 | AF62: 7 | AG62: 15 | AH62: 22 | AI62: 34 | AJ62: 49 | AK62: 63 | AL62: 0 | AM62: 0 | AN62: 0 | AO62: Y | AP62: R | AQ62: 0 | AR62: 0 | AS62: 1 | AT62: 0 | AU62: Y | BC62: 0 | BD62: 0 | BE62: 0 | BF62: 0 | BG62: 0 | BH62: 0 | BI62: N | BJ62: N | BK62: N | BL62: N | BM62: N | BN62: N | BU62: 0 | BV62: 0 | BW62: 0 | BX62: 0 | BY62: 0 | BZ62: 0 | CA62: P | CB62: N | CC62: N | CD62: N | CE62: N | CF62: N | CG62: N | CH62: Y | CI62: 0 | CL62: 0 | CM62: N | CN62: 0 | CO62: Y | CP62: N | CQ62: A | CR62: N | CT62: N | CU62: 4 | CV62: N | CW62: N | CY62: N | DA62: Y | DC62: 0 | DD62: P | DG62: N | DH62: N | DI62: N | DJ62: N | DK62: N | DP62: 0 | DQ62: 0 | DR62: 90 | DS62: 90 | DT62: 0 | DU62: 0 | DV62: N | DW62: P | DZ62: N | EC62: D | ED62: 0 | EE62: R | EF62: 100 | EG62: N | EH62: N | EI62: N | EJ62: N | EK62: N | EL62: 1 | EM62: N | EO62: 0 | EP62: P | EQ62: Y | ES62: 0 | EV62: N | EW62: 6 | EX62: N | EY62: N | EZ62: Y | FA62: N | FB62: N | FC62: Y | FE62: N | FF62: N | FG62: N | FH62: Y | FI62: N | FJ62: N | FK62: N | FL62: Y | FM62: 0 | FN62: N | FO62: N | FP62: N | FQ62: N | FR62: 0 | FS62: 0 | FT62: N | FV62: 0 | FY62: N | FZ62: N | GA62: 1 | GB62: M | GC62: N | GD62: N | GE62: N | GF62: 0 | GH62: N | GI62: Y | GJ62: N | GK62: Y | GL62: E | GM62: 0 | GN62: 0 | GO62: N | GP62: Y | GQ62: N | GR62: 2 | GS62: 0 | GT62: 0 | GU62: 0 | GV62: 0 | GW62: N | GX62: Y | HB62: N | HC62: 0 | HD62: N | HE62: N | HG62: 0 | HH62: 0 | HI62: 0 | HJ62: 0 | HK62: 0 | HM62: N | HO62: 0 | HP62: 0 | HR62: 0 | HS62: 0 | HT62: 0 | HU62: 0 | HV62: D | HW62: W | HY62: 0 | HZ62: 0 | IA62: 0 | IB62: N | IC62: N | ID62: N | IE62: N
A63: A4 | B63: KKP TR-KOP | C63: KKP TR-KOP PRIMER | D63: 101 | E63: On B/S,Program,KMK-I | G63: 8 | H63: 240 | I63: IDR | J63: 31 | K63: 0.06 | L63: 0.2 | M63: 0.06 | N63: 0.2 | O63: N | P63: 18 | Q63: M | R63: 6 | S63: 10 | T63: Y | U63: Y | V63: N | W63: 0 | X63: I | Y63: 1 | Z63: 0 | AA63: 0 | AB63: 0 | AC63: 0 | AD63: 0 | AE63: 0 | AF63: 7 | AG63: 15 | AH63: 22 | AI63: 34 | AJ63: 49 | AK63: 63 | AL63: 0 | AM63: 0 | AN63: 0 | AO63: Y | AP63: R | AQ63: 0 | AR63: 0 | AS63: 1 | AT63: 0 | AU63: Y | BC63: 0 | BD63: 0 | BE63: 0 | BF63: 0 | BG63: 0 | BH63: 0 | BI63: N | BJ63: N | BK63: N | BL63: N | BM63: N | BN63: N | BU63: 0 | BV63: 0 | BW63: 0 | BX63: 0 | BY63: 0 | BZ63: 0 | CA63: P | CB63: N | CC63: N | CD63: N | CE63: N | CF63: N | CG63: N | CH63: Y | CI63: 0 | CL63: 0 | CM63: N | CN63: 0 | CO63: Y | CP63: N | CQ63: A | CR63: N | CT63: N | CU63: 4 | CV63: N | CW63: N | CY63: N | DA63: Y | DC63: 0 | DD63: P | DG63: N | DH63: N | DI63: N | DJ63: N | DK63: N | DP63: 0 | DQ63: 0 | DR63: 90 | DS63: 90 | DT63: 0 | DU63: 0 | DV63: N | DW63: P | DZ63: N | EC63: D | ED63: 0 | EE63: R | EF63: 100 | EG63: N | EH63: N | EI63: N | EJ63: N | EK63: N | EL63: 1 | EM63: N | EO63: 0 | EP63: X | EQ63: Y | ES63: 0 | EV63: N | EW63: 6 | EX63: N | EY63: N | EZ63: Y | FA63: N | FB63: N | FC63: N | FE63: N | FF63: N | FG63: N | FH63: Y | FI63: N | FJ63: N | FK63: N | FL63: Y | FM63: 0 | FN63: N | FO63: N | FP63: N | FQ63: N | FR63: 0 | FS63: 0 | FT63: N | FV63: 0 | FY63: N | FZ63: N | GA63: 18 | GB63: M | GC63: N | GD63: N | GE63: N | GF63: 0 | GH63: N | GI63: Y | GJ63: N | GK63: Y | GL63: X | GM63: 0 | GN63: 0 | GO63: N | GP63: Y | GQ63: N | GR63: 2 | GS63: 0 | GT63: 0 | GU63: 0 | GV63: 0 | GW63: N | GX63: Y | HB63: N | HC63: 0 | HD63: N | HE63: N | HG63: 0 | HH63: 0 | HI63: 0 | HJ63: 0 | HK63: 0 | HM63: N | HO63: 0 | HP63: 0 | HR63: 0 | HS63: 0 | HT63: 0 | HU63: 0 | HV63: D | HW63: W | HY63: 0 | HZ63: 0 | IA63: 0 | IB63: N | IC63: N | ID63: N | IE63: N
A64: A5 | B64: KKP TR-KLP | C64: KKP TR-KOP KLP TANI | D64: 101 | E64: On B/S,Program,KMK-I | G64: 8 | H64: 240 | I64: IDR | J64: 31 | K64: 0.06 | L64: 0.2 | M64: 0.06 | N64: 0.2 | O64: N | P64: 18 | Q64: M | R64: 6 | S64: 10 | T64: Y | U64: Y | V64: N | W64: 0 | X64: I | Y64: 1 | Z64: 0 | AA64: 0 | AB64: 0 | AC64: 0 | AD64: 0 | AE64: 0 | AF64: 7 | AG64: 15 | AH64: 22 | AI64: 34 | AJ64: 49 | AK64: 63 | AL64: 0 | AM64: 0 | AN64: 0 | AO64: Y | AP64: R | AQ64: 0 | AR64: 0 | AS64: 1 | AT64: 0 | AU64: Y | BC64: 0 | BD64: 0 | BE64: 0 | BF64: 0 | BG64: 0 | BH64: 0 | BI64: N | BJ64: N | BK64: N | BL64: N | BM64: N | BN64: N | BU64: 0 | BV64: 0 | BW64: 0 | BX64: 0 | BY64: 0 | BZ64: 0 | CA64: P | CB64: N | CC64: N | CD64: N | CE64: N | CF64: N | CG64: N | CH64: Y | CI64: 0 | CL64: 0 | CM64: N | CN64: 0 | CO64: Y | CP64: N | CQ64: A | CR64: N | CT64: N | CU64: 4 | CV64: N | CW64: N | CY64: N | DA64: Y | DC64: 0 | DD64: P | DG64: N | DH64: N | DI64: N | DJ64: N | DK64: N | DP64: 0 | DQ64: 0 | DR64: 90 | DS64: 90 | DT64: 0 | DU64: 0 | DV64: N | DW64: P | DZ64: N | EC64: D | ED64: 0 | EE64: R | EF64: 100 | EG64: N | EH64: N | EI64: N | EJ64: N | EK64: N | EL64: 1 | EM64: N | EO64: 0 | EP64: X | EQ64: Y | ES64: 0 | EV64: N | EW64: 6 | EX64: N | EY64: N | EZ64: Y | FA64: N | FB64: N | FC64: N | FE64: N | FF64: N | FG64: N | FH64: Y | FI64: N | FJ64: N | FK64: N | FL64: Y | FM64: 0 | FN64: N | FO64: N | FP64: N | FQ64: N | FR64: 0 | FS64: 0 | FT64: N | FV64: 0 | FY64: N | FZ64: N | GA64: 18 | GB64: M | GC64: N | GD64: N | GE64: N | GF64: 0 | GH64: N | GI64: Y | GJ64: N | GK64: Y | GL64: X | GM64: 0 | GN64: 0 | GO64: N | GP64: Y | GQ64: N | GR64: 2 | GS64: 0 | GT64: 0 | GU64: 0 | GV64: 0 | GW64: N | GX64: Y | HB64: N | HC64: 0 | HD64: N | HE64: N | HG64: 0 | HH64: 0 | HI64: 0 | HJ64: 0 | HK64: 0 | HM64: N | HO64: 0 | HP64: 0 | HR64: 0 | HS64: 0 | HT64: 0 | HU64: 0 | HV64: D | HW64: W | HY64: 0 | HZ64: 0 | IA64: 0 | IB64: N | IC64: N | ID64: N | IE64: N
A65: A6 | B65: KKP Padi | C65: KKP Padi-Jgg-Kedelai | D65: 101 | E65: On B/S,Program,KMK-I | G65: 8 | H65: 240 | I65: IDR | J65: 31 | K65: 0.01 | L65: 0.2 | M65: 0.01 | N65: 0.2 | O65: N | P65: 6 | Q65: M | R65: 6 | S65: 10 | T65: Y | U65: Y | V65: N | W65: 0 | X65: I | Y65: 1 | Z65: 0 | AA65: 0 | AB65: 0 | AC65: 0 | AD65: 0 | AE65: 0 | AF65: 7 | AG65: 15 | AH65: 22 | AI65: 34 | AJ65: 49 | AK65: 63 | AL65: 0 | AM65: 0 | AN65: 0 | AO65: Y | AP65: R | AQ65: 0 | AR65: 0 | AS65: 1 | AT65: 0 | AU65: Y | BC65: 0 | BD65: 0 | BE65: 0 | BF65: 0 | BG65: 0 | BH65: 0 | BI65: N | BJ65: N | BK65: N | BL65: N | BM65: N | BN65: N | BU65: 0 | BV65: 0 | BW65: 0 | BX65: 0 | BY65: 0 | BZ65: 0 | CA65: P | CB65: N | CC65: N | CD65: N | CE65: N | CF65: N | CG65: N | CH65: Y | CI65: 0 | CL65: 0 | CM65: N | CN65: 0 | CO65: Y | CP65: N | CQ65: A | CR65: N | CT65: N | CU65: 4 | CV65: N | CW65: N | CY65: N | DA65: Y | DC65: 0 | DD65: P | DG65: N | DH65: N | DI65: N | DJ65: N | DK65: N | DP65: 0 | DQ65: 0 | DR65: 90 | DS65: 90 | DT65: 0 | DU65: 0 | DV65: N | DW65: P | DZ65: N | EC65: D | ED65: 0 | EE65: R | EF65: 100 | EG65: N | EH65: N | EI65: N | EJ65: N | EK65: N | EL65: 1 | EM65: N | EO65: 0 | EP65: P | EQ65: Y | ES65: 0 | EV65: N | EW65: 6 | EX65: N | EY65: N | EZ65: Y | FA65: N | FB65: N | FC65: N | FE65: N | FF65: N | FG65: N | FH65: Y | FI65: N | FJ65: N | FK65: N | FL65: Y | FM65: 0 | FN65: N | FO65: N | FP65: N | FQ65: N | FR65: 0 | FS65: 0 | FT65: N | FV65: 0 | FY65: N | FZ65: N | GA65: 6 | GB65: M | GC65: N | GD65: N | GE65: N | GF65: 0 | GH65: N | GI65: Y | GJ65: N | GK65: Y | GL65: P | GM65: 0 | GN65: 0 | GO65: N | GP65: Y | GQ65: N | GR65: 2 | GS65: 0 | GT65: 0 | GU65: 0 | GV65: 0 | GW65: N | GX65: Y | HB65: N | HC65: 0 | HD65: N | HE65: N | HG65: 0 | HH65: 0 | HI65: 0 | HJ65: 0 | HK65: 0 | HM65: N | HO65: 0 | HP65: 0 | HR65: 0 | HS65: 0 | HT65: 0 | HU65: 0 | HV65: D | HW65: W | HY65: 0 | HZ65: 0 | IA65: 0 | IB65: N | IC65: N | ID65: N | IE65: N
A66: I1 | B66: KR. PUKK | C66: KREDIT PUKK | D66: 301 | E66: POffB,Perhit Bunga K | G66: 8 | H66: 240 | I66: IDR | J66: 31 | K66: 0.01 | L66: 0.36 | M66: 0.01 | N66: 0.36 | O66: N | P66: 1 | Q66: M | R66: 6 | S66: 0 | T66: Y | U66: N | V66: N | W66: 0 | X66: I | Y66: 1 | Z66: 0 | AA66: 0 | AB66: 0 | AC66: 0 | AD66: 0 | AE66: 0 | AF66: 7 | AG66: 15 | AH66: 22 | AI66: 34 | AJ66: 49 | AK66: 63 | AL66: 0 | AM66: 0 | AN66: 0 | AO66: Y | AP66: R | AQ66: 0 | AR66: 0 | AS66: 1 | AT66: 0 | AU66: Y | BC66: 0 | BD66: 0 | BE66: 0 | BF66: 0 | BG66: 0 | BH66: 0 | BI66: N | BJ66: N | BK66: N | BL66: N | BM66: N | BN66: N | BU66: 0 | BV66: 0 | BW66: 0 | BX66: 0 | BY66: 0 | BZ66: 0 | CB66: N | CC66: N | CD66: N | CE66: N | CF66: N | CG66: N | CH66: N | CI66: 0 | CL66: 0 | CM66: N | CN66: 0 | CO66: Y | CP66: N | CQ66: A | CR66: N | CT66: Y | CU66: 4 | CV66: N | CW66: N | CY66: N | DA66: Y | DC66: 0 | DD66: O | DG66: N | DH66: N | DI66: N | DJ66: N | DK66: N | DP66: 0 | DQ66: 0 | DR66: 90 | DS66: 90 | DT66: 0 | DU66: 0 | DV66: N | DZ66: N | EC66: D | ED66: 2 | EE66: R | EF66: 100 | EG66: N | EH66: N | EI66: N | EJ66: Z | EK66: N | EL66: 9 | EM66: N | EO66: 0 | EP66: P | EQ66: Y | ES66: 0 | EV66: Y | EW66: 6 | EX66: N | EY66: N | EZ66: N | FA66: N | FB66: Y | FC66: N | FE66: N | FF66: N | FG66: N | FH66: N | FI66: N | FJ66: N | FK66: N | FL66: N | FM66: 0 | FN66: N | FO66: N | FP66: N | FQ66: N | FR66: 0 | FS66: 0 | FT66: N | FV66: 0 | FY66: N | FZ66: N | GA66: 1 | GB66: M | GC66: N | GD66: N | GE66: N | GF66: 0 | GH66: N | GI66: N | GJ66: N | GK66: Y | GL66: P | GM66: 0 | GN66: 0 | GO66: Y | GP66: Y | GQ66: N | GR66: 0 | GS66: 0 | GT66: 0 | GU66: 0 | GV66: 0 | GW66: N | GX66: Y | HB66: N | HC66: 0 | HD66: N | HE66: Y | HF66: O | HG66: 0 | HH66: 0 | HI66: 0 | HJ66: 0 | HK66: 0 | HL66: 18 | HM66: N | HO66: 0 | HP66: 0 | HR66: 0 | HS66: 0 | HT66: 0 | HU66: 0 | HV66: D | HW66: W | HY66: 0 | HZ66: 0 | IA66: 0 | IB66: N | IC66: N | ID66: N | IE66: N
A67: I2 | B67: KR.DANABBM | C67: KRD PENYL DANA-BBM | D67: 301 | E67: POffB, Perhit Bunga | G67: 8 | H67: 240 | I67: IDR | J67: 0 | K67: 0.06 | L67: 0.36 | M67: 0.06 | N67: 0.36 | O67: N | P67: 36 | Q67: M | R67: 6 | S67: 0 | T67: Y | U67: N | V67: N | W67: 0 | X67: I | Y67: 1 | Z67: 0 | AA67: 0 | AB67: 0 | AC67: 0 | AD67: 0 | AE67: 0 | AF67: 7 | AG67: 15 | AH67: 22 | AI67: 34 | AJ67: 49 | AK67: 63 | AL67: 0 | AM67: 0 | AN67: 0 | AO67: Y | AP67: R | AQ67: 0 | AR67: 0 | AS67: 1 | AT67: 0 | AU67: Y | BC67: 0 | BD67: 0 | BE67: 0 | BF67: 0 | BG67: 0 | BH67: 0 | BI67: N | BJ67: N | BK67: N | BL67: N | BM67: N | BN67: N | BU67: 0 | BV67: 0 | BW67: 0 | BX67: 0 | BY67: 0 | BZ67: 0 | CB67: N | CC67: N | CD67: N | CE67: N | CF67: N | CG67: N | CH67: N | CI67: 0 | CL67: 0 | CM67: N | CN67: 0 | CO67: Y | CP67: N | CQ67: A | CR67: N | CT67: Y | CU67: 4 | CV67: N | CW67: N | CY67: N | DA67: N | DC67: 0 | DD67: O | DG67: N | DH67: N | DI67: N | DJ67: N | DK67: N | DP67: 0 | DQ67: 0 | DR67: 90 | DS67: 90 | DT67: 0 | DU67: 0 | DV67: N | DZ67: N | EC67: M | ED67: 2 | EE67: R | EF67: 100 | EG67: N | EH67: N | EI67: N | EJ67: Z | EK67: N | EL67: 9 | EM67: N | EO67: 0 | EP67: X | EQ67: N | ES67: 0 | EV67: Y | EW67: 2 | EX67: N | EY67: N | EZ67: N | FA67: N | FB67: Y | FC67: N | FE67: N | FF67: N | FG67: N | FH67: N | FI67: N | FJ67: N | FK67: N | FL67: N | FM67: 0 | FN67: N | FO67: N | FP67: N | FQ67: N | FR67: 0 | FS67: 0 | FT67: N | FV67: 0 | FY67: N | FZ67: N | GA67: 3 | GB67: M | GC67: N | GD67: N | GE67: N | GF67: 0 | GH67: N | GI67: N | GJ67: N | GK67: Y | GL67: E | GM67: 0 | GN67: 0 | GO67: Y | GP67: Y | GQ67: N | GR67: 0 | GS67: 0 | GT67: 0 | GU67: 0 | GV67: 0 | GW67: N | GX67: N | HB67: N | HC67: 0 | HD67: N | HE67: N | HG67: 0 | HH67: 0 | HI67: 0 | HJ67: 0 | HK67: 0 | HM67: N | HO67: 0 | HP67: 0 | HR67: 0 | HS67: 0 | HT67: 0 | HU67: 0 | HV67: D | HW67: W | HY67: 0 | HZ67: 0 | IA67: 0 | IB67: N | IC67: N | ID67: N | IE67: N
A68: AH | B68: PINJ BULOG | C68: PINJAMAN BULOG | D68: 101 | E68: On B/S,Program,KMK-I | G68: 8 | H68: 240 | I68: IDR | J68: 31 | K68: 0 | L68: 0.36 | M68: 0 | N68: 0.36 | O68: N | P68: 12 | Q68: M | R68: 6 | S68: 0 | T68: Y | U68: Y | V68: N | W68: 0 | X68: I | Y68: 1 | Z68: 0 | AA68: 0 | AB68: 0 | AC68: 0 | AD68: 0 | AE68: 0 | AF68: 7 | AG68: 21 | AH68: 35 | AI68: 49 | AJ68: 63 | AK68: 77 | AL68: 0 | AM68: 0 | AN68: 0 | AO68: Y | AP68: R | AQ68: 0 | AR68: 0 | AS68: 0 | AT68: 0 | AU68: Y | BC68: 0 | BD68: 0 | BE68: 0 | BF68: 0 | BG68: 0 | BH68: 0 | BI68: N | BJ68: N | BK68: N | BL68: N | BM68: N | BN68: N | BU68: 0 | BV68: 0 | BW68: 0 | BX68: 0 | BY68: 0 | BZ68: 0 | CA68: P | CB68: N | CC68: N | CD68: N | CE68: N | CF68: N | CG68: N | CH68: N | CI68: 0 | CJ68: N | CL68: 0 | CM68: N | CN68: 0 | CO68: Y | CP68: N | CQ68: B | CR68: N | CT68: N | CU68: 4 | CV68: N | CW68: N | CY68: N | DA68: Y | DC68: 0 | DD68: P | DG68: N | DH68: N | DI68: N | DJ68: N | DK68: N | DP68: 0 | DQ68: 0 | DR68: 90 | DS68: 90 | DT68: 0 | DU68: 0 | DV68: N | DW68: P | DY68: 15 | DZ68: N | EC68: D | ED68: 2 | EE68: R | EF68: 100 | EG68: N | EH68: N | EI68: N | EJ68: Z | EK68: N | EL68: 1 | EM68: N | EO68: 99 | EP68: X | EQ68: Y | ER68: N | ES68: 0 | EV68: Y | EW68: 2 | EX68: N | EY68: N | EZ68: Y | FA68: N | FB68: Y | FC68: N | FD68: B | FE68: N | FF68: N | FG68: N | FH68: N | FI68: N | FJ68: N | FK68: N | FL68: N | FM68: 0 | FN68: N | FO68: N | FP68: N | FQ68: N | FR68: 0 | FS68: 0 | FT68: N | FV68: 0 | FY68: N | FZ68: N | GA68: 3 | GB68: M | GC68: N | GD68: N | GE68: N | GF68: 0 | GG68: O | GH68: N | GI68: Y | GJ68: N | GK68: Y | GL68: P | GM68: 0 | GN68: 0 | GO68: N | GP68: Y | GQ68: N | GR68: 2 | GS68: 0 | GT68: 0 | GU68: 0 | GV68: 0 | GW68: N | GX68: N | HB68: N | HC68: 0 | HD68: N | HE68: N | HG68: 0 | HH68: 0 | HI68: 0 | HJ68: 0 | HK68: 0 | HM68: N | HO68: 0 | HP68: 0 | HR68: 0 | HS68: 0 | HT68: 0 | HU68: 0 | HV68: D | HW68: W | HY68: 0 | HZ68: 0 | IA68: 0 | IB68: N | IC68: N | ID68: N | IE68: N
A69: A7 | B69: P4K 2001 | C69: KRD P4K 2001 BULANAN | D69: 101 | E69: On B/S, Program, KMK | G69: 8 | H69: 240 | I69: IDR | J69: 7 | K69: 0.12 | L69: 0.36 | M69: 0.12 | N69: 0.36 | O69: N | P69: 1 | Q69: M | R69: 0 | S69: 0 | T69: Y | U69: Y | V69: N | W69: 0 | X69: I | Y69: 1 | Z69: 0 | AA69: 0 | AB69: 0 | AC69: 0 | AD69: 0 | AE69: 0 | AF69: 7 | AG69: 21 | AH69: 35 | AI69: 49 | AJ69: 63 | AK69: 77 | AL69: 0 | AM69: 0 | AN69: 0 | AO69: Y | AP69: R | AQ69: 0 | AR69: 0 | AS69: 1 | AT69: 0 | AU69: Y | BC69: 0 | BD69: 0 | BE69: 0 | BF69: 0 | BG69: 0 | BH69: 0 | BI69: N | BJ69: N | BK69: N | BL69: N | BM69: N | BN69: N | BU69: 0 | BV69: 0 | BW69: 0 | BX69: 0 | BY69: 0 | BZ69: 0 | CA69: P | CB69: N | CC69: N | CD69: N | CE69: N | CF69: N | CG69: N | CH69: N | CI69: 0 | CJ69: N | CL69: 0 | CM69: N | CN69: 0 | CO69: N | CP69: N | CQ69: A | CR69: N | CT69: Y | CU69: 4 | CV69: N | CW69: N | CY69: N | DA69: Y | DC69: 0 | DD69: O | DG69: N | DH69: N | DI69: N | DJ69: N | DK69: N | DP69: 0 | DQ69: 0 | DR69: 90 | DS69: 90 | DT69: 0 | DU69: 0 | DV69: N | DW69: P | DX69: P | DY69: 17 | DZ69: N | EC69: F | ED69: 5 | EE69: R | EF69: 100 | EG69: N | EH69: N | EI69: N | EJ69: Z | EK69: N | EL69: 1 | EM69: N | EO69: 0 | EP69: P | EQ69: Y | ER69: N | ES69: 0 | EV69: Y | EW69: 0 | EX69: N | EY69: N | EZ69: N | FA69: N | FB69: Y | FC69: N | FD69: B | FE69: N | FF69: N | FG69: N | FH69: N | FI69: N | FJ69: N | FK69: N | FL69: N | FM69: 0 | FN69: N | FO69: N | FP69: N | FQ69: N | FR69: 0 | FS69: 0 | FT69: N | FV69: 0 | FY69: N | FZ69: N | GA69: 1 | GB69: M | GC69: N | GD69: N | GE69: N | GF69: 0 | GG69: O | GH69: N | GI69: N | GJ69: N | GK69: Y | GL69: P | GM69: 0 | GN69: 0 | GO69: Y | GP69: Y | GQ69: Y | GR69: 2 | GS69: 2 | GT69: 0 | GU69: 0 | GV69: 0 | GW69: N | GX69: Y | HB69: N | HC69: 0 | HD69: N | HE69: N | HG69: 0 | HH69: 0 | HI69: 0 | HJ69: 0 | HK69: 0 | HM69: N | HO69: 0 | HP69: 0 | HR69: 0 | HS69: 0 | HT69: 0 | HU69: 0 | HV69: D | HW69: W | HY69: 9 | HZ69: 0 | IA69: 12 | IB69: Y | IC69: Y | ID69: Y | IE69: N
A70: AI | B70: MOISTER-T | C70: PINJ MOISTER TESTER | D70: 101 | E70: On B/S, Program, KMK | G70: 8 | H70: 240 | I70: IDR | J70: 31 | K70: 0.08 | L70: 0.36 | M70: 0.08 | N70: 0.36 | O70: N | P70: 1 | Q70: M | R70: 6 | S70: 0 | T70: Y | U70: Y | V70: N | W70: 0 | X70: I | Y70: 1 | Z70: 0 | AA70: 0 | AB70: 0 | AC70: 0 | AD70: 0 | AE70: 0 | AF70: 7 | AG70: 21 | AH70: 35 | AI70: 49 | AJ70: 63 | AK70: 77 | AL70: 0 | AM70: 0 | AN70: 0 | AO70: Y | AP70: R | AQ70: 0 | AR70: 0 | AS70: 1 | AT70: 0 | AU70: Y | BC70: 0 | BD70: 0 | BE70: 0 | BF70: 0 | BG70: 0 | BH70: 0 | BI70: N | BJ70: N | BK70: N | BL70: N | BM70: N | BN70: N | BU70: 0 | BV70: 0 | BW70: 0 | BX70: 0 | BY70: 0 | BZ70: 0 | CA70: P | CB70: N | CC70: N | CD70: N | CE70: N | CF70: N | CG70: N | CH70: N | CI70: 0 | CJ70: N | CL70: 0 | CM70: N | CN70: 0 | CO70: N | CP70: N | CQ70: A | CR70: N | CT70: Y | CU70: 4 | CV70: N | CW70: N | CY70: N | DA70: Y | DC70: 0 | DD70: P | DG70: N | DH70: N | DI70: N | DJ70: N | DK70: N | DP70: 0 | DQ70: 0 | DR70: 90 | DS70: 90 | DT70: 0 | DU70: 0 | DV70: N | DW70: P | DX70: P | DY70: 15 | DZ70: N | EC70: D | ED70: 2 | EE70: R | EF70: 100 | EG70: N | EH70: N | EI70: N | EJ70: Z | EK70: N | EL70: 1 | EM70: N | EO70: 99 | EP70: P | EQ70: Y | ER70: N | ES70: 0 | EV70: Y | EW70: 1 | EX70: N | EY70: N | EZ70: Y | FA70: N | FB70: Y | FC70: N | FD70: B | FE70: N | FF70: N | FG70: N | FH70: N | FI70: N | FJ70: N | FK70: N | FL70: N | FM70: 0 | FN70: N | FO70: N | FP70: N | FQ70: N | FR70: 0 | FS70: 0 | FT70: N | FV70: 0 | FY70: N | FZ70: N | GA70: 1 | GB70: M | GC70: N | GD70: N | GE70: N | GF70: 0 | GG70: O | GH70: N | GI70: Y | GJ70: N | GK70: Y | GL70: P | GM70: 0 | GN70: 0 | GO70: N | GP70: Y | GQ70: N | GR70: 2 | GS70: 0 | GT70: 0 | GU70: 0 | GV70: 0 | GW70: N | GX70: Y | HB70: N | HC70: 0 | HD70: N | HE70: N | HG70: 0 | HH70: 0 | HI70: 0 | HJ70: 0 | HK70: 0 | HM70: N | HO70: 0 | HP70: 0 | HR70: 0 | HS70: 0 | HT70: 0 | HU70: 0 | HV70: D | HW70: W | HY70: 0 | HZ70: 0 | IA70: 0 | IB70: N | IC70: N | ID70: N | IE70: N
A71: AJ | B71: TRI-KUTKUD | C71: PINJ TRI-KUT KUD | D71: 101 | E71: On B/S, Program, KMK | G71: 8 | H71: 240 | I71: IDR | J71: 0 | K71: 0.08 | L71: 0.36 | M71: 0.08 | N71: 0.36 | O71: N | P71: 24 | Q71: M | R71: 6 | S71: 0 | T71: Y | U71: N | V71: N | W71: 0 | X71: I | Y71: 1 | Z71: 0 | AA71: 0 | AB71: 0 | AC71: 0 | AD71: 0 | AE71: 0 | AF71: 7 | AG71: 21 | AH71: 35 | AI71: 49 | AJ71: 63 | AK71: 77 | AL71: 0 | AM71: 0 | AN71: 0 | AO71: Y | AP71: R | AQ71: 0 | AR71: 0 | AS71: 1 | AT71: 0 | AU71: Y | BC71: 0 | BD71: 0 | BE71: 0 | BF71: 0 | BG71: 0 | BH71: 0 | BI71: N | BJ71: N | BK71: N | BL71: N | BM71: N | BN71: N | BU71: 0 | BV71: 0 | BW71: 0 | BX71: 0 | BY71: 0 | BZ71: 0 | CA71: P | CB71: N | CC71: N | CD71: N | CE71: N | CF71: N | CG71: N | CH71: N | CI71: 0 | CL71: 0 | CM71: N | CN71: 0 | CO71: Y | CP71: N | CQ71: A | CR71: N | CT71: Y | CU71: 4 | CV71: N | CW71: N | CY71: N | DA71: N | DC71: 0 | DD71: P | DG71: N | DH71: N | DI71: N | DJ71: N | DK71: N | DP71: 0 | DQ71: 0 | DR71: 90 | DS71: 90 | DT71: 0 | DU71: 0 | DV71: N | DZ71: N | EC71: D | ED71: 2 | EE71: R | EF71: 100 | EG71: N | EH71: N | EI71: N | EJ71: Z | EK71: N | EL71: 1 | EM71: N | EO71: 0 | EP71: P | EQ71: Y | ES71: 0 | EV71: Y | EW71: 5 | EX71: N | EY71: N | EZ71: Y | FA71: N | FB71: Y | FC71: N | FE71: N | FF71: N | FG71: N | FH71: N | FI71: N | FJ71: N | FK71: N | FL71: N | FM71: 0 | FN71: N | FO71: N | FP71: N | FQ71: N | FR71: 0 | FS71: 0 | FT71: N | FV71: 0 | FY71: N | FZ71: N | GA71: 24 | GB71: M | GC71: N | GD71: N | GE71: N | GF71: 0 | GH71: N | GI71: N | GJ71: N | GK71: Y | GL71: P | GM71: 0 | GN71: 0 | GO71: N | GP71: Y | GQ71: N | GR71: 0 | GS71: 0 | GT71: 0 | GU71: 0 | GV71: 0 | GW71: N | GX71: Y | HB71: N | HC71: 0 | HD71: N | HE71: N | HG71: 0 | HH71: 0 | HI71: 0 | HJ71: 0 | HK71: 0 | HM71: N | HO71: 0 | HP71: 0 | HR71: 0 | HS71: 0 | HT71: 0 | HU71: 0 | HV71: D | HW71: W | HY71: 0 | HZ71: 0 | IA71: 0 | IB71: N | IC71: N | ID71: N | IE71: N
A72: AK | B72: TRI-KSU | C72: PINJ TRI-KSU | D72: 101 | E72: On B/S, Program, KMK | G72: 8 | H72: 240 | I72: IDR | J72: 0 | K72: 0.08 | L72: 0.36 | M72: 0.08 | N72: 0.36 | O72: N | P72: 24 | Q72: M | R72: 6 | S72: 0 | T72: Y | U72: N | V72: N | W72: 0 | X72: I | Y72: 1 | Z72: 0 | AA72: 0 | AB72: 0 | AC72: 0 | AD72: 0 | AE72: 0 | AF72: 7 | AG72: 21 | AH72: 35 | AI72: 49 | AJ72: 63 | AK72: 77 | AL72: 0 | AM72: 0 | AN72: 0 | AO72: Y | AP72: R | AQ72: 0 | AR72: 0 | AS72: 1 | AT72: 0 | AU72: Y | BC72: 0 | BD72: 0 | BE72: 0 | BF72: 0 | BG72: 0 | BH72: 0 | BI72: N | BJ72: N | BK72: N | BL72: N | BM72: N | BN72: N | BU72: 0 | BV72: 0 | BW72: 0 | BX72: 0 | BY72: 0 | BZ72: 0 | CA72: P | CB72: N | CC72: N | CD72: N | CE72: N | CF72: N | CG72: N | CH72: N | CI72: 0 | CL72: 0 | CM72: N | CN72: 0 | CO72: Y | CP72: N | CQ72: A | CR72: N | CT72: Y | CU72: 4 | CV72: N | CW72: N | CY72: N | DA72: N | DC72: 0 | DD72: P | DG72: N | DH72: N | DI72: N | DJ72: N | DK72: N | DP72: 0 | DQ72: 0 | DR72: 90 | DS72: 90 | DT72: 0 | DU72: 0 | DV72: N | DZ72: N | EC72: D | ED72: 2 | EE72: R | EF72: 100 | EG72: N | EH72: N | EI72: N | EJ72: Z | EK72: N | EL72: 1 | EM72: N | EO72: 0 | EP72: P | EQ72: Y | ES72: 0 | EV72: Y | EW72: 5 | EX72: N | EY72: N | EZ72: Y | FA72: N | FB72: Y | FC72: N | FE72: N | FF72: N | FG72: N | FH72: N | FI72: N | FJ72: N | FK72: N | FL72: N | FM72: 0 | FN72: N | FO72: N | FP72: N | FQ72: N | FR72: 0 | FS72: 0 | FT72: N | FV72: 0 | FY72: N | FZ72: N | GA72: 24 | GB72: M | GC72: N | GD72: N | GE72: N | GF72: 0 | GH72: N | GI72: N | GJ72: N | GK72: Y | GL72: P | GM72: 0 | GN72: 0 | GO72: N | GP72: Y | GQ72: N | GR72: 0 | GS72: 0 | GT72: 0 | GU72: 0 | GV72: 0 | GW72: N | GX72: Y | HB72: N | HC72: 0 | HD72: N | HE72: N | HG72: 0 | HH72: 0 | HI72: 0 | HJ72: 0 | HK72: 0 | HM72: N | HO72: 0 | HP72: 0 | HR72: 0 | HS72: 0 | HT72: 0 | HU72: 0 | HV72: D | HW72: W | HY72: 0 | HZ72: 0 | IA72: 0 | IB72: N | IC72: N | ID72: N | IE72: N
A73: AL | B73: TRIKLPTANI | C73: KRD TRI A/N KLP TANI | D73: 101 | E73: On B/S, Program, KMK | G73: 8 | H73: 240 | I73: IDR | J73: 0 | K73: 0.06 | L73: 0.36 | M73: 0.06 | N73: 0.36 | O73: N | P73: 24 | Q73: M | R73: 6 | S73: 0 | T73: Y | U73: Y | V73: N | W73: 0 | X73: I | Y73: 1 | Z73: 0 | AA73: 0 | AB73: 0 | AC73: 0 | AD73: 0 | AE73: 0 | AF73: 7 | AG73: 21 | AH73: 35 | AI73: 49 | AJ73: 63 | AK73: 77 | AL73: 7 | AM73: 0 | AN73: 0 | AO73: Y | AP73: R | AQ73: 0 | AR73: 0 | AS73: 1 | AT73: 0 | AU73: Y | BC73: 0 | BD73: 0 | BE73: 0 | BF73: 0 | BG73: 0 | BH73: 0 | BI73: N | BJ73: N | BK73: N | BL73: N | BM73: N | BN73: N | BU73: 0 | BV73: 0 | BW73: 0 | BX73: 0 | BY73: 0 | BZ73: 0 | CA73: P | CB73: N | CC73: N | CD73: N | CE73: N | CF73: N | CG73: N | CH73: N | CI73: 0 | CL73: 0 | CM73: N | CN73: 0 | CO73: N | CP73: N | CQ73: A | CR73: N | CT73: Y | CU73: 4 | CV73: N | CW73: N | CY73: N | DA73: N | DC73: 0 | DD73: K | DG73: N | DH73: N | DI73: N | DJ73: N | DK73: N | DP73: 0 | DQ73: 0 | DR73: 90 | DS73: 90 | DT73: 0 | DU73: 0 | DV73: N | DZ73: N | EC73: D | ED73: 2 | EE73: R | EF73: 100 | EG73: N | EH73: N | EI73: N | EJ73: Z | EK73: N | EL73: 1 | EM73: N | EO73: 0 | EP73: P | EQ73: Y | ES73: 0 | EV73: Y | EW73: 5 | EX73: N | EY73: N | EZ73: N | FA73: N | FB73: Y | FC73: N | FE73: N | FF73: N | FG73: N | FH73: N | FI73: N | FJ73: N | FK73: N | FL73: N | FM73: 0 | FN73: N | FO73: N | FP73: N | FQ73: N | FR73: 0 | FS73: 0 | FT73: N | FV73: 0 | FY73: N | FZ73: N | GA73: 24 | GB73: M | GC73: N | GD73: N | GE73: Y | GF73: 0 | GH73: N | GI73: N | GJ73: N | GK73: Y | GL73: P | GM73: 0 | GN73: 0 | GO73: Y | GP73: N | GQ73: N | GR73: 0 | GS73: 0 | GT73: 0 | GU73: 0 | GV73: 0 | GW73: N | GX73: Y | HB73: N | HC73: 0 | HD73: N | HE73: N | HG73: 0 | HH73: 0 | HI73: 0 | HJ73: 0 | HK73: 0 | HM73: N | HO73: 0 | HP73: 0 | HR73: 0 | HS73: 0 | HT73: 0 | HU73: 0 | HV73: D | HW73: W | HY73: 0 | HZ73: 0 | IA73: 0 | IB73: N | IC73: N | ID73: N | IE73: N
A74: AM | B74: SEMBAKO | C74: PINJ DISTRB SEMBAKO | D74: 101 | E74: On B/S, Program, KMK | G74: 8 | H74: 240 | I74: IDR | J74: 0 | K74: 0.06 | L74: 0.36 | M74: 0.06 | N74: 0.36 | O74: N | P74: 12 | Q74: M | R74: 6 | S74: 0 | T74: Y | U74: Y | V74: N | W74: 0 | X74: I | Y74: 1 | Z74: 0 | AA74: 0 | AB74: 0 | AC74: 0 | AD74: 0 | AE74: 0 | AF74: 7 | AG74: 21 | AH74: 35 | AI74: 49 | AJ74: 63 | AK74: 77 | AL74: 7 | AM74: 0 | AN74: 0 | AO74: Y | AP74: R | AQ74: 0 | AR74: 0 | AS74: 1 | AT74: 0 | AU74: Y | BC74: 0 | BD74: 0 | BE74: 0 | BF74: 0 | BG74: 0 | BH74: 0 | BI74: N | BJ74: N | BK74: N | BL74: N | BM74: N | BN74: N | BU74: 0 | BV74: 0 | BW74: 0 | BX74: 0 | BY74: 0 | BZ74: 0 | CA74: P | CB74: N | CC74: N | CD74: N | CE74: N | CF74: N | CG74: N | CH74: N | CI74: 0 | CL74: 0 | CM74: N | CN74: 0 | CO74: N | CP74: N | CQ74: A | CR74: N | CT74: Y | CU74: 4 | CV74: N | CW74: N | CY74: N | DA74: N | DC74: 0 | DD74: P | DG74: N | DH74: N | DI74: N | DJ74: N | DK74: N | DP74: 0 | DQ74: 0 | DR74: 90 | DS74: 90 | DT74: 0 | DU74: 0 | DV74: N | DZ74: N | EC74: D | ED74: 2 | EE74: R | EF74: 100 | EG74: N | EH74: N | EI74: N | EJ74: Z | EK74: N | EL74: 1 | EM74: N | EO74: 0 | EP74: P | EQ74: N | ES74: 0 | EV74: Y | EW74: 5 | EX74: N | EY74: N | EZ74: Y | FA74: N | FB74: Y | FC74: N | FE74: N | FF74: N | FG74: N | FH74: N | FI74: N | FJ74: N | FK74: N | FL74: N | FM74: 0 | FN74: N | FO74: N | FP74: N | FQ74: N | FR74: 0 | FS74: 0 | FT74: N | FV74: 0 | FY74: N | FZ74: N | GA74: 12 | GB74: M | GC74: N | GD74: N | GE74: Y | GF74: 0 | GH74: N | GI74: N | GJ74: N | GK74: Y | GL74: P | GM74: 0 | GN74: 0 | GO74: N | GP74: N | GQ74: N | GR74: 0 | GS74: 0 | GT74: 0 | GU74: 0 | GV74: 0 | GW74: N | GX74: Y | HB74: N | HC74: 0 | HD74: N | HE74: N | HG74: 0 | HH74: 0 | HI74: 0 | HJ74: 0 | HK74: 0 | HM74: N | HO74: 0 | HP74: 0 | HR74: 0 | HS74: 0 | HT74: 0 | HU74: 0 | HV74: D | HW74: W | HY74: 0 | HZ74: 0 | IA74: 0 | IB74: N | IC74: N | ID74: N | IE74: N
A75: AN | B75: KRD-KOP | C75: KRD KOP KUD-NON KUD | D75: 101 | E75: On B/S, Program, KMK | G75: 8 | H75: 240 | I75: IDR | J75: 0 | K75: 0.06 | L75: 0.36 | M75: 0.06 | N75: 0.36 | O75: N | P75: 1 | Q75: M | R75: 1 | S75: 0 | T75: Y | U75: Y | V75: N | W75: 0 | X75: I | Y75: 1 | Z75: 0 | AA75: 0 | AB75: 0 | AC75: 0 | AD75: 0 | AE75: 0 | AF75: 7 | AG75: 21 | AH75: 35 | AI75: 49 | AJ75: 63 | AK75: 77 | AL75: 7 | AM75: 0 | AN75: 0 | AO75: Y | AP75: R | AQ75: 0 | AR75: 0 | AS75: 1 | AT75: 0 | AU75: Y | BC75: 0 | BD75: 0 | BE75: 0 | BF75: 0 | BG75: 0 | BH75: 0 | BI75: N | BJ75: N | BK75: N | BL75: N | BM75: N | BN75: N | BU75: 0 | BV75: 0 | BW75: 0 | BX75: 0 | BY75: 0 | BZ75: 0 | CA75: P | CB75: N | CC75: N | CD75: N | CE75: N | CF75: N | CG75: N | CH75: N | CI75: 0 | CL75: 0 | CM75: N | CN75: 0 | CO75: N | CP75: N | CQ75: A | CR75: N | CT75: Y | CU75: 4 | CV75: N | CW75: N | CY75: N | DA75: N | DC75: 0 | DD75: P | DG75: N | DH75: N | DI75: N | DJ75: N | DK75: N | DP75: 0 | DQ75: 0 | DR75: 90 | DS75: 90 | DT75: 0 | DU75: 0 | DV75: N | DZ75: N | EC75: D | ED75: 2 | EE75: R | EF75: 100 | EG75: N | EH75: N | EI75: N | EJ75: Z | EK75: N | EL75: 1 | EM75: N | EO75: 0 | EP75: P | EQ75: Y | ES75: 0 | EV75: Y | EW75: 1 | EX75: N | EY75: N | EZ75: Y | FA75: N | FB75: Y | FC75: N | FE75: N | FF75: N | FG75: N | FH75: N | FI75: N | FJ75: N | FK75: N | FL75: N | FM75: 0 | FN75: N | FO75: N | FP75: N | FQ75: N | FR75: 0 | FS75: 0 | FT75: N | FV75: 0 | FY75: N | FZ75: N | GA75: 1 | GB75: M | GC75: N | GD75: N | GE75: Y | GF75: 0 | GH75: N | GI75: N | GJ75: N | GK75: Y | GL75: P | GM75: 0 | GN75: 0 | GO75: N | GP75: N | GQ75: N | GR75: 0 | GS75: 0 | GT75: 0 | GU75: 0 | GV75: 0 | GW75: N | GX75: Y | HB75: N | HC75: 0 | HD75: N | HE75: N | HG75: 0 | HH75: 0 | HI75: 0 | HJ75: 0 | HK75: 0 | HM75: N | HO75: 0 | HP75: 0 | HR75: 0 | HS75: 0 | HT75: 0 | HU75: 0 | HV75: D | HW75: W | HY75: 0 | HZ75: 0 | IA75: 0 | IB75: N | IC75: N | ID75: N | IE75: N
A76: AO | B76: KRD-KOP | C76: KRD KOP KUD-NON KUD | D76: 103 | E76: On B/S, Program, KMK | G76: 8 | H76: 310 | I76: IDR | J76: 0 | K76: 0.06 | L76: 0.36 | M76: 0.06 | N76: 0.36 | O76: N | P76: 1 | Q76: M | R76: 6 | S76: 0 | T76: Y | U76: Y | V76: N | W76: 0 | X76: I | Y76: 1 | Z76: 0 | AA76: 0 | AB76: 0 | AC76: 0 | AD76: 0 | AE76: 0 | AF76: 7 | AG76: 21 | AH76: 35 | AI76: 49 | AJ76: 63 | AK76: 77 | AL76: 7 | AM76: 0 | AN76: 0 | AO76: Y | AP76: R | AQ76: 0 | AR76: 0 | AS76: 1 | AT76: 0 | AU76: Y | BC76: 0 | BD76: 0 | BE76: 0 | BF76: 0 | BG76: 0 | BH76: 0 | BI76: N | BJ76: N | BK76: N | BL76: N | BM76: N | BN76: N | BU76: 0 | BV76: 0 | BW76: 0 | BX76: 0 | BY76: 0 | BZ76: 0 | CA76: P | CB76: N | CC76: N | CD76: N | CE76: N | CF76: N | CG76: N | CH76: N | CI76: 0 | CL76: 0 | CM76: N | CN76: 0 | CO76: N | CP76: N | CQ76: A | CR76: N | CT76: Y | CU76: 4 | CV76: N | CW76: N | CY76: N | DA76: N | DC76: 0 | DD76: P | DG76: N | DH76: N | DI76: N | DJ76: N | DK76: N | DP76: 0 | DQ76: 0 | DR76: 90 | DS76: 90 | DT76: 0 | DU76: 0 | DV76: N | DZ76: N | EC76: D | ED76: 2 | EE76: R | EF76: 100 | EG76: N | EH76: N | EI76: N | EJ76: Z | EK76: N | EL76: 1 | EM76: N | EO76: 0 | EP76: P | EQ76: Y | ES76: 0 | EV76: Y | EW76: 1 | EX76: N | EY76: N | EZ76: Y | FA76: N | FB76: Y | FC76: N | FE76: N | FF76: N | FG76: N | FH76: N | FI76: N | FJ76: N | FK76: N | FL76: N | FM76: 0 | FN76: N | FO76: N | FP76: N | FQ76: N | FR76: 0 | FS76: 0 | FT76: N | FV76: 0 | FY76: N | FZ76: N | GA76: 1 | GB76: M | GC76: N | GD76: N | GE76: Y | GF76: 0 | GH76: N | GI76: N | GJ76: N | GK76: Y | GL76: P | GM76: 0 | GN76: 0 | GO76: N | GP76: N | GQ76: N | GR76: 0 | GS76: 0 | GT76: 0 | GU76: 0 | GV76: 0 | GW76: N | GX76: Y | HB76: N | HC76: 0 | HD76: N | HE76: N | HG76: 0 | HH76: 0 | HI76: 0 | HJ76: 0 | HK76: 0 | HM76: N | HO76: 0 | HP76: 0 | HR76: 0 | HS76: 0 | HT76: 0 | HU76: 0 | HV76: D | HW76: W | HY76: 0 | HZ76: 0 | IA76: 0 | IB76: N | IC76: N | ID76: N | IE76: N
A77: AP | B77: KOPPOLAIII | C77: KRD KOP POLA III | D77: 101 | E77: On B/S, Program, KMK | G77: 8 | H77: 240 | I77: IDR | J77: 0 | K77: 0.06 | L77: 0.36 | M77: 0.06 | N77: 0.36 | O77: N | P77: 1 | Q77: M | R77: 6 | S77: 0 | T77: Y | U77: Y | V77: N | W77: 0 | X77: I | Y77: 1 | Z77: 0 | AA77: 0 | AB77: 0 | AC77: 0 | AD77: 0 | AE77: 0 | AF77: 7 | AG77: 21 | AH77: 35 | AI77: 49 | AJ77: 63 | AK77: 77 | AL77: 7 | AM77: 0 | AN77: 0 | AO77: Y | AP77: R | AQ77: 0 | AR77: 0 | AS77: 1 | AT77: 0 | AU77: Y | BC77: 0 | BD77: 0 | BE77: 0 | BF77: 0 | BG77: 0 | BH77: 0 | BI77: N | BJ77: N | BK77: N | BL77: N | BM77: N | BN77: N | BU77: 0 | BV77: 0 | BW77: 0 | BX77: 0 | BY77: 0 | BZ77: 0 | CA77: P | CB77: N | CC77: N | CD77: N | CE77: N | CF77: N | CG77: N | CH77: N | CI77: 0 | CL77: 0 | CM77: N | CN77: 0 | CO77: N | CP77: N | CQ77: A | CR77: N | CT77: Y | CU77: 4 | CV77: N | CW77: N | CY77: N | DA77: N | DC77: 0 | DD77: P | DG77: N | DH77: N | DI77: N | DJ77: N | DK77: N | DP77: 0 | DQ77: 0 | DR77: 90 | DS77: 90 | DT77: 0 | DU77: 0 | DV77: N | DZ77: N | EC77: D | ED77: 2 | EE77: R | EF77: 100 | EG77: N | EH77: N | EI77: N | EJ77: Z | EK77: N | EL77: 1 | EM77: N | EO77: 0 | EP77: P | EQ77: N | ES77: 0 | EV77: Y | EW77: 1 | EX77: N | EY77: N | EZ77: Y | FA77: N | FB77: Y | FC77: N | FE77: N | FF77: N | FG77: N | FH77: N | FI77: N | FJ77: N | FK77: N | FL77: N | FM77: 0 | FN77: N | FO77: N | FP77: N | FQ77: N | FR77: 0 | FS77: 0 | FT77: N | FV77: 0 | FY77: N | FZ77: N | GA77: 1 | GB77: M | GC77: N | GD77: N | GE77: Y | GF77: 0 | GH77: N | GI77: N | GJ77: N | GK77: Y | GL77: P | GM77: 0 | GN77: 0 | GO77: N | GP77: N | GQ77: N | GR77: 0 | GS77: 0 | GT77: 0 | GU77: 0 | GV77: 0 | GW77: N | GX77: Y | HB77: N | HC77: 0 | HD77: N | HE77: N | HG77: 0 | HH77: 0 | HI77: 0 | HJ77: 0 | HK77: 0 | HM77: N | HO77: 0 | HP77: 0 | HR77: 0 | HS77: 0 | HT77: 0 | HU77: 0 | HV77: D | HW77: W | HY77: 0 | HZ77: 0 | IA77: 0 | IB77: N | IC77: N | ID77: N | IE77: N
A78: AS | B78: KEPRES 29/ | C78: KMK KEPRES 29/84 | D78: 103 | E78: On B/S, Program, KMK | G78: 8 | H78: 310 | I78: IDR | J78: 31 | K78: 0.08 | L78: 0.36 | M78: 0.08 | N78: 0.36 | O78: N | P78: 1 | Q78: M | R78: 6 | S78: 0 | T78: Y | U78: Y | V78: N | W78: 0 | X78: I | Y78: 1 | Z78: 0 | AA78: 0 | AB78: 0 | AC78: 0 | AD78: 0 | AE78: 0 | AF78: 7 | AG78: 21 | AH78: 35 | AI78: 49 | AJ78: 63 | AK78: 77 | AL78: 0 | AM78: 0 | AN78: 0 | AO78: Y | AP78: R | AQ78: 0 | AR78: 0 | AS78: 1 | AT78: 0 | AU78: Y | BC78: 0 | BD78: 0 | BE78: 0 | BF78: 0 | BG78: 0 | BH78: 0 | BI78: N | BJ78: N | BK78: N | BL78: N | BM78: N | BN78: N | BU78: 0 | BV78: 0 | BW78: 0 | BX78: 0 | BY78: 0 | BZ78: 0 | CA78: P | CB78: N | CC78: N | CD78: N | CE78: N | CF78: N | CG78: N | CH78: N | CI78: 0 | CJ78: N | CL78: 0 | CM78: N | CN78: 0 | CO78: N | CP78: N | CQ78: A | CR78: N | CT78: N | CU78: 4 | CV78: N | CW78: N | CY78: N | DA78: Y | DC78: 0 | DD78: P | DG78: N | DH78: N | DI78: N | DJ78: N | DK78: N | DP78: 0 | DQ78: 0 | DR78: 90 | DS78: 90 | DT78: 0 | DU78: 0 | DV78: N | DW78: P | DY78: 17 | DZ78: N | EC78: D | ED78: 2 | EE78: R | EF78: 100 | EG78: N | EH78: N | EI78: N | EJ78: Z | EK78: N | EL78: 1 | EM78: N | EO78: 99 | EP78: X | EQ78: Y | ER78: N | ES78: 0 | EV78: Y | EW78: 6 | EX78: N | EY78: N | EZ78: Y | FA78: N | FB78: Y | FC78: N | FD78: B | FE78: N | FF78: N | FG78: N | FH78: N | FI78: N | FJ78: N | FK78: N | FL78: N | FM78: 0 | FN78: N | FO78: N | FP78: N | FQ78: N | FR78: 0 | FS78: 0 | FT78: N | FV78: 0 | FY78: N | FZ78: N | GA78: 1 | GB78: M | GC78: N | GD78: N | GE78: N | GF78: 0 | GG78: O | GH78: N | GI78: Y | GJ78: N | GK78: Y | GL78: P | GM78: 0 | GN78: 0 | GO78: N | GP78: Y | GQ78: N | GR78: 2 | GS78: 0 | GT78: 0 | GU78: 0 | GV78: 0 | GW78: N | GX78: Y | HB78: N | HC78: 0 | HD78: N | HE78: N | HG78: 0 | HH78: 0 | HI78: 0 | HJ78: 0 | HK78: 0 | HM78: N | HO78: 0 | HP78: 0 | HR78: 0 | HS78: 0 | HT78: 0 | HU78: 0 | HV78: D | HW78: W | HY78: 0 | HZ78: 0 | IA78: 0 | IB78: N | IC78: N | ID78: N | IE78: N
A79: AR | B79: KMK KTRNAS | C79: KMK KONTRAKTOR NAS | D79: 102 | E79: On B/S,Program,KMK-I | G79: 8 | H79: 230 | I79: IDR | J79: 31 | K79: 0 | L79: 0.3 | M79: 0 | N79: 0.3 | O79: N | P79: 1 | Q79: M | R79: 6 | S79: 10 | T79: Y | U79: Y | V79: N | W79: 0 | X79: I | Y79: 1 | Z79: 0 | AA79: 0 | AB79: 0 | AC79: 0 | AD79: 0 | AE79: 0 | AF79: 7 | AG79: 21 | AH79: 35 | AI79: 0 | AJ79: 0 | AK79: 0 | AL79: 0 | AM79: 0 | AN79: 0 | AO79: Y | AP79: R | AQ79: 0 | AR79: 0 | AS79: 0 | AT79: 0 | AU79: Y | BC79: 0 | BD79: 0 | BE79: 0 | BF79: 0 | BG79: 0 | BH79: 0 | BI79: N | BJ79: N | BK79: N | BL79: N | BM79: N | BN79: N | BU79: 0 | BV79: 0 | BW79: 0 | BX79: 0 | BY79: 0 | BZ79: 0 | CA79: P | CB79: N | CC79: N | CD79: N | CE79: N | CF79: N | CG79: N | CH79: N | CI79: 0 | CJ79: N | CL79: 0 | CM79: N | CN79: 0 | CO79: Y | CP79: N | CQ79: A | CR79: N | CT79: N | CU79: 4 | CV79: N | CW79: N | CY79: N | DA79: Y | DC79: 0 | DD79: P | DG79: N | DH79: N | DI79: N | DJ79: N | DK79: N | DP79: 0 | DQ79: 0 | DR79: 90 | DS79: 90 | DT79: 0 | DU79: 0 | DV79: N | DW79: P | DX79: P | DY79: 17 | DZ79: N | EC79: D | ED79: 2 | EE79: R | EF79: 100 | EG79: N | EH79: N | EI79: N | EJ79: N | EK79: N | EL79: 1 | EM79: N | EO79: 99 | EP79: X | EQ79: Y | ER79: N | ES79: 0 | EV79: Y | EW79: 6 | EX79: N | EY79: N | EZ79: Y | FA79: N | FB79: Y | FC79: N | FD79: B | FE79: N | FF79: N | FG79: N | FH79: N | FI79: N | FJ79: N | FK79: N | FL79: N | FM79: 0 | FN79: N | FO79: N | FP79: N | FQ79: N | FR79: 0 | FS79: 0 | FT79: N | FV79: 0 | FY79: N | FZ79: N | GA79: 1 | GB79: M | GC79: N | GD79: N | GE79: N | GF79: 0 | GG79: O | GH79: N | GI79: Y | GJ79: N | GK79: Y | GL79: P | GM79: 0 | GN79: 0 | GO79: N | GP79: Y | GQ79: N | GR79: 2 | GS79: 0 | GT79: 0 | GU79: 0 | GV79: 0 | GW79: N | GX79: Y | HB79: N | HC79: 0 | HD79: N | HE79: N | HG79: 0 | HH79: 0 | HI79: 0 | HJ79: 0 | HK79: 0 | HM79: N | HO79: 0 | HP79: 0 | HR79: 0 | HS79: 0 | HT79: 0 | HU79: 0 | HV79: D | HW79: W | HY79: 0 | HZ79: 0 | IA79: 0 | IB79: N | IC79: N | ID79: N | IE79: N
A80: AT | B80: KMK EBJ | C80: KMK EBJ III DAN IV | D80: 103 | E80: On B/S, Program, KMK | G80: 8 | H80: 310 | I80: IDR | J80: 31 | K80: 0.08 | L80: 0.36 | M80: 0.08 | N80: 0.36 | O80: N | P80: 1 | Q80: M | R80: 6 | S80: 0 | T80: Y | U80: Y | V80: N | W80: 0 | X80: I | Y80: 1 | Z80: 0 | AA80: 0 | AB80: 0 | AC80: 0 | AD80: 0 | AE80: 0 | AF80: 7 | AG80: 21 | AH80: 35 | AI80: 49 | AJ80: 63 | AK80: 77 | AL80: 0 | AM80: 0 | AN80: 0 | AO80: Y | AP80: R | AQ80: 0 | AR80: 0 | AS80: 1 | AT80: 0 | AU80: Y | BC80: 0 | BD80: 0 | BE80: 0 | BF80: 0 | BG80: 0 | BH80: 0 | BI80: N | BJ80: N | BK80: N | BL80: N | BM80: N | BN80: N | BU80: 0 | BV80: 0 | BW80: 0 | BX80: 0 | BY80: 0 | BZ80: 0 | CA80: P | CB80: N | CC80: N | CD80: N | CE80: N | CF80: N | CG80: N | CH80: N | CI80: 0 | CJ80: N | CL80: 0 | CM80: N | CN80: 0 | CO80: N | CP80: N | CQ80: A | CR80: N | CT80: N | CU80: 4 | CV80: N | CW80: N | CY80: N | DA80: Y | DC80: 0 | DD80: P | DG80: N | DH80: N | DI80: N | DJ80: N | DK80: N | DP80: 0 | DQ80: 0 | DR80: 90 | DS80: 90 | DT80: 0 | DU80: 0 | DV80: N | DW80: P | DY80: 17 | DZ80: N | EC80: D | ED80: 2 | EE80: R | EF80: 100 | EG80: N | EH80: N | EI80: N | EJ80: Z | EK80: N | EL80: 1 | EM80: N | EO80: 99 | EP80: X | EQ80: Y | ER80: N | ES80: 0 | EV80: Y | EW80: 6 | EX80: N | EY80: N | EZ80: Y | FA80: N | FB80: Y | FC80: N | FD80: B | FE80: N | FF80: N | FG80: N | FH80: N | FI80: N | FJ80: N | FK80: N | FL80: N | FM80: 0 | FN80: N | FO80: N | FP80: N | FQ80: N | FR80: 0 | FS80: 0 | FT80: N | FV80: 0 | FY80: N | FZ80: N | GA80: 1 | GB80: M | GC80: N | GD80: N | GE80: N | GF80: 0 | GG80: O | GH80: N | GI80: Y | GJ80: N | GK80: Y | GL80: P | GM80: 0 | GN80: 0 | GO80: N | GP80: Y | GQ80: N | GR80: 2 | GS80: 0 | GT80: 0 | GU80: 0 | GV80: 0 | GW80: N | GX80: Y | HB80: N | HC80: 0 | HD80: N | HE80: N | HG80: 0 | HH80: 0 | HI80: 0 | HJ80: 0 | HK80: 0 | HM80: N | HO80: 0 | HP80: 0 | HR80: 0 | HS80: 0 | HT80: 0 | HU80: 0 | HV80: D | HW80: W | HY80: 0 | HZ80: 0 | IA80: 0 | IB80: N | IC80: N | ID80: N | IE80: N
A81: AU | B81: KMK FSDP | C81: KMK FSDP | D81: 103 | E81: On B/S, Program, KMK | G81: 8 | H81: 310 | I81: IDR | J81: 31 | K81: 0.08 | L81: 0.36 | M81: 0.08 | N81: 0.36 | O81: N | P81: 1 | Q81: M | R81: 6 | S81: 0 | T81: Y | U81: Y | V81: N | W81: 0 | X81: I | Y81: 1 | Z81: 0 | AA81: 0 | AB81: 0 | AC81: 0 | AD81: 0 | AE81: 0 | AF81: 7 | AG81: 21 | AH81: 35 | AI81: 49 | AJ81: 63 | AK81: 77 | AL81: 0 | AM81: 0 | AN81: 0 | AO81: Y | AP81: R | AQ81: 0 | AR81: 0 | AS81: 1 | AT81: 0 | AU81: Y | BC81: 0 | BD81: 0 | BE81: 0 | BF81: 0 | BG81: 0 | BH81: 0 | BI81: N | BJ81: N | BK81: N | BL81: N | BM81: N | BN81: N | BU81: 0 | BV81: 0 | BW81: 0 | BX81: 0 | BY81: 0 | BZ81: 0 | CA81: P | CB81: N | CC81: N | CD81: N | CE81: N | CF81: N | CG81: N | CH81: N | CI81: 0 | CJ81: N | CL81: 0 | CM81: N | CN81: 0 | CO81: N | CP81: N | CQ81: A | CR81: N | CT81: N | CU81: 4 | CV81: N | CW81: N | CY81: N | DA81: Y | DC81: 0 | DD81: P | DG81: N | DH81: N | DI81: N | DJ81: N | DK81: N | DP81: 0 | DQ81: 0 | DR81: 90 | DS81: 90 | DT81: 0 | DU81: 0 | DV81: N | DW81: P | DY81: 17 | DZ81: N | EC81: D | ED81: 2 | EE81: R | EF81: 100 | EG81: N | EH81: N | EI81: N | EJ81: Z | EK81: N | EL81: 1 | EM81: N | EO81: 99 | EP81: X | EQ81: Y | ER81: N | ES81: 0 | EV81: Y | EW81: 6 | EX81: N | EY81: N | EZ81: Y | FA81: N | FB81: Y | FC81: N | FD81: B | FE81: N | FF81: N | FG81: N | FH81: N | FI81: N | FJ81: N | FK81: N | FL81: N | FM81: 0 | FN81: N | FO81: N | FP81: N | FQ81: N | FR81: 0 | FS81: 0 | FT81: N | FV81: 0 | FY81: N | FZ81: N | GA81: 1 | GB81: M | GC81: N | GD81: N | GE81: N | GF81: 0 | GG81: O | GH81: N | GI81: Y | GJ81: N | GK81: Y | GL81: P | GM81: 0 | GN81: 0 | GO81: N | GP81: Y | GQ81: N | GR81: 2 | GS81: 0 | GT81: 0 | GU81: 0 | GV81: 0 | GW81: N | GX81: Y | HB81: N | HC81: 0 | HD81: N | HE81: N | HG81: 0 | HH81: 0 | HI81: 0 | HJ81: 0 | HK81: 0 | HM81: N | HO81: 0 | HP81: 0 | HR81: 0 | HS81: 0 | HT81: 0 | HU81: 0 | HV81: D | HW81: W | HY81: 0 | HZ81: 0 | IA81: 0 | IB81: N | IC81: N | ID81: N | IE81: N
A82: AV | B82: KAKOP AGRI | C82: KMK KAKOP AGRIBISNIS | D82: 101 | E82: On B/S, Program, KMK | G82: 8 | H82: 240 | I82: IDR | J82: 31 | K82: 0.08 | L82: 0.36 | M82: 0.08 | N82: 0.36 | O82: N | P82: 12 | Q82: M | R82: 6 | S82: 0 | T82: Y | U82: Y | V82: N | W82: 0 | X82: I | Y82: 1 | Z82: 0 | AA82: 0 | AB82: 0 | AC82: 0 | AD82: 0 | AE82: 0 | AF82: 7 | AG82: 21 | AH82: 35 | AI82: 49 | AJ82: 63 | AK82: 77 | AL82: 0 | AM82: 0 | AN82: 0 | AO82: Y | AP82: R | AQ82: 0 | AR82: 0 | AS82: 1 | AT82: 0 | AU82: Y | BC82: 0 | BD82: 0 | BE82: 0 | BF82: 0 | BG82: 0 | BH82: 0 | BI82: N | BJ82: N | BK82: N | BL82: N | BM82: N | BN82: N | BU82: 0 | BV82: 0 | BW82: 0 | BX82: 0 | BY82: 0 | BZ82: 0 | CA82: P | CB82: N | CC82: N | CD82: N | CE82: N | CF82: N | CG82: N | CH82: N | CI82: 0 | CJ82: N | CL82: 0 | CM82: N | CN82: 0 | CO82: N | CP82: N | CQ82: A | CR82: N | CT82: N | CU82: 4 | CV82: N | CW82: N | CY82: N | DA82: Y | DC82: 0 | DD82: P | DG82: N | DH82: N | DI82: N | DJ82: N | DK82: N | DP82: 0 | DQ82: 0 | DR82: 90 | DS82: 90 | DT82: 0 | DU82: 0 | DV82: N | DW82: P | DY82: 17 | DZ82: N | EC82: D | ED82: 2 | EE82: R | EF82: 100 | EG82: N | EH82: N | EI82: N | EJ82: Z | EK82: N | EL82: 1 | EM82: N | EO82: 99 | EP82: X | EQ82: N | ER82: N | ES82: 0 | EV82: Y | EW82: 6 | EX82: N | EY82: N | EZ82: Y | FA82: N | FB82: Y | FC82: N | FD82: B | FE82: N | FF82: N | FG82: N | FH82: N | FI82: N | FJ82: N | FK82: N | FL82: N | FM82: 0 | FN82: N | FO82: N | FP82: N | FQ82: N | FR82: 0 | FS82: 0 | FT82: N | FV82: 0 | FY82: N | FZ82: N | GA82: 1 | GB82: M | GC82: N | GD82: N | GE82: N | GF82: 0 | GG82: O | GH82: N | GI82: Y | GJ82: N | GK82: Y | GL82: P | GM82: 0 | GN82: 0 | GO82: N | GP82: Y | GQ82: N | GR82: 2 | GS82: 0 | GT82: 0 | GU82: 0 | GV82: 0 | GW82: N | GX82: Y | HB82: N | HC82: 0 | HD82: N | HE82: N | HG82: 0 | HH82: 0 | HI82: 0 | HJ82: 0 | HK82: 0 | HM82: N | HO82: 0 | HP82: 0 | HR82: 0 | HS82: 0 | HT82: 0 | HU82: 0 | HV82: D | HW82: W | HY82: 0 | HZ82: 0 | IA82: 0 | IB82: N | IC82: N | ID82: N | IE82: N
A83: AW | B83: PANGAN0001 | C83: KAKOP PANGAN OO/01 | D83: 101 | E83: On B/S, Program, KMK | G83: 8 | H83: 240 | I83: IDR | J83: 31 | K83: 0.08 | L83: 0.36 | M83: 0.08 | N83: 0.36 | O83: N | P83: 12 | Q83: M | R83: 6 | S83: 0 | T83: Y | U83: Y | V83: N | W83: 0 | X83: I | Y83: 1 | Z83: 0 | AA83: 0 | AB83: 0 | AC83: 0 | AD83: 0 | AE83: 0 | AF83: 7 | AG83: 21 | AH83: 35 | AI83: 49 | AJ83: 63 | AK83: 77 | AL83: 0 | AM83: 0 | AN83: 0 | AO83: Y | AP83: R | AQ83: 0 | AR83: 0 | AS83: 1 | AT83: 0 | AU83: Y | BC83: 0 | BD83: 0 | BE83: 0 | BF83: 0 | BG83: 0 | BH83: 0 | BI83: N | BJ83: N | BK83: N | BL83: N | BM83: N | BN83: N | BU83: 0 | BV83: 0 | BW83: 0 | BX83: 0 | BY83: 0 | BZ83: 0 | CA83: P | CB83: N | CC83: N | CD83: N | CE83: N | CF83: N | CG83: N | CH83: N | CI83: 0 | CJ83: N | CL83: 0 | CM83: N | CN83: 0 | CO83: N | CP83: N | CQ83: A | CR83: N | CT83: N | CU83: 4 | CV83: N | CW83: N | CY83: N | DA83: Y | DC83: 0 | DD83: P | DG83: N | DH83: N | DI83: N | DJ83: N | DK83: N | DP83: 0 | DQ83: 0 | DR83: 90 | DS83: 90 | DT83: 0 | DU83: 0 | DV83: N | DW83: P | DY83: 17 | DZ83: N | EC83: D | ED83: 2 | EE83: R | EF83: 100 | EG83: N | EH83: N | EI83: N | EJ83: Z | EK83: N | EL83: 1 | EM83: N | EO83: 99 | EP83: X | EQ83: Y | ER83: N | ES83: 0 | EV83: Y | EW83: 6 | EX83: N | EY83: N | EZ83: Y | FA83: N | FB83: Y | FC83: N | FD83: B | FE83: N | FF83: N | FG83: N | FH83: N | FI83: N | FJ83: N | FK83: N | FL83: N | FM83: 0 | FN83: N | FO83: N | FP83: N | FQ83: N | FR83: 0 | FS83: 0 | FT83: N | FV83: 0 | FY83: N | FZ83: N | GA83: 1 | GB83: M | GC83: N | GD83: N | GE83: N | GF83: 0 | GG83: O | GH83: N | GI83: Y | GJ83: N | GK83: Y | GL83: P | GM83: 0 | GN83: 0 | GO83: N | GP83: Y | GQ83: N | GR83: 2 | GS83: 0 | GT83: 0 | GU83: 0 | GV83: 0 | GW83: N | GX83: Y | HB83: N | HC83: 0 | HD83: N | HE83: N | HG83: 0 | HH83: 0 | HI83: 0 | HJ83: 0 | HK83: 0 | HM83: N | HO83: 0 | HP83: 0 | HR83: 0 | HS83: 0 | HT83: 0 | HU83: 0 | HV83: D | HW83: W | HY83: 0 | HZ83: 0 | IA83: 0 | IB83: N | IC83: N | ID83: N | IE83: N
A84: AX | B84: KRD EDP II | C84: KREDIT EDP II | D84: 103 | E84: On B/S, Program, KMK | G84: 8 | H84: 310 | I84: IDR | J84: 31 | K84: 0.08 | L84: 0.36 | M84: 0.08 | N84: 0.36 | O84: N | P84: 12 | Q84: M | R84: 6 | S84: 0 | T84: Y | U84: Y | V84: N | W84: 0 | X84: I | Y84: 1 | Z84: 0 | AA84: 0 | AB84: 0 | AC84: 0 | AD84: 0 | AE84: 0 | AF84: 7 | AG84: 21 | AH84: 35 | AI84: 49 | AJ84: 63 | AK84: 77 | AL84: 0 | AM84: 0 | AN84: 0 | AO84: Y | AP84: R | AQ84: 0 | AR84: 0 | AS84: 1 | AT84: 0 | AU84: Y | BC84: 0 | BD84: 0 | BE84: 0 | BF84: 0 | BG84: 0 | BH84: 0 | BI84: N | BJ84: N | BK84: N | BL84: N | BM84: N | BN84: N | BU84: 0 | BV84: 0 | BW84: 0 | BX84: 0 | BY84: 0 | BZ84: 0 | CA84: P | CB84: N | CC84: N | CD84: N | CE84: N | CF84: N | CG84: N | CH84: N | CI84: 0 | CJ84: N | CL84: 0 | CM84: N | CN84: 0 | CO84: N | CP84: N | CQ84: A | CR84: N | CT84: N | CU84: 4 | CV84: N | CW84: N | CY84: N | DA84: Y | DC84: 0 | DD84: P | DG84: N | DH84: N | DI84: N | DJ84: N | DK84: N | DP84: 0 | DQ84: 0 | DR84: 90 | DS84: 90 | DT84: 0 | DU84: 0 | DV84: N | DW84: P | DY84: 17 | DZ84: N | EC84: D | ED84: 2 | EE84: R | EF84: 100 | EG84: N | EH84: N | EI84: N | EJ84: Z | EK84: N | EL84: 1 | EM84: N | EO84: 99 | EP84: X | EQ84: Y | ER84: N | ES84: 0 | EV84: Y | EW84: 6 | EX84: N | EY84: N | EZ84: Y | FA84: N | FB84: Y | FC84: N | FD84: B | FE84: N | FF84: N | FG84: N | FH84: N | FI84: N | FJ84: N | FK84: N | FL84: N | FM84: 0 | FN84: N | FO84: N | FP84: N | FQ84: N | FR84: 0 | FS84: 0 | FT84: N | FV84: 0 | FY84: N | FZ84: N | GA84: 1 | GB84: M | GC84: N | GD84: N | GE84: N | GF84: 0 | GG84: O | GH84: N | GI84: Y | GJ84: N | GK84: Y | GL84: P | GM84: 0 | GN84: 0 | GO84: N | GP84: Y | GQ84: N | GR84: 2 | GS84: 0 | GT84: 0 | GU84: 0 | GV84: 0 | GW84: N | GX84: Y | HB84: N | HC84: 0 | HD84: N | HE84: N | HG84: 0 | HH84: 0 | HI84: 0 | HJ84: 0 | HK84: 0 | HM84: N | HO84: 0 | HP84: 0 | HR84: 0 | HS84: 0 | HT84: 0 | HU84: 0 | HV84: D | HW84: W | HY84: 0 | HZ84: 0 | IA84: 0 | IB84: N | IC84: N | ID84: N | IE84: N
A85: AY | B85: KRD IRP | C85: KREDIT IRP | D85: 103 | E85: On B/S, Program, KMK | G85: 8 | H85: 310 | I85: IDR | J85: 31 | K85: 0.08 | L85: 0.36 | M85: 0.08 | N85: 0.36 | O85: N | P85: 12 | Q85: M | R85: 6 | S85: 0 | T85: Y | U85: Y | V85: N | W85: 0 | X85: I | Y85: 1 | Z85: 0 | AA85: 0 | AB85: 0 | AC85: 0 | AD85: 0 | AE85: 0 | AF85: 7 | AG85: 21 | AH85: 35 | AI85: 49 | AJ85: 63 | AK85: 77 | AL85: 0 | AM85: 0 | AN85: 0 | AO85: Y | AP85: R | AQ85: 0 | AR85: 0 | AS85: 1 | AT85: 0 | AU85: Y | BC85: 0 | BD85: 0 | BE85: 0 | BF85: 0 | BG85: 0 | BH85: 0 | BI85: N | BJ85: N | BK85: N | BL85: N | BM85: N | BN85: N | BU85: 0 | BV85: 0 | BW85: 0 | BX85: 0 | BY85: 0 | BZ85: 0 | CA85: P | CB85: N | CC85: N | CD85: N | CE85: N | CF85: N | CG85: N | CH85: N | CI85: 0 | CJ85: N | CL85: 0 | CM85: N | CN85: 0 | CO85: N | CP85: N | CQ85: A | CR85: N | CT85: N | CU85: 4 | CV85: N | CW85: N | CY85: N | DA85: Y | DC85: 0 | DD85: P | DG85: N | DH85: N | DI85: N | DJ85: N | DK85: N | DP85: 0 | DQ85: 0 | DR85: 90 | DS85: 90 | DT85: 0 | DU85: 0 | DV85: N | DW85: P | DY85: 17 | DZ85: N | EC85: D | ED85: 2 | EE85: R | EF85: 100 | EG85: N | EH85: N | EI85: N | EJ85: Z | EK85: N | EL85: 1 | EM85: N | EO85: 99 | EP85: X | EQ85: Y | ER85: N | ES85: 0 | EV85: Y | EW85: 6 | EX85: N | EY85: N | EZ85: Y | FA85: N | FB85: Y | FC85: N | FD85: B | FE85: N | FF85: N | FG85: N | FH85: N | FI85: N | FJ85: N | FK85: N | FL85: N | FM85: 0 | FN85: N | FO85: N | FP85: N | FQ85: N | FR85: 0 | FS85: 0 | FT85: N | FV85: 0 | FY85: N | FZ85: N | GA85: 1 | GB85: M | GC85: N | GD85: N | GE85: N | GF85: 0 | GG85: O | GH85: N | GI85: Y | GJ85: N | GK85: Y | GL85: P | GM85: 0 | GN85: 0 | GO85: N | GP85: Y | GQ85: N | GR85: 2 | GS85: 0 | GT85: 0 | GU85: 0 | GV85: 0 | GW85: N | GX85: Y | HB85: N | HC85: 0 | HD85: N | HE85: N | HG85: 0 | HH85: 0 | HI85: 0 | HJ85: 0 | HK85: 0 | HM85: N | HO85: 0 | HP85: 0 | HR85: 0 | HS85: 0 | HT85: 0 | HU85: 0 | HV85: D | HW85: W | HY85: 0 | HZ85: 0 | IA85: 0 | IB85: N | IC85: N | ID85: N | IE85: N
A86: AZ | B86: KEB-SMIEP | C86: KREDIT KEB-SMIEP | D86: 103 | E86: On B/S, Program, KMK | G86: 8 | H86: 310 | I86: IDR | J86: 31 | K86: 0.08 | L86: 0.36 | M86: 0.08 | N86: 0.36 | O86: N | P86: 12 | Q86: M | R86: 6 | S86: 0 | T86: Y | U86: Y | V86: N | W86: 0 | X86: I | Y86: 1 | Z86: 0 | AA86: 0 | AB86: 0 | AC86: 0 | AD86: 0 | AE86: 0 | AF86: 7 | AG86: 21 | AH86: 35 | AI86: 49 | AJ86: 63 | AK86: 77 | AL86: 0 | AM86: 0 | AN86: 0 | AO86: Y | AP86: R | AQ86: 0 | AR86: 0 | AS86: 1 | AT86: 0 | AU86: Y | BC86: 0 | BD86: 0 | BE86: 0 | BF86: 0 | BG86: 0 | BH86: 0 | BI86: N | BJ86: N | BK86: N | BL86: N | BM86: N | BN86: N | BU86: 0 | BV86: 0 | BW86: 0 | BX86: 0 | BY86: 0 | BZ86: 0 | CA86: P | CB86: N | CC86: N | CD86: N | CE86: N | CF86: N | CG86: N | CH86: N | CI86: 0 | CJ86: N | CL86: 0 | CM86: N | CN86: 0 | CO86: N | CP86: N | CQ86: A | CR86: N | CT86: N | CU86: 4 | CV86: N | CW86: N | CY86: N | DA86: Y | DC86: 0 | DD86: P | DG86: N | DH86: N | DI86: N | DJ86: N | DK86: N | DP86: 0 | DQ86: 0 | DR86: 90 | DS86: 90 | DT86: 0 | DU86: 0 | DV86: N | DW86: P | DY86: 17 | DZ86: N | EC86: D | ED86: 2 | EE86: R | EF86: 100 | EG86: N | EH86: N | EI86: N | EJ86: Z | EK86: N | EL86: 1 | EM86: N | EO86: 99 | EP86: X | EQ86: Y | ER86: N | ES86: 0 | EV86: Y | EW86: 6 | EX86: N | EY86: N | EZ86: Y | FA86: N | FB86: Y | FC86: N | FD86: B | FE86: N | FF86: N | FG86: N | FH86: N | FI86: N | FJ86: N | FK86: N | FL86: N | FM86: 0 | FN86: N | FO86: N | FP86: N | FQ86: N | FR86: 0 | FS86: 0 | FT86: N | FV86: 0 | FY86: N | FZ86: N | GA86: 1 | GB86: M | GC86: N | GD86: N | GE86: N | GF86: 0 | GG86: O | GH86: N | GI86: Y | GJ86: N | GK86: Y | GL86: P | GM86: 0 | GN86: 0 | GO86: N | GP86: Y | GQ86: N | GR86: 2 | GS86: 0 | GT86: 0 | GU86: 0 | GV86: 0 | GW86: N | GX86: Y | HB86: N | HC86: 0 | HD86: N | HE86: N | HG86: 0 | HH86: 0 | HI86: 0 | HJ86: 0 | HK86: 0 | HM86: N | HO86: 0 | HP86: 0 | HR86: 0 | HS86: 0 | HT86: 0 | HU86: 0 | HV86: D | HW86: W | HY86: 0 | HZ86: 0 | IA86: 0 | IB86: N | IC86: N | ID86: N | IE86: N
A87: BA | B87: NONANN BDN | C87: PESKT NON ANN BIDAN | D87: 104 | E87: On B/S, Program, KI, | G87: 8 | H87: 240 | I87: IDR | J87: 31 | K87: 0.06 | L87: 0.36 | M87: 0.06 | N87: 0.36 | O87: N | P87: 1 | Q87: M | R87: 0 | S87: 0 | T87: Y | U87: Y | V87: N | W87: 0 | X87: I | Y87: 1 | Z87: 0 | AA87: 0 | AB87: 0 | AC87: 0 | AD87: 0 | AE87: 0 | AF87: 7 | AG87: 21 | AH87: 35 | AI87: 49 | AJ87: 63 | AK87: 77 | AL87: 0 | AM87: 0 | AN87: 0 | AO87: Y | AP87: R | AQ87: 0 | AR87: 0 | AS87: 14 | AT87: 0 | AU87: Y | BC87: 0 | BD87: 0 | BE87: 0 | BF87: 0 | BG87: 0 | BH87: 0 | BI87: N | BJ87: N | BK87: N | BL87: N | BM87: N | BN87: N | BU87: 0 | BV87: 0 | BW87: 0 | BX87: 0 | BY87: 0 | BZ87: 0 | CA87: P | CB87: N | CC87: N | CD87: N | CE87: N | CF87: N | CG87: N | CH87: N | CI87: 0 | CJ87: N | CL87: 0 | CM87: N | CN87: 0 | CO87: N | CP87: N | CQ87: A | CR87: N | CT87: Y | CU87: 4 | CV87: N | CW87: N | CY87: N | DA87: Y | DC87: 0 | DD87: O | DG87: N | DH87: N | DI87: N | DJ87: N | DK87: N | DP87: 0 | DQ87: 0 | DR87: 90 | DS87: 90 | DT87: 0 | DU87: 0 | DV87: N | DW87: P | DX87: P | DY87: 17 | DZ87: N | EC87: F | ED87: 5 | EE87: R | EF87: 100 | EG87: N | EH87: N | EI87: N | EJ87: Z | EK87: N | EL87: 2 | EM87: N | EO87: 0 | EP87: P | EQ87: N | ER87: N | ES87: 0 | EV87: Y | EW87: 0 | EX87: N | EY87: N | EZ87: N | FA87: N | FB87: Y | FC87: N | FD87: B | FE87: N | FF87: N | FG87: N | FH87: N | FI87: N | FJ87: N | FK87: N | FL87: N | FM87: 0 | FN87: N | FO87: N | FP87: N | FQ87: N | FR87: 0 | FS87: 0 | FT87: N | FV87: 0 | FY87: N | FZ87: N | GA87: 1 | GB87: M | GC87: N | GD87: N | GE87: N | GF87: 0 | GG87: O | GH87: N | GI87: N | GJ87: N | GK87: Y | GL87: P | GM87: 0 | GN87: 0 | GO87: Y | GP87: Y | GQ87: Y | GR87: 2 | GS87: 2 | GT87: 0 | GU87: 0 | GV87: 0 | GW87: N | GX87: Y | HB87: N | HC87: 0 | HD87: N | HE87: N | HG87: 0 | HH87: 0 | HI87: 0 | HJ87: 0 | HK87: 0 | HM87: N | HO87: 0 | HP87: 0 | HR87: 0 | HS87: 0 | HT87: 0 | HU87: 0 | HV87: D | HW87: W | HY87: 0 | HZ87: 0 | IA87: 0 | IB87: Y | IC87: N | ID87: N | IE87: N
A88: BB | B88: KREDIT RCP | C88: KREDIT PERSEKOT RCP | D88: 104 | E88: On B/S,Program,KI-ID | G88: 8 | H88: 240 | I88: IDR | J88: 31 | K88: 0.06 | L88: 0.36 | M88: 0.06 | N88: 0.36 | O88: N | P88: 1 | Q88: M | R88: 6 | S88: 0 | T88: Y | U88: Y | V88: N | W88: 0 | X88: I | Y88: 1 | Z88: 0 | AA88: 0 | AB88: 0 | AC88: 0 | AD88: 0 | AE88: 0 | AF88: 7 | AG88: 21 | AH88: 35 | AI88: 49 | AJ88: 63 | AK88: 77 | AL88: 0 | AM88: 0 | AN88: 0 | AO88: Y | AP88: R | AQ88: 0 | AR88: 0 | AS88: 1 | AT88: 0 | AU88: Y | BC88: 0 | BD88: 0 | BE88: 0 | BF88: 0 | BG88: 0 | BH88: 0 | BI88: N | BJ88: N | BK88: N | BL88: N | BM88: N | BN88: N | BU88: 0 | BV88: 0 | BW88: 0 | BX88: 0 | BY88: 0 | BZ88: 0 | CA88: P | CB88: N | CC88: N | CD88: N | CE88: N | CF88: N | CG88: N | CH88: N | CI88: 0 | CJ88: N | CL88: 0 | CM88: N | CN88: 0 | CO88: N | CP88: N | CQ88: A | CR88: N | CT88: Y | CU88: 4 | CV88: N | CW88: N | CY88: N | DA88: Y | DC88: 0 | DD88: O | DG88: N | DH88: N | DI88: N | DJ88: N | DK88: N | DP88: 0 | DQ88: 0 | DR88: 90 | DS88: 90 | DT88: 0 | DU88: 0 | DV88: N | DW88: P | DX88: P | DY88: 17 | DZ88: N | EC88: D | ED88: 2 | EE88: R | EF88: 100 | EG88: N | EH88: N | EI88: N | EJ88: Z | EK88: N | EL88: 2 | EM88: N | EO88: 0 | EP88: P | EQ88: N | ER88: N | ES88: 0 | EV88: Y | EW88: 0 | EX88: N | EY88: N | EZ88: N | FA88: N | FB88: Y | FC88: N | FD88: B | FE88: N | FF88: N | FG88: N | FH88: N | FI88: N | FJ88: N | FK88: N | FL88: N | FM88: 0 | FN88: N | FO88: N | FP88: N | FQ88: N | FR88: 0 | FS88: 0 | FT88: N | FV88: 0 | FY88: N | FZ88: N | GA88: 1 | GB88: M | GC88: N | GD88: N | GE88: N | GF88: 0 | GG88: O | GH88: N | GI88: N | GJ88: N | GK88: Y | GL88: P | GM88: 0 | GN88: 0 | GO88: Y | GP88: Y | GQ88: Y | GR88: 2 | GS88: 2 | GT88: 0 | GU88: 0 | GV88: 0 | GW88: N | GX88: Y | HB88: N | HC88: 0 | HD88: N | HE88: N | HG88: 0 | HH88: 0 | HI88: 0 | HJ88: 0 | HK88: 0 | HM88: N | HO88: 0 | HP88: 0 | HR88: 0 | HS88: 0 | HT88: 0 | HU88: 0 | HV88: D | HW88: W | HY88: 0 | HZ88: 0 | IA88: 0 | IB88: Y | IC88: N | ID88: N | IE88: N
A89: BC | B89: KREDIT RCP | C89: KREDIT PERSEKOT RCP | D89: 106 | E89: On B/S,Program,KI-ID | G89: 8 | H89: 310 | I89: IDR | J89: 31 | K89: 0.06 | L89: 0.36 | M89: 0.06 | N89: 0.36 | O89: N | P89: 1 | Q89: M | R89: 6 | S89: 0 | T89: Y | U89: Y | V89: N | W89: 0 | X89: I | Y89: 1 | Z89: 0 | AA89: 0 | AB89: 0 | AC89: 0 | AD89: 0 | AE89: 0 | AF89: 7 | AG89: 21 | AH89: 35 | AI89: 49 | AJ89: 63 | AK89: 77 | AL89: 0 | AM89: 0 | AN89: 0 | AO89: Y | AP89: R | AQ89: 0 | AR89: 0 | AS89: 1 | AT89: 0 | AU89: Y | BC89: 0 | BD89: 0 | BE89: 0 | BF89: 0 | BG89: 0 | BH89: 0 | BI89: N | BJ89: N | BK89: N | BL89: N | BM89: N | BN89: N | BU89: 0 | BV89: 0 | BW89: 0 | BX89: 0 | BY89: 0 | BZ89: 0 | CA89: P | CB89: N | CC89: N | CD89: N | CE89: N | CF89: N | CG89: N | CH89: N | CI89: 0 | CJ89: N | CL89: 0 | CM89: N | CN89: 0 | CO89: N | CP89: N | CQ89: A | CR89: N | CT89: Y | CU89: 4 | CV89: N | CW89: N | CY89: N | DA89: Y | DC89: 0 | DD89: O | DG89: N | DH89: N | DI89: N | DJ89: N | DK89: N | DP89: 0 | DQ89: 0 | DR89: 90 | DS89: 90 | DT89: 0 | DU89: 0 | DV89: N | DW89: P | DX89: P | DY89: 17 | DZ89: N | EC89: D | ED89: 2 | EE89: R | EF89: 100 | EG89: N | EH89: N | EI89: N | EJ89: Z | EK89: N | EL89: 2 | EM89: N | EO89: 0 | EP89: P | EQ89: Y | ER89: N | ES89: 0 | EV89: Y | EW89: 0 | EX89: N | EY89: N | EZ89: N | FA89: N | FB89: Y | FC89: N | FD89: B | FE89: N | FF89: N | FG89: N | FH89: N | FI89: N | FJ89: N | FK89: N | FL89: N | FM89: 0 | FN89: N | FO89: N | FP89: N | FQ89: N | FR89: 0 | FS89: 0 | FT89: N | FV89: 0 | FY89: N | FZ89: N | GA89: 1 | GB89: M | GC89: N | GD89: N | GE89: N | GF89: 0 | GG89: O | GH89: N | GI89: N | GJ89: N | GK89: Y | GL89: P | GM89: 0 | GN89: 0 | GO89: Y | GP89: Y | GQ89: Y | GR89: 2 | GS89: 2 | GT89: 0 | GU89: 0 | GV89: 0 | GW89: N | GX89: Y | HB89: N | HC89: 0 | HD89: N | HE89: N | HG89: 0 | HH89: 0 | HI89: 0 | HJ89: 0 | HK89: 0 | HM89: N | HO89: 0 | HP89: 0 | HR89: 0 | HS89: 0 | HT89: 0 | HU89: 0 | HV89: D | HW89: W | HY89: 0 | HZ89: 0 | IA89: 0 | IB89: Y | IC89: N | ID89: N | IE89: N
A90: BD | B90: INPRES PSR | C90: KREDIT INPRES PASAR | D90: 302 | E90: POffB,Perhit Bunga K | G90: 8 | H90: 240 | I90: IDR | J90: 31 | K90: 0.06 | L90: 0.36 | M90: 0.06 | N90: 0.36 | O90: N | P90: 1 | Q90: M | R90: 6 | S90: 0 | T90: Y | U90: Y | V90: N | W90: 0 | X90: I | Y90: 1 | Z90: 0 | AA90: 0 | AB90: 0 | AC90: 0 | AD90: 0 | AE90: 0 | AF90: 7 | AG90: 21 | AH90: 35 | AI90: 49 | AJ90: 63 | AK90: 77 | AL90: 0 | AM90: 0 | AN90: 0 | AO90: Y | AP90: R | AQ90: 0 | AR90: 0 | AS90: 1 | AT90: 0 | AU90: Y | BC90: 0 | BD90: 0 | BE90: 0 | BF90: 0 | BG90: 0 | BH90: 0 | BI90: N | BJ90: N | BK90: N | BL90: N | BM90: N | BN90: N | BU90: 0 | BV90: 0 | BW90: 0 | BX90: 0 | BY90: 0 | BZ90: 0 | CA90: P | CB90: N | CC90: N | CD90: N | CE90: N | CF90: N | CG90: N | CH90: N | CI90: 0 | CJ90: N | CL90: 0 | CM90: N | CN90: 0 | CO90: N | CP90: N | CQ90: A | CR90: N | CT90: Y | CU90: 4 | CV90: N | CW90: N | CY90: N | DA90: Y | DC90: 0 | DD90: O | DG90: N | DH90: N | DI90: N | DJ90: N | DK90: N | DP90: 0 | DQ90: 0 | DR90: 90 | DS90: 90 | DT90: 0 | DU90: 0 | DV90: N | DW90: P | DX90: P | DY90: 17 | DZ90: N | EC90: D | ED90: 2 | EE90: R | EF90: 100 | EG90: N | EH90: N | EI90: N | EJ90: Z | EK90: N | EL90: 2 | EM90: N | EO90: 0 | EP90: P | EQ90: N | ER90: N | ES90: 0 | EV90: Y | EW90: 0 | EX90: N | EY90: N | EZ90: N | FA90: N | FB90: Y | FC90: N | FD90: B | FE90: N | FF90: N | FG90: N | FH90: N | FI90: N | FJ90: N | FK90: N | FL90: N | FM90: 0 | FN90: N | FO90: N | FP90: N | FQ90: N | FR90: 0 | FS90: 0 | FT90: N | FV90: 0 | FY90: N | FZ90: N | GA90: 1 | GB90: M | GC90: N | GD90: N | GE90: N | GF90: 0 | GG90: O | GH90: N | GI90: N | GJ90: N | GK90: Y | GL90: P | GM90: 0 | GN90: 0 | GO90: Y | GP90: Y | GQ90: Y | GR90: 2 | GS90: 2 | GT90: 0 | GU90: 0 | GV90: 0 | GW90: N | GX90: Y | HB90: N | HC90: 0 | HD90: N | HE90: N | HG90: 0 | HH90: 0 | HI90: 0 | HJ90: 0 | HK90: 0 | HM90: N | HO90: 0 | HP90: 0 | HR90: 0 | HS90: 0 | HT90: 0 | HU90: 0 | HV90: D | HW90: W | HY90: 0 | HZ90: 0 | IA90: 0 | IB90: Y | IC90: N | ID90: N | IE90: N
A91: BE | B91: KUD/NONKUD | C91: KOP KUD/NONKUD PROG | D91: 104 | E91: On B/S,Program,KI-ID | G91: 8 | H91: 240 | I91: IDR | J91: 31 | K91: 0.06 | L91: 0.36 | M91: 0.06 | N91: 0.36 | O91: N | P91: 1 | Q91: M | R91: 6 | S91: 0 | T91: Y | U91: Y | V91: N | W91: 0 | X91: I | Y91: 1 | Z91: 0 | AA91: 0 | AB91: 0 | AC91: 0 | AD91: 0 | AE91: 0 | AF91: 7 | AG91: 21 | AH91: 35 | AI91: 49 | AJ91: 63 | AK91: 77 | AL91: 0 | AM91: 0 | AN91: 0 | AO91: Y | AP91: R | AQ91: 0 | AR91: 0 | AS91: 1 | AT91: 0 | AU91: Y | BC91: 0 | BD91: 0 | BE91: 0 | BF91: 0 | BG91: 0 | BH91: 0 | BI91: N | BJ91: N | BK91: N | BL91: N | BM91: N | BN91: N | BU91: 0 | BV91: 0 | BW91: 0 | BX91: 0 | BY91: 0 | BZ91: 0 | CA91: P | CB91: N | CC91: N | CD91: N | CE91: N | CF91: N | CG91: N | CH91: N | CI91: 0 | CJ91: N | CL91: 0 | CM91: N | CN91: 0 | CO91: N | CP91: N | CQ91: A | CR91: N | CT91: Y | CU91: 4 | CV91: N | CW91: N | CY91: N | DA91: Y | DC91: 0 | DD91: O | DG91: N | DH91: N | DI91: N | DJ91: N | DK91: N | DP91: 0 | DQ91: 0 | DR91: 90 | DS91: 90 | DT91: 0 | DU91: 0 | DV91: N | DW91: P | DX91: P | DY91: 17 | DZ91: N | EC91: D | ED91: 2 | EE91: R | EF91: 100 | EG91: N | EH91: N | EI91: N | EJ91: Z | EK91: N | EL91: 2 | EM91: N | EO91: 0 | EP91: P | EQ91: N | ER91: N | ES91: 0 | EV91: Y | EW91: 6 | EX91: N | EY91: N | EZ91: N | FA91: N | FB91: Y | FC91: N | FD91: B | FE91: N | FF91: N | FG91: N | FH91: N | FI91: N | FJ91: N | FK91: N | FL91: N | FM91: 0 | FN91: N | FO91: N | FP91: N | FQ91: N | FR91: 0 | FS91: 0 | FT91: N | FV91: 0 | FY91: N | FZ91: N | GA91: 1 | GB91: M | GC91: N | GD91: N | GE91: N | GF91: 0 | GG91: O | GH91: N | GI91: N | GJ91: N | GK91: Y | GL91: P | GM91: 0 | GN91: 0 | GO91: Y | GP91: Y | GQ91: Y | GR91: 2 | GS91: 2 | GT91: 0 | GU91: 0 | GV91: 0 | GW91: N | GX91: Y | HB91: N | HC91: 0 | HD91: N | HE91: N | HG91: 0 | HH91: 0 | HI91: 0 | HJ91: 0 | HK91: 0 | HM91: N | HO91: 0 | HP91: 0 | HR91: 0 | HS91: 0 | HT91: 0 | HU91: 0 | HV91: D | HW91: W | HY91: 0 | HZ91: 0 | IA91: 0 | IB91: N | IC91: N | ID91: N | IE91: N
A92: BF | B92: KUD/NONKUD | C92: KOP KUD/NONKUD RITEL | D92: 105 | E92: On B/S,Program,KI-ID | G92: 8 | H92: 230 | I92: IDR | J92: 31 | K92: 0.06 | L92: 0.36 | M92: 0.06 | N92: 0.36 | O92: N | P92: 1 | Q92: M | R92: 6 | S92: 0 | T92: Y | U92: Y | V92: N | W92: 0 | X92: I | Y92: 1 | Z92: 0 | AA92: 0 | AB92: 0 | AC92: 0 | AD92: 0 | AE92: 0 | AF92: 7 | AG92: 21 | AH92: 35 | AI92: 49 | AJ92: 63 | AK92: 77 | AL92: 0 | AM92: 0 | AN92: 0 | AO92: Y | AP92: R | AQ92: 0 | AR92: 0 | AS92: 1 | AT92: 0 | AU92: Y | BC92: 0 | BD92: 0 | BE92: 0 | BF92: 0 | BG92: 0 | BH92: 0 | BI92: N | BJ92: N | BK92: N | BL92: N | BM92: N | BN92: N | BU92: 0 | BV92: 0 | BW92: 0 | BX92: 0 | BY92: 0 | BZ92: 0 | CA92: P | CB92: N | CC92: N | CD92: N | CE92: N | CF92: N | CG92: N | CH92: N | CI92: 0 | CJ92: N | CL92: 0 | CM92: N | CN92: 0 | CO92: N | CP92: N | CQ92: A | CR92: N | CT92: Y | CU92: 4 | CV92: N | CW92: N | CY92: N | DA92: Y | DC92: 0 | DD92: O | DG92: N | DH92: N | DI92: N | DJ92: N | DK92: N | DP92: 0 | DQ92: 0 | DR92: 90 | DS92: 90 | DT92: 0 | DU92: 0 | DV92: N | DW92: P | DX92: P | DY92: 17 | DZ92: N | EC92: D | ED92: 2 | EE92: R | EF92: 100 | EG92: N | EH92: N | EI92: N | EJ92: Z | EK92: N | EL92: 2 | EM92: N | EO92: 0 | EP92: P | EQ92: N | ER92: N | ES92: 0 | EV92: Y | EW92: 0 | EX92: N | EY92: N | EZ92: N | FA92: N | FB92: Y | FC92: N | FD92: B | FE92: N | FF92: N | FG92: N | FH92: N | FI92: N | FJ92: N | FK92: N | FL92: N | FM92: 0 | FN92: N | FO92: N | FP92: N | FQ92: N | FR92: 0 | FS92: 0 | FT92: N | FV92: 0 | FY92: N | FZ92: N | GA92: 1 | GB92: M | GC92: N | GD92: N | GE92: N | GF92: 0 | GG92: O | GH92: N | GI92: N | GJ92: N | GK92: Y | GL92: P | GM92: 0 | GN92: 0 | GO92: Y | GP92: Y | GQ92: Y | GR92: 2 | GS92: 2 | GT92: 0 | GU92: 0 | GV92: 0 | GW92: N | GX92: Y | HB92: N | HC92: 0 | HD92: N | HE92: N | HG92: 0 | HH92: 0 | HI92: 0 | HJ92: 0 | HK92: 0 | HM92: N | HO92: 0 | HP92: 0 | HR92: 0 | HS92: 0 | HT92: 0 | HU92: 0 | HV92: D | HW92: W | HY92: 0 | HZ92: 0 | IA92: 0 | IB92: Y | IC92: N | ID92: N | IE92: N
A93: BG | B93: KUD/NONKUD | C93: KOP KUD/NONKUD MENGH | D93: 107 | E93: On B/S,Program,KI-ID | G93: 8 | H93: 320 | I93: IDR | J93: 31 | K93: 0.02 | L93: 0.36 | M93: 0.02 | N93: 0.36 | O93: N | P93: 1 | Q93: M | R93: 6 | S93: 0 | T93: Y | U93: Y | V93: N | W93: 0 | X93: I | Y93: 1 | Z93: 0 | AA93: 0 | AB93: 0 | AC93: 0 | AD93: 0 | AE93: 0 | AF93: 7 | AG93: 21 | AH93: 35 | AI93: 49 | AJ93: 63 | AK93: 77 | AL93: 0 | AM93: 0 | AN93: 0 | AO93: Y | AP93: R | AQ93: 0 | AR93: 0 | AS93: 1 | AT93: 0 | AU93: Y | BC93: 0 | BD93: 0 | BE93: 0 | BF93: 0 | BG93: 0 | BH93: 0 | BI93: N | BJ93: N | BK93: N | BL93: N | BM93: N | BN93: N | BU93: 0 | BV93: 0 | BW93: 0 | BX93: 0 | BY93: 0 | BZ93: 0 | CA93: P | CB93: N | CC93: N | CD93: N | CE93: N | CF93: N | CG93: N | CH93: N | CI93: 0 | CJ93: N | CL93: 0 | CM93: N | CN93: 0 | CO93: N | CP93: N | CQ93: A | CR93: N | CT93: Y | CU93: 4 | CV93: N | CW93: N | CY93: N | DA93: Y | DC93: 0 | DD93: O | DG93: N | DH93: N | DI93: N | DJ93: N | DK93: N | DP93: 0 | DQ93: 0 | DR93: 90 | DS93: 90 | DT93: 0 | DU93: 0 | DV93: N | DW93: P | DX93: P | DY93: 17 | DZ93: N | EC93: D | ED93: 2 | EE93: R | EF93: 100 | EG93: N | EH93: N | EI93: N | EJ93: Z | EK93: N | EL93: 2 | EM93: N | EO93: 0 | EP93: P | EQ93: Y | ER93: N | ES93: 0 | EV93: Y | EW93: 6 | EX93: N | EY93: N | EZ93: N | FA93: N | FB93: Y | FC93: N | FD93: B | FE93: N | FF93: N | FG93: N | FH93: N | FI93: N | FJ93: N | FK93: N | FL93: N | FM93: 0 | FN93: N | FO93: N | FP93: N | FQ93: N | FR93: 0 | FS93: 0 | FT93: N | FV93: 0 | FY93: N | FZ93: N | GA93: 1 | GB93: M | GC93: N | GD93: N | GE93: N | GF93: 0 | GG93: O | GH93: N | GI93: N | GJ93: N | GK93: Y | GL93: P | GM93: 0 | GN93: 0 | GO93: Y | GP93: Y | GQ93: Y | GR93: 2 | GS93: 2 | GT93: 0 | GU93: 0 | GV93: 0 | GW93: N | GX93: Y | HB93: N | HC93: 0 | HD93: N | HE93: N | HG93: 0 | HH93: 0 | HI93: 0 | HJ93: 0 | HK93: 0 | HM93: N | HO93: 0 | HP93: 0 | HR93: 0 | HS93: 0 | HT93: 0 | HU93: 0 | HV93: D | HW93: W | HY93: 0 | HZ93: 0 | IA93: 0 | IB93: N | IC93: Y | ID93: N | IE93: N
A94: BH | B94: KOPPOLAIII | C94: KRD KOP POLA III | D94: 104 | E94: On B/S,Program,KI-ID | G94: 8 | H94: 240 | I94: IDR | J94: 31 | K94: 0.06 | L94: 0.36 | M94: 0.06 | N94: 0.36 | O94: N | P94: 1 | Q94: M | R94: 6 | S94: 0 | T94: Y | U94: Y | V94: N | W94: 0 | X94: I | Y94: 1 | Z94: 0 | AA94: 0 | AB94: 0 | AC94: 0 | AD94: 0 | AE94: 0 | AF94: 7 | AG94: 21 | AH94: 35 | AI94: 49 | AJ94: 63 | AK94: 77 | AL94: 0 | AM94: 0 | AN94: 0 | AO94: Y | AP94: R | AQ94: 0 | AR94: 0 | AS94: 1 | AT94: 0 | AU94: Y | BC94: 0 | BD94: 0 | BE94: 0 | BF94: 0 | BG94: 0 | BH94: 0 | BI94: N | BJ94: N | BK94: N | BL94: N | BM94: N | BN94: N | BU94: 0 | BV94: 0 | BW94: 0 | BX94: 0 | BY94: 0 | BZ94: 0 | CA94: P | CB94: N | CC94: N | CD94: N | CE94: N | CF94: N | CG94: N | CH94: N | CI94: 0 | CJ94: N | CL94: 0 | CM94: N | CN94: 0 | CO94: N | CP94: N | CQ94: A | CR94: N | CT94: Y | CU94: 4 | CV94: N | CW94: N | CY94: N | DA94: Y | DC94: 0 | DD94: O | DG94: N | DH94: N | DI94: N | DJ94: N | DK94: N | DP94: 0 | DQ94: 0 | DR94: 90 | DS94: 90 | DT94: 0 | DU94: 0 | DV94: N | DW94: P | DX94: P | DY94: 17 | DZ94: N | EC94: D | ED94: 2 | EE94: R | EF94: 100 | EG94: N | EH94: N | EI94: N | EJ94: Z | EK94: N | EL94: 2 | EM94: N | EO94: 0 | EP94: P | EQ94: N | ER94: N | ES94: 0 | EV94: Y | EW94: 6 | EX94: N | EY94: N | EZ94: N | FA94: N | FB94: Y | FC94: N | FD94: B | FE94: N | FF94: N | FG94: N | FH94: N | FI94: N | FJ94: N | FK94: N | FL94: N | FM94: 0 | FN94: N | FO94: N | FP94: N | FQ94: N | FR94: 0 | FS94: 0 | FT94: N | FV94: 0 | FY94: N | FZ94: N | GA94: 1 | GB94: M | GC94: N | GD94: N | GE94: N | GF94: 0 | GG94: O | GH94: N | GI94: N | GJ94: N | GK94: Y | GL94: P | GM94: 0 | GN94: 0 | GO94: Y | GP94: Y | GQ94: Y | GR94: 2 | GS94: 2 | GT94: 0 | GU94: 0 | GV94: 0 | GW94: N | GX94: Y | HB94: N | HC94: 0 | HD94: N | HE94: N | HG94: 0 | HH94: 0 | HI94: 0 | HJ94: 0 | HK94: 0 | HM94: N | HO94: 0 | HP94: 0 | HR94: 0 | HS94: 0 | HT94: 0 | HU94: 0 | HV94: D | HW94: W | HY94: 0 | HZ94: 0 | IA94: 0 | IB94: N | IC94: N | ID94: N | IE94: N
A95: BI | B95: PENGPANGAN | C95: R/C PENG PANGAN KUD | D95: 104 | E95: On B/S,Program,KI-ID | G95: 8 | H95: 240 | I95: IDR | J95: 31 | K95: 0.06 | L95: 0.36 | M95: 0.06 | N95: 0.36 | O95: N | P95: 1 | Q95: M | R95: 6 | S95: 0 | T95: Y | U95: Y | V95: N | W95: 0 | X95: I | Y95: 1 | Z95: 0 | AA95: 0 | AB95: 0 | AC95: 0 | AD95: 0 | AE95: 0 | AF95: 7 | AG95: 21 | AH95: 35 | AI95: 49 | AJ95: 63 | AK95: 77 | AL95: 0 | AM95: 0 | AN95: 0 | AO95: Y | AP95: R | AQ95: 0 | AR95: 0 | AS95: 1 | AT95: 0 | AU95: Y | BC95: 0 | BD95: 0 | BE95: 0 | BF95: 0 | BG95: 0 | BH95: 0 | BI95: N | BJ95: N | BK95: N | BL95: N | BM95: N | BN95: N | BU95: 0 | BV95: 0 | BW95: 0 | BX95: 0 | BY95: 0 | BZ95: 0 | CA95: P | CB95: N | CC95: N | CD95: N | CE95: N | CF95: N | CG95: N | CH95: N | CI95: 0 | CJ95: N | CL95: 0 | CM95: N | CN95: 0 | CO95: N | CP95: N | CQ95: A | CR95: N | CT95: Y | CU95: 4 | CV95: N | CW95: N | CY95: N | DA95: Y | DC95: 0 | DD95: O | DG95: N | DH95: N | DI95: N | DJ95: N | DK95: N | DP95: 0 | DQ95: 0 | DR95: 90 | DS95: 90 | DT95: 0 | DU95: 0 | DV95: N | DW95: P | DX95: P | DY95: 17 | DZ95: N | EC95: D | ED95: 2 | EE95: R | EF95: 100 | EG95: N | EH95: N | EI95: N | EJ95: Z | EK95: N | EL95: 1 | EM95: N | EO95: 0 | EP95: P | EQ95: Y | ER95: N | ES95: 0 | EV95: Y | EW95: 0 | EX95: N | EY95: N | EZ95: N | FA95: N | FB95: Y | FC95: N | FD95: B | FE95: N | FF95: N | FG95: N | FH95: N | FI95: N | FJ95: N | FK95: N | FL95: N | FM95: 0 | FN95: N | FO95: N | FP95: N | FQ95: N | FR95: 0 | FS95: 0 | FT95: N | FV95: 0 | FY95: N | FZ95: N | GA95: 1 | GB95: M | GC95: N | GD95: N | GE95: N | GF95: 0 | GG95: O | GH95: N | GI95: N | GJ95: N | GK95: Y | GL95: P | GM95: 0 | GN95: 0 | GO95: Y | GP95: Y | GQ95: Y | GR95: 2 | GS95: 2 | GT95: 0 | GU95: 0 | GV95: 0 | GW95: N | GX95: Y | HB95: N | HC95: 0 | HD95: N | HE95: N | HG95: 0 | HH95: 0 | HI95: 0 | HJ95: 0 | HK95: 0 | HM95: N | HO95: 0 | HP95: 0 | HR95: 0 | HS95: 0 | HT95: 0 | HU95: 0 | HV95: D | HW95: W | HY95: 0 | HZ95: 0 | IA95: 0 | IB95: Y | IC95: N | ID95: N | IE95: N
A96: BJ | B96: KREDIT RCP | C96: KREDIT INV FSDP | D96: 106 | E96: On B/S,Program,KI-ID | G96: 8 | H96: 310 | I96: IDR | J96: 31 | K96: 0.06 | L96: 0.36 | M96: 0.06 | N96: 0.36 | O96: N | P96: 1 | Q96: M | R96: 6 | S96: 0 | T96: Y | U96: Y | V96: N | W96: 0 | X96: I | Y96: 1 | Z96: 0 | AA96: 0 | AB96: 0 | AC96: 0 | AD96: 0 | AE96: 0 | AF96: 7 | AG96: 21 | AH96: 35 | AI96: 49 | AJ96: 63 | AK96: 77 | AL96: 0 | AM96: 0 | AN96: 0 | AO96: Y | AP96: R | AQ96: 0 | AR96: 0 | AS96: 1 | AT96: 0 | AU96: Y | BC96: 0 | BD96: 0 | BE96: 0 | BF96: 0 | BG96: 0 | BH96: 0 | BI96: N | BJ96: N | BK96: N | BL96: N | BM96: N | BN96: N | BU96: 0 | BV96: 0 | BW96: 0 | BX96: 0 | BY96: 0 | BZ96: 0 | CA96: P | CB96: N | CC96: N | CD96: N | CE96: N | CF96: N | CG96: N | CH96: N | CI96: 0 | CJ96: N | CL96: 0 | CM96: N | CN96: 0 | CO96: N | CP96: N | CQ96: A | CR96: N | CT96: Y | CU96: 4 | CV96: N | CW96: N | CY96: N | DA96: Y | DC96: 0 | DD96: O | DG96: N | DH96: N | DI96: N | DJ96: N | DK96: N | DP96: 0 | DQ96: 0 | DR96: 90 | DS96: 90 | DT96: 0 | DU96: 0 | DV96: N | DW96: P | DX96: P | DY96: 17 | DZ96: N | EC96: D | ED96: 2 | EE96: R | EF96: 100 | EG96: N | EH96: N | EI96: N | EJ96: Z | EK96: N | EL96: 2 | EM96: N | EO96: 0 | EP96: P | EQ96: Y | ER96: N | ES96: 0 | EV96: Y | EW96: 0 | EX96: N | EY96: N | EZ96: N | FA96: N | FB96: Y | FC96: N | FD96: B | FE96: N | FF96: N | FG96: N | FH96: N | FI96: N | FJ96: N | FK96: N | FL96: N | FM96: 0 | FN96: N | FO96: N | FP96: N | FQ96: N | FR96: 0 | FS96: 0 | FT96: N | FV96: 0 | FY96: N | FZ96: N | GA96: 1 | GB96: M | GC96: N | GD96: N | GE96: N | GF96: 0 | GG96: O | GH96: N | GI96: N | GJ96: N | GK96: Y | GL96: P | GM96: 0 | GN96: 0 | GO96: Y | GP96: Y | GQ96: Y | GR96: 2 | GS96: 2 | GT96: 0 | GU96: 0 | GV96: 0 | GW96: N | GX96: Y | HB96: N | HC96: 0 | HD96: N | HE96: N | HG96: 0 | HH96: 0 | HI96: 0 | HJ96: 0 | HK96: 0 | HM96: N | HO96: 0 | HP96: 0 | HR96: 0 | HS96: 0 | HT96: 0 | HU96: 0 | HV96: D | HW96: W | HY96: 0 | HZ96: 0 | IA96: 0 | IB96: Y | IC96: N | ID96: N | IE96: N
A97: BK | B97: KRD SPETP | C97: KRD SPETP | D97: 104 | E97: On B/S,Program,KI-ID | G97: 8 | H97: 240 | I97: IDR | J97: 31 | K97: 0.06 | L97: 0.36 | M97: 0.06 | N97: 0.36 | O97: N | P97: 1 | Q97: M | R97: 6 | S97: 0 | T97: Y | U97: Y | V97: N | W97: 0 | X97: I | Y97: 1 | Z97: 0 | AA97: 0 | AB97: 0 | AC97: 0 | AD97: 0 | AE97: 0 | AF97: 7 | AG97: 21 | AH97: 35 | AI97: 49 | AJ97: 63 | AK97: 77 | AL97: 0 | AM97: 0 | AN97: 0 | AO97: Y | AP97: R | AQ97: 0 | AR97: 0 | AS97: 1 | AT97: 0 | AU97: Y | BC97: 0 | BD97: 0 | BE97: 0 | BF97: 0 | BG97: 0 | BH97: 0 | BI97: N | BJ97: N | BK97: N | BL97: N | BM97: N | BN97: N | BU97: 0 | BV97: 0 | BW97: 0 | BX97: 0 | BY97: 0 | BZ97: 0 | CA97: P | CB97: N | CC97: N | CD97: N | CE97: N | CF97: N | CG97: N | CH97: N | CI97: 0 | CJ97: N | CL97: 0 | CM97: N | CN97: 0 | CO97: N | CP97: N | CQ97: A | CR97: N | CT97: Y | CU97: 4 | CV97: N | CW97: N | CY97: N | DA97: Y | DC97: 0 | DD97: O | DG97: N | DH97: N | DI97: N | DJ97: N | DK97: N | DP97: 0 | DQ97: 0 | DR97: 90 | DS97: 90 | DT97: 0 | DU97: 0 | DV97: N | DW97: P | DX97: P | DY97: 17 | DZ97: N | EC97: D | ED97: 2 | EE97: R | EF97: 100 | EG97: N | EH97: N | EI97: N | EJ97: Z | EK97: N | EL97: 2 | EM97: N | EO97: 0 | EP97: P | EQ97: N | ER97: N | ES97: 0 | EV97: Y | EW97: 0 | EX97: N | EY97: N | EZ97: N | FA97: N | FB97: Y | FC97: N | FD97: B | FE97: N | FF97: N | FG97: N | FH97: N | FI97: N | FJ97: N | FK97: N | FL97: N | FM97: 0 | FN97: N | FO97: N | FP97: N | FQ97: N | FR97: 0 | FS97: 0 | FT97: N | FV97: 0 | FY97: N | FZ97: N | GA97: 1 | GB97: M | GC97: N | GD97: N | GE97: N | GF97: 0 | GG97: O | GH97: N | GI97: N | GJ97: N | GK97: Y | GL97: P | GM97: 0 | GN97: 0 | GO97: Y | GP97: Y | GQ97: Y | GR97: 2 | GS97: 2 | GT97: 0 | GU97: 0 | GV97: 0 | GW97: N | GX97: Y | HB97: N | HC97: 0 | HD97: N | HE97: N | HG97: 0 | HH97: 0 | HI97: 0 | HJ97: 0 | HK97: 0 | HM97: N | HO97: 0 | HP97: 0 | HR97: 0 | HS97: 0 | HT97: 0 | HU97: 0 | HV97: D | HW97: W | HY97: 0 | HZ97: 0 | IA97: 0 | IB97: Y | IC97: N | ID97: N | IE97: N
A98: BL | B98: SFDP-KIB | C98: KRD SFDP POLA KIB | D98: 104 | E98: On B/S,Program,KI-ID | G98: 8 | H98: 240 | I98: IDR | J98: 31 | K98: 0.06 | L98: 0.36 | M98: 0.06 | N98: 0.36 | O98: N | P98: 1 | Q98: M | R98: 6 | S98: 0 | T98: Y | U98: Y | V98: N | W98: 0 | X98: I | Y98: 1 | Z98: 0 | AA98: 0 | AB98: 0 | AC98: 0 | AD98: 0 | AE98: 0 | AF98: 7 | AG98: 21 | AH98: 35 | AI98: 49 | AJ98: 63 | AK98: 77 | AL98: 0 | AM98: 0 | AN98: 0 | AO98: Y | AP98: R | AQ98: 0 | AR98: 0 | AS98: 1 | AT98: 0 | AU98: Y | BC98: 0 | BD98: 0 | BE98: 0 | BF98: 0 | BG98: 0 | BH98: 0 | BI98: N | BJ98: N | BK98: N | BL98: N | BM98: N | BN98: N | BU98: 0 | BV98: 0 | BW98: 0 | BX98: 0 | BY98: 0 | BZ98: 0 | CA98: P | CB98: N | CC98: N | CD98: N | CE98: N | CF98: N | CG98: N | CH98: N | CI98: 0 | CJ98: N | CL98: 0 | CM98: N | CN98: 0 | CO98: N | CP98: N | CQ98: A | CR98: N | CT98: Y | CU98: 4 | CV98: N | CW98: N | CY98: N | DA98: Y | DC98: 0 | DD98: O | DG98: N | DH98: N | DI98: N | DJ98: N | DK98: N | DP98: 0 | DQ98: 0 | DR98: 90 | DS98: 90 | DT98: 0 | DU98: 0 | DV98: N | DW98: P | DX98: P | DY98: 17 | DZ98: N | EC98: D | ED98: 2 | EE98: R | EF98: 100 | EG98: N | EH98: N | EI98: N | EJ98: Z | EK98: N | EL98: 2 | EM98: N | EO98: 0 | EP98: P | EQ98: N | ER98: N | ES98: 0 | EV98: Y | EW98: 0 | EX98: N | EY98: N | EZ98: N | FA98: N | FB98: Y | FC98: N | FD98: B | FE98: N | FF98: N | FG98: N | FH98: N | FI98: N | FJ98: N | FK98: N | FL98: N | FM98: 0 | FN98: N | FO98: N | FP98: N | FQ98: N | FR98: 0 | FS98: 0 | FT98: N | FV98: 0 | FY98: N | FZ98: N | GA98: 1 | GB98: M | GC98: N | GD98: N | GE98: N | GF98: 0 | GG98: O | GH98: N | GI98: N | GJ98: N | GK98: Y | GL98: P | GM98: 0 | GN98: 0 | GO98: Y | GP98: Y | GQ98: Y | GR98: 2 | GS98: 2 | GT98: 0 | GU98: 0 | GV98: 0 | GW98: N | GX98: Y | HB98: N | HC98: 0 | HD98: N | HE98: N | HG98: 0 | HH98: 0 | HI98: 0 | HJ98: 0 | HK98: 0 | HM98: N | HO98: 0 | HP98: 0 | HR98: 0 | HS98: 0 | HT98: 0 | HU98: 0 | HV98: D | HW98: W | HY98: 0 | HZ98: 0 | IA98: 0 | IB98: Y | IC98: N | ID98: N | IE98: N
... A101: BO | B101: KKOP AGRIB | C101: KKOP KI AGRIBISNIS | D101: 104 | E101: On B/S,Program,KI-ID | G101: 8 | H101: 240 | I101: IDR | J101: 31 | K101: 0.06 | L101: 0.36 | M101: 0.06 | N101: 0.36 | O101: N | P101: 1 | Q101: M | R101: 6 | S101: 0 | T101: Y | U101: Y | V101: N | W101: 0 | X101: I | Y101: 1 | Z101: 0 | AA101: 0 | AB101: 0 | AC101: 0 | AD101: 0 | AE101: 0 | AF101: 7 | AG101: 21 | AH101: 35 | AI101: 49 | AJ101: 63 | AK101: 77 | AL101: 0 | AM101: 0 | AN101: 0 | AO101: Y | AP101: R | AQ101: 0 | AR101: 0 | AS101: 1 | AT101: 0 | AU101: Y | BC101: 0 | BD101: 0 | BE101: 0 | BF101: 0 | BG101: 0 | BH101: 0 | BI101: N | BJ101: N | BK101: N | BL101: N | BM101: N | BN101: N | BU101: 0 | BV101: 0 | BW101: 0 | BX101: 0 | BY101: 0 | BZ101: 0 | CA101: P | CB101: N | CC101: N | CD101: N | CE101: N | CF101: N | CG101: N | CH101: N | CI101: 0 | CJ101: N | CL101: 0 | CM101: N | CN101: 0 | CO101: N | CP101: N | CQ101: A | CR101: N | CT101: Y | CU101: 4 | CV101: N | CW101: N | CY101: N | DA101: Y | DC101: 0 | DD101: O | DG101: N | DH101: N | DI101: N | DJ101: N | DK101: N | DP101: 0 | DQ101: 0 | DR101: 90 | DS101: 90 | DT101: 0 | DU101: 0 | DV101: N | DW101: P | DX101: P | DY101: 17 | DZ101: N | EC101: D | ED101: 2 | EE101: R | EF101: 100 | EG101: N | EH101: N | EI101: N | EJ101: Z | EK101: N | EL101: 2 | EM101: N | EO101: 0 | EP101: P | EQ101: N | ER101: N | ES101: 0 | EV101: Y | EW101: 0 | EX101: N | EY101: N | EZ101: N | FA101: N | FB101: Y | FC101: N | FD101: B | FE101: N | FF101: N | FG101: N | FH101: N | FI101: N | FJ101: N | FK101: N | FL101: N | FM101: 0 | FN101: N | FO101: N | FP101: N | FQ101: N | FR101: 0 | FS101: 0 | FT101: N | FV101: 0 | FY101: N | FZ101: N | GA101: 1 | GB101: M | GC101: N | GD101: N | GE101: N | GF101: 0 | GG101: O | GH101: N | GI101: N | GJ101: N | GK101: Y | GL101: P | GM101: 0 | GN101: 0 | GO101: Y | GP101: Y | GQ101: Y | GR101: 2 | GS101: 2 | GT101: 0 | GU101: 0 | GV101: 0 | GW101: N | GX101: Y | HB101: N | HC101: 0 | HD101: N | HE101: N | HG101: 0 | HH101: 0 | HI101: 0 | HJ101: 0 | HK101: 0 | HM101: N | HO101: 0 | HP101: 0 | HR101: 0 | HS101: 0 | HT101: 0 | HU101: 0 | HV101: D | HW101: W | HY101: 0 | HZ101: 0 | IA101: 0 | IB101: Y | IC101: N | ID101: N | IE101: N
A102: BP | B102: PIRTRANS | C102: KIK PASCAKOV PIRTRAN | D102: 104 | E102: On B/S,Program,KI-ID | G102: 8 | H102: 240 | I102: IDR | J102: 31 | K102: 0 | L102: 0.36 | M102: 0 | N102: 0.36 | O102: N | P102: 6 | Q102: M | R102: 6 | S102: 0 | T102: Y | U102: Y | V102: N | W102: 0 | X102: I | Y102: 1 | Z102: 0 | AA102: 0 | AB102: 0 | AC102: 0 | AD102: 0 | AE102: 0 | AF102: 7 | AG102: 21 | AH102: 35 | AI102: 49 | AJ102: 63 | AK102: 77 | AL102: 0 | AM102: 0 | AN102: 0 | AO102: Y | AP102: R | AQ102: 0 | AR102: 0 | AS102: 1 | AT102: 0 | AU102: Y | BC102: 0 | BD102: 0 | BE102: 0 | BF102: 0 | BG102: 0 | BH102: 0 | BI102: N | BJ102: N | BK102: N | BL102: N | BM102: N | BN102: N | BU102: 0 | BV102: 0 | BW102: 0 | BX102: 0 | BY102: 0 | BZ102: 0 | CA102: P | CB102: N | CC102: N | CD102: N | CE102: N | CF102: N | CG102: N | CH102: N | CI102: 0 | CJ102: N | CL102: 0 | CM102: N | CN102: 0 | CO102: Y | CP102: N | CQ102: A | CR102: N | CT102: Y | CU102: 4 | CV102: N | CW102: N | CY102: N | DA102: Y | DC102: 0 | DD102: O | DG102: N | DH102: N | DI102: N | DJ102: N | DK102: N | DP102: 0 | DQ102: 0 | DR102: 90 | DS102: 90 | DT102: 0 | DU102: 0 | DV102: N | DW102: P | DX102: N | DZ102: N | EC102: D | ED102: 2 | EE102: R | EF102: 100 | EG102: N | EH102: N | EI102: N | EJ102: Z | EK102: N | EL102: 2 | EM102: N | EO102: 0 | EP102: P | EQ102: N | ER102: N | ES102: 0 | EV102: Y | EW102: 0 | EX102: N | EY102: N | EZ102: N | FA102: N | FB102: Y | FC102: N | FD102: B | FE102: N | FF102: N | FG102: N | FH102: N | FI102: N | FJ102: N | FK102: N | FL102: N | FM102: 0 | FN102: N | FO102: N | FP102: N | FQ102: N | FR102: 0 | FS102: 0 | FT102: N | FV102: 0 | FY102: N | FZ102: N | GA102: 1 | GB102: M | GC102: N | GD102: N | GE102: N | GF102: 0 | GH102: N | GI102: N | GJ102: N | GK102: Y | GL102: P | GM102: 0 | GN102: 0 | GO102: Y | GP102: Y | GQ102: Y | GR102: 2 | GS102: 2 | GT102: 0 | GU102: 0 | GV102: 0 | GW102: N | GX102: Y | HB102: N | HC102: 0 | HD102: N | HE102: N | HG102: 0 | HH102: 0 | HI102: 0 | HJ102: 0 | HK102: 0 | HM102: N | HO102: 0 | HP102: 0 | HR102: 0 | HS102: 0 | HT102: 0 | HU102: 0 | HV102: D | HW102: W | HY102: 0 | HZ102: 0 | IA102: 0 | IB102: N | IC102: N | ID102: N | IE102: N
A103: BR | B103: TANNAKIKAN | C103: KREDIT TANI,NAK,IKAN | D103: 104 | E103: On B/S,Program,KI-ID | G103: 8 | H103: 240 | I103: IDR | J103: 31 | K103: 0.06 | L103: 0.36 | M103: 0.06 | N103: 0.36 | O103: N | P103: 1 | Q103: M | R103: 6 | S103: 0 | T103: Y | U103: Y | V103: N | W103: 0 | X103: I | Y103: 1 | Z103: 0 | AA103: 0 | AB103: 0 | AC103: 0 | AD103: 0 | AE103: 0 | AF103: 7 | AG103: 21 | AH103: 35 | AI103: 49 | AJ103: 63 | AK103: 77 | AL103: 0 | AM103: 0 | AN103: 0 | AO103: Y | AP103: R | AQ103: 0 | AR103: 0 | AS103: 1 | AT103: 0 | AU103: Y | BC103: 0 | BD103: 0 | BE103: 0 | BF103: 0 | BG103: 0 | BH103: 0 | BI103: N | BJ103: N | BK103: N | BL103: N | BM103: N | BN103: N | BU103: 0 | BV103: 0 | BW103: 0 | BX103: 0 | BY103: 0 | BZ103: 0 | CA103: P | CB103: N | CC103: N | CD103: N | CE103: N | CF103: N | CG103: N | CH103: N | CI103: 0 | CJ103: N | CL103: 0 | CM103: N | CN103: 0 | CO103: N | CP103: N | CQ103: A | CR103: N | CT103: Y | CU103: 4 | CV103: N | CW103: N | CY103: N | DA103: Y | DC103: 0 | DD103: O | DG103: N | DH103: N | DI103: N | DJ103: N | DK103: N | DP103: 0 | DQ103: 0 | DR103: 90 | DS103: 90 | DT103: 0 | DU103: 0 | DV103: N | DW103: P | DX103: P | DY103: 17 | DZ103: N | EC103: D | ED103: 2 | EE103: R | EF103: 100 | EG103: N | EH103: N | EI103: N | EJ103: Z | EK103: N | EL103: 2 | EM103: N | EO103: 0 | EP103: P | EQ103: N | ER103: N | ES103: 0 | EV103: Y | EW103: 0 | EX103: N | EY103: N | EZ103: N | FA103: N | FB103: Y | FC103: N | FD103: B | FE103: N | FF103: N | FG103: N | FH103: N | FI103: N | FJ103: N | FK103: N | FL103: N | FM103: 0 | FN103: N | FO103: N | FP103: N | FQ103: N | FR103: 0 | FS103: 0 | FT103: N | FV103: 0 | FY103: N | FZ103: N | GA103: 1 | GB103: M | GC103: N | GD103: N | GE103: N | GF103: 0 | GG103: O | GH103: N | GI103: N | GJ103: N | GK103: Y | GL103: P | GM103: 0 | GN103: 0 | GO103: Y | GP103: Y | GQ103: Y | GR103: 2 | GS103: 2 | GT103: 0 | GU103: 0 | GV103: 0 | GW103: N | GX103: Y | HB103: N | HC103: 0 | HD103: N | HE103: N | HG103: 0 | HH103: 0 | HI103: 0 | HJ103: 0 | HK103: 0 | HM103: N | HO103: 0 | HP103: 0 | HR103: 0 | HS103: 0 | HT103: 0 | HU103: 0 | HV103: D | HW103: W | HY103: 0 | HZ103: 0 | IA103: 0 | IB103: Y | IC103: N | ID103: N | IE103: N
